Workbook

Sheet Прайс
A1: ="ПРАЙС PHOENIX СХІДНИЦЯ · "&$B$3&" · "&$U$11&" · Тариф: "&$B$4&" · Пакет: "&$B$5 -> ПРАЙС PHOENIX СХІДНИЦЯ · 0сінь 26 0-10% · 01.10.2026 – 30.11.2026 · Тариф: Rack Rate · Пакет: RO | U1: ТЕХНІЧНІ ДАНІ — НЕ РЕДАГУВАТИ
A3: Активний прайс-лист | B3: 0сінь 26 0-10% | D3: ="Період дії: "&$U$11 -> Період дії: 01.10.2026 – 30.11.2026 | U3: =IFERROR(MATCH($B$3,ПЛ_РЯДОК,0),0) -> 5 | V3: колонка прайс-листа
A4: Тариф (знижка) | B4: Rack Rate | D4: ="Знижка на проживання: "&TEXT($U$5,"0%")&IF($B$5="BBSPA"," — фіксована для пакета BBSPA; обраний тариф не застосовується","") -> Знижка на проживання: 0% | U4: =IFERROR(SUMIFS(ТАРИФИ_ЗНИЖКИ,ТАРИФИ_НАЗВИ,$B$4),0) -> 0 | V4: знижка тарифу
A5: Пакет | B5: RO | D5: =IF($B$5="RO","Лише проживання.",IF($B$5="BB","Проживання + сніданок за кожного гостя.",IF($B$5="BBSPA","Проживання + сніданок і SPA за кожного гостя.",IF($B$5="ROSPA","Проживання + 1 фіксований SPA-візит на обʼєкт.",IF($B$5="ROSPABB","Проживання + сніданки за кількістю гостей + 1 SPA-візит на обʼєкт.",""))))) -> Лише проживання. | U5: =IF($B$5="BBSPA",ЗНИЖКА_BBSPA,$U$4) -> 0 | V5: знижка на проживання
A6: =IF($U$3=0,"⚠ Прайс-лист не обрано або не знайдено — оберіть значення у клітинці B3.",IF($U$13=0,"⚠ У цьому прайс-листі ще не заповнені базові RO-ціни — сітка буде порожньою. Заповніть його блок на листі «Керування прайсом».","Усі ціни — за ніч, за дорослих гостей, у гривні. Дитячі тарифи рахує лист «Калькулятор». Ціна діє за базовою місткістю категорії; кожне додаткове місце додає доплату з «Довідника категорій» × знижку.")) -> Усі ціни — за ніч, за дорослих гостей, у гривні. Дитячі тарифи рахує лист «Калькулятор». Ціна діє за базовою місткістю категорії; кожне додаткове місце додає доплату з «Довідника категорій» × знижку. | U6: =IF($U$3=0,0,IFERROR(INDEX(ПЕРЕМИКАЧІ,IF($B$5="BBSPA",2,1),$U$3),0)) -> 0 | V6: перемикач: пакет
D7: БУДНІ — кількість гостей | M7: ВИХІДНІ — кількість гостей | U7: =IF($U$3=0,0,IFERROR(INDEX(ПЕРЕМИКАЧІ,3,$U$3),0)) -> 0 | V7: перемикач: SPA
A8: Категорія | B8: Назва на Booking | C8: Код | D8: 1 | E8: 2 | F8: 3 | G8: 4 | H8: 5 | I8: 6 | J8: 7 | K8: 8 | M8: 1 | N8: 2 | O8: 3 | P8: 4 | Q8: 5 | R8: 6 | S8: 7 | T8: 8 | U8: =IF(OR($B$5="BB",$B$5="BBSPA",$B$5="ROSPABB"),1,0) -> 0 | V8: потрібен пакет
A9: =IF('Довідник категорій'!B5="","",'Довідник категорій'!B5) -> Classic Chalet | B9: =IF($A9="","",IFERROR(INDEX(ДОВ_BOOKING,MATCH($A9,КАТЕГОРІЇ,0)),"")) -> Шале з 1 спальнею | C9: =IF($A9="","",IFERROR(INDEX(ДОВ_КОД,MATCH($A9,КАТЕГОРІЇ,0)),"")) -> CH-CL | D9: =IF(OR($AF9=0,D$8>$Y9),"",ROUND($W9*(1-$U$5)/ОКРУГЛЕННЯ,0)*ОКРУГЛЕННЯ+MAX(0,D$8-$Z9)*$AA9*(1-$U$5)+D$8*$AB9*(1-$U$5*$U$6)+$AD9*(1-$U$5*$U$7)) -> 4200 | E9: =IF(OR($AF9=0,E$8>$Y9),"",ROUND($W9*(1-$U$5)/ОКРУГЛЕННЯ,0)*ОКРУГЛЕННЯ+MAX(0,E$8-$Z9)*$AA9*(1-$U$5)+E$8*$AB9*(1-$U$5*$U$6)+$AD9*(1-$U$5*$U$7)) -> 4200 | F9: =IF(OR($AF9=0,F$8>$Y9),"",ROUND($W9*(1-$U$5)/ОКРУГЛЕННЯ,0)*ОКРУГЛЕННЯ+MAX(0,F$8-$Z9)*$AA9*(1-$U$5)+F$8*$AB9*(1-$U$5*$U$6)+$AD9*(1-$U$5*$U$7)) -> 5200 | G9: =IF(OR($AF9=0,G$8>$Y9),"",ROUND($W9*(1-$U$5)/ОКРУГЛЕННЯ,0)*ОКРУГЛЕННЯ+MAX(0,G$8-$Z9)*$AA9*(1-$U$5)+G$8*$AB9*(1-$U$5*$U$6)+$AD9*(1-$U$5*$U$7)) | H9: =IF(OR($AF9=0,H$8>$Y9),"",ROUND($W9*(1-$U$5)/ОКРУГЛЕННЯ,0)*ОКРУГЛЕННЯ+MAX(0,H$8-$Z9)*$AA9*(1-$U$5)+H$8*$AB9*(1-$U$5*$U$6)+$AD9*(1-$U$5*$U$7)) | I9: =IF(OR($AF9=0,I$8>$Y9),"",ROUND($W9*(1-$U$5)/ОКРУГЛЕННЯ,0)*ОКРУГЛЕННЯ+MAX(0,I$8-$Z9)*$AA9*(1-$U$5)+I$8*$AB9*(1-$U$5*$U$6)+$AD9*(1-$U$5*$U$7)) | J9: =IF(OR($AF9=0,J$8>$Y9),"",ROUND($W9*(1-$U$5)/ОКРУГЛЕННЯ,0)*ОКРУГЛЕННЯ+MAX(0,J$8-$Z9)*$AA9*(1-$U$5)+J$8*$AB9*(1-$U$5*$U$6)+$AD9*(1-$U$5*$U$7)) | K9: =IF(OR($AF9=0,K$8>$Y9),"",ROUND($W9*(1-$U$5)/ОКРУГЛЕННЯ,0)*ОКРУГЛЕННЯ+MAX(0,K$8-$Z9)*$AA9*(1-$U$5)+K$8*$AB9*(1-$U$5*$U$6)+$AD9*(1-$U$5*$U$7)) | M9: =IF(OR($AG9=0,M$8>$Y9),"",ROUND($X9*(1-$U$5)/ОКРУГЛЕННЯ,0)*ОКРУГЛЕННЯ+MAX(0,M$8-$Z9)*$AA9*(1-$U$5)+M$8*$AC9*(1-$U$5*$U$6)+$AE9*(1-$U$5*$U$7)) -> 4700 | N9: =IF(OR($AG9=0,N$8>$Y9),"",ROUND($X9*(1-$U$5)/ОКРУГЛЕННЯ,0)*ОКРУГЛЕННЯ+MAX(0,N$8-$Z9)*$AA9*(1-$U$5)+N$8*$AC9*(1-$U$5*$U$6)+$AE9*(1-$U$5*$U$7)) -> 4700 | O9: =IF(OR($AG9=0,O$8>$Y9),"",ROUND($X9*(1-$U$5)/ОКРУГЛЕННЯ,0)*ОКРУГЛЕННЯ+MAX(0,O$8-$Z9)*$AA9*(1-$U$5)+O$8*$AC9*(1-$U$5*$U$6)+$AE9*(1-$U$5*$U$7)) -> 5700 | P9: =IF(OR($AG9=0,P$8>$Y9),"",ROUND($X9*(1-$U$5)/ОКРУГЛЕННЯ,0)*ОКРУГЛЕННЯ+MAX(0,P$8-$Z9)*$AA9*(1-$U$5)+P$8*$AC9*(1-$U$5*$U$6)+$AE9*(1-$U$5*$U$7)) | Q9: =IF(OR($AG9=0,Q$8>$Y9),"",ROUND($X9*(1-$U$5)/ОКРУГЛЕННЯ,0)*ОКРУГЛЕННЯ+MAX(0,Q$8-$Z9)*$AA9*(1-$U$5)+Q$8*$AC9*(1-$U$5*$U$6)+$AE9*(1-$U$5*$U$7)) | R9: =IF(OR($AG9=0,R$8>$Y9),"",ROUND($X9*(1-$U$5)/ОКРУГЛЕННЯ,0)*ОКРУГЛЕННЯ+MAX(0,R$8-$Z9)*$AA9*(1-$U$5)+R$8*$AC9*(1-$U$5*$U$6)+$AE9*(1-$U$5*$U$7)) | S9: =IF(OR($AG9=0,S$8>$Y9),"",ROUND($X9*(1-$U$5)/ОКРУГЛЕННЯ,0)*ОКРУГЛЕННЯ+MAX(0,S$8-$Z9)*$AA9*(1-$U$5)+S$8*$AC9*(1-$U$5*$U$6)+$AE9*(1-$U$5*$U$7)) | T9: =IF(OR($AG9=0,T$8>$Y9),"",ROUND($X9*(1-$U$5)/ОКРУГЛЕННЯ,0)*ОКРУГЛЕННЯ+MAX(0,T$8-$Z9)*$AA9*(1-$U$5)+T$8*$AC9*(1-$U$5*$U$6)+$AE9*(1-$U$5*$U$7)) | U9: =IF(OR($B$5="ROSPA",$B$5="ROSPABB"),1,0) -> 0 | V9: потрібен SPA | W9: =IF(OR($U$3=0,$A9=""),0,IFERROR(INDEX(БАЗА_ЦІНИ,MATCH($A9,БАЗА_КАТ,0),$U$3),0)) -> 4200 | X9: =IF(OR($U$3=0,$A9=""),0,IFERROR(INDEX(БАЗА_ЦІНИ,MATCH($A9,БАЗА_КАТ,0),$U$3+1),0)) -> 4700 | Y9: =IF($A9="",0,IFERROR(INDEX(ДОВ_МАКС,MATCH($A9,КАТЕГОРІЇ,0)),0)) -> 3 | Z9: =IF($A9="",0,IFERROR(INDEX(ДОВ_ВКЛ,MATCH($A9,КАТЕГОРІЇ,0)),0)) -> 2 | AA9: =IF($A9="",0,IFERROR(INDEX(ДОВ_ДОПЛ_ДОР,MATCH($A9,КАТЕГОРІЇ,0)),0)) -> 1000 | AB9: =IF(OR($U$3=0,$U$8=0),0,IFERROR(INDEX(ПАКЕТИ_ЦІНИ,MATCH($U$10&"|Будні",ПАКЕТИ_КЛЮЧ,0),$U$3),0)) -> 0 | AC9: =IF(OR($U$3=0,$U$8=0),0,IFERROR(INDEX(ПАКЕТИ_ЦІНИ,MATCH($U$10&"|Вихідні",ПАКЕТИ_КЛЮЧ,0),$U$3),0)) -> 0 | AD9: =IF(OR($U$3=0,$U$9=0,$A9=""),0,IFERROR(INDEX(SPA_ЦІНИ,MATCH(INDEX(ДОВ_SPA,MATCH($A9,КАТЕГОРІЇ,0)),SPA_РІВЕНЬ,0),$U$3),0)) -> 0 | AE9: =IF(OR($U$3=0,$U$9=0,$A9=""),0,IFERROR(INDEX(SPA_ЦІНИ,MATCH(INDEX(ДОВ_SPA,MATCH($A9,КАТЕГОРІЇ,0)),SPA_РІВЕНЬ,0),$U$3+1),0)) -> 0 | AF9: =IF(OR($A9="",W9=0,AND($U$8=1,AB9=0),AND($U$9=1,AD9=0)),0,1) -> 1 | AG9: =IF(OR($A9="",X9=0,AND($U$8=1,AC9=0),AND($U$9=1,AE9=0)),0,1) -> 1
A10: =IF('Довідник категорій'!B6="","",'Довідник категорій'!B6) -> Forest View Chalet | B10: =IF($A10="","",IFERROR(INDEX(ДОВ_BOOKING,MATCH($A10,КАТЕГОРІЇ,0)),"")) -> Вілла Делюкс | C10: =IF($A10="","",IFERROR(INDEX(ДОВ_КОД,MATCH($A10,КАТЕГОРІЇ,0)),"")) -> CH-FV | D10: =IF(OR($AF10=0,D$8>$Y10),"",ROUND($W10*(1-$U$5)/ОКРУГЛЕННЯ,0)*ОКРУГЛЕННЯ+MAX(0,D$8-$Z10)*$AA10*(1-$U$5)+D$8*$AB10*(1-$U$5*$U$6)+$AD10*(1-$U$5*$U$7)) -> 4600 | E10: =IF(OR($AF10=0,E$8>$Y10),"",ROUND($W10*(1-$U$5)/ОКРУГЛЕННЯ,0)*ОКРУГЛЕННЯ+MAX(0,E$8-$Z10)*$AA10*(1-$U$5)+E$8*$AB10*(1-$U$5*$U$6)+$AD10*(1-$U$5*$U$7)) -> 4600 | F10: =IF(OR($AF10=0,F$8>$Y10),"",ROUND($W10*(1-$U$5)/ОКРУГЛЕННЯ,0)*ОКРУГЛЕННЯ+MAX(0,F$8-$Z10)*$AA10*(1-$U$5)+F$8*$AB10*(1-$U$5*$U$6)+$AD10*(1-$U$5*$U$7)) -> 5600 | G10: =IF(OR($AF10=0,G$8>$Y10),"",ROUND($W10*(1-$U$5)/ОКРУГЛЕННЯ,0)*ОКРУГЛЕННЯ+MAX(0,G$8-$Z10)*$AA10*(1-$U$5)+G$8*$AB10*(1-$U$5*$U$6)+$AD10*(1-$U$5*$U$7)) | H10: =IF(OR($AF10=0,H$8>$Y10),"",ROUND($W10*(1-$U$5)/ОКРУГЛЕННЯ,0)*ОКРУГЛЕННЯ+MAX(0,H$8-$Z10)*$AA10*(1-$U$5)+H$8*$AB10*(1-$U$5*$U$6)+$AD10*(1-$U$5*$U$7)) | I10: =IF(OR($AF10=0,I$8>$Y10),"",ROUND($W10*(1-$U$5)/ОКРУГЛЕННЯ,0)*ОКРУГЛЕННЯ+MAX(0,I$8-$Z10)*$AA10*(1-$U$5)+I$8*$AB10*(1-$U$5*$U$6)+$AD10*(1-$U$5*$U$7)) | J10: =IF(OR($AF10=0,J$8>$Y10),"",ROUND($W10*(1-$U$5)/ОКРУГЛЕННЯ,0)*ОКРУГЛЕННЯ+MAX(0,J$8-$Z10)*$AA10*(1-$U$5)+J$8*$AB10*(1-$U$5*$U$6)+$AD10*(1-$U$5*$U$7)) | K10: =IF(OR($AF10=0,K$8>$Y10),"",ROUND($W10*(1-$U$5)/ОКРУГЛЕННЯ,0)*ОКРУГЛЕННЯ+MAX(0,K$8-$Z10)*$AA10*(1-$U$5)+K$8*$AB10*(1-$U$5*$U$6)+$AD10*(1-$U$5*$U$7)) | M10: =IF(OR($AG10=0,M$8>$Y10),"",ROUND($X10*(1-$U$5)/ОКРУГЛЕННЯ,0)*ОКРУГЛЕННЯ+MAX(0,M$8-$Z10)*$AA10*(1-$U$5)+M$8*$AC10*(1-$U$5*$U$6)+$AE10*(1-$U$5*$U$7)) -> 5200 | N10: =IF(OR($AG10=0,N$8>$Y10),"",ROUND($X10*(1-$U$5)/ОКРУГЛЕННЯ,0)*ОКРУГЛЕННЯ+MAX(0,N$8-$Z10)*$AA10*(1-$U$5)+N$8*$AC10*(1-$U$5*$U$6)+$AE10*(1-$U$5*$U$7)) -> 5200 | O10: =IF(OR($AG10=0,O$8>$Y10),"",ROUND($X10*(1-$U$5)/ОКРУГЛЕННЯ,0)*ОКРУГЛЕННЯ+MAX(0,O$8-$Z10)*$AA10*(1-$U$5)+O$8*$AC10*(1-$U$5*$U$6)+$AE10*(1-$U$5*$U$7)) -> 6200 | P10: =IF(OR($AG10=0,P$8>$Y10),"",ROUND($X10*(1-$U$5)/ОКРУГЛЕННЯ,0)*ОКРУГЛЕННЯ+MAX(0,P$8-$Z10)*$AA10*(1-$U$5)+P$8*$AC10*(1-$U$5*$U$6)+$AE10*(1-$U$5*$U$7)) | Q10: =IF(OR($AG10=0,Q$8>$Y10),"",ROUND($X10*(1-$U$5)/ОКРУГЛЕННЯ,0)*ОКРУГЛЕННЯ+MAX(0,Q$8-$Z10)*$AA10*(1-$U$5)+Q$8*$AC10*(1-$U$5*$U$6)+$AE10*(1-$U$5*$U$7)) | R10: =IF(OR($AG10=0,R$8>$Y10),"",ROUND($X10*(1-$U$5)/ОКРУГЛЕННЯ,0)*ОКРУГЛЕННЯ+MAX(0,R$8-$Z10)*$AA10*(1-$U$5)+R$8*$AC10*(1-$U$5*$U$6)+$AE10*(1-$U$5*$U$7)) | S10: =IF(OR($AG10=0,S$8>$Y10),"",ROUND($X10*(1-$U$5)/ОКРУГЛЕННЯ,0)*ОКРУГЛЕННЯ+MAX(0,S$8-$Z10)*$AA10*(1-$U$5)+S$8*$AC10*(1-$U$5*$U$6)+$AE10*(1-$U$5*$U$7)) | T10: =IF(OR($AG10=0,T$8>$Y10),"",ROUND($X10*(1-$U$5)/ОКРУГЛЕННЯ,0)*ОКРУГЛЕННЯ+MAX(0,T$8-$Z10)*$AA10*(1-$U$5)+T$8*$AC10*(1-$U$5*$U$6)+$AE10*(1-$U$5*$U$7)) | U10: =IF($U$8=0,"",IF($B$5="ROSPABB","BB",$B$5)) | V10: ключ пакета | W10: =IF(OR($U$3=0,$A10=""),0,IFERROR(INDEX(БАЗА_ЦІНИ,MATCH($A10,БАЗА_КАТ,0),$U$3),0)) -> 4550 | X10: =IF(OR($U$3=0,$A10=""),0,IFERROR(INDEX(БАЗА_ЦІНИ,MATCH($A10,БАЗА_КАТ,0),$U$3+1),0)) -> 5150 | Y10: =IF($A10="",0,IFERROR(INDEX(ДОВ_МАКС,MATCH($A10,КАТЕГОРІЇ,0)),0)) -> 3 | Z10: =IF($A10="",0,IFERROR(INDEX(ДОВ_ВКЛ,MATCH($A10,КАТЕГОРІЇ,0)),0)) -> 2 | AA10: =IF($A10="",0,IFERROR(INDEX(ДОВ_ДОПЛ_ДОР,MATCH($A10,КАТЕГОРІЇ,0)),0)) -> 1000 | AB10: =IF(OR($U$3=0,$U$8=0),0,IFERROR(INDEX(ПАКЕТИ_ЦІНИ,MATCH($U$10&"|Будні",ПАКЕТИ_КЛЮЧ,0),$U$3),0)) -> 0 | AC10: =IF(OR($U$3=0,$U$8=0),0,IFERROR(INDEX(ПАКЕТИ_ЦІНИ,MATCH($U$10&"|Вихідні",ПАКЕТИ_КЛЮЧ,0),$U$3),0)) -> 0 | AD10: =IF(OR($U$3=0,$U$9=0,$A10=""),0,IFERROR(INDEX(SPA_ЦІНИ,MATCH(INDEX(ДОВ_SPA,MATCH($A10,КАТЕГОРІЇ,0)),SPA_РІВЕНЬ,0),$U$3),0)) -> 0 | AE10: =IF(OR($U$3=0,$U$9=0,$A10=""),0,IFERROR(INDEX(SPA_ЦІНИ,MATCH(INDEX(ДОВ_SPA,MATCH($A10,КАТЕГОРІЇ,0)),SPA_РІВЕНЬ,0),$U$3+1),0)) -> 0 | AF10: =IF(OR($A10="",W10=0,AND($U$8=1,AB10=0),AND($U$9=1,AD10=0)),0,1) -> 1 | AG10: =IF(OR($A10="",X10=0,AND($U$8=1,AC10=0),AND($U$9=1,AE10=0)),0,1) -> 1
A11: =IF('Довідник категорій'!B7="","",'Довідник категорій'!B7) -> Premium Chalet | B11: =IF($A11="","",IFERROR(INDEX(ДОВ_BOOKING,MATCH($A11,КАТЕГОРІЇ,0)),"")) -> Шале з 3 спальнями | C11: =IF($A11="","",IFERROR(INDEX(ДОВ_КОД,MATCH($A11,КАТЕГОРІЇ,0)),"")) -> CH-PR | D11: =IF(OR($AF11=0,D$8>$Y11),"",ROUND($W11*(1-$U$5)/ОКРУГЛЕННЯ,0)*ОКРУГЛЕННЯ+MAX(0,D$8-$Z11)*$AA11*(1-$U$5)+D$8*$AB11*(1-$U$5*$U$6)+$AD11*(1-$U$5*$U$7)) -> 7800 | E11: =IF(OR($AF11=0,E$8>$Y11),"",ROUND($W11*(1-$U$5)/ОКРУГЛЕННЯ,0)*ОКРУГЛЕННЯ+MAX(0,E$8-$Z11)*$AA11*(1-$U$5)+E$8*$AB11*(1-$U$5*$U$6)+$AD11*(1-$U$5*$U$7)) -> 7800 | F11: =IF(OR($AF11=0,F$8>$Y11),"",ROUND($W11*(1-$U$5)/ОКРУГЛЕННЯ,0)*ОКРУГЛЕННЯ+MAX(0,F$8-$Z11)*$AA11*(1-$U$5)+F$8*$AB11*(1-$U$5*$U$6)+$AD11*(1-$U$5*$U$7)) -> 7800 | G11: =IF(OR($AF11=0,G$8>$Y11),"",ROUND($W11*(1-$U$5)/ОКРУГЛЕННЯ,0)*ОКРУГЛЕННЯ+MAX(0,G$8-$Z11)*$AA11*(1-$U$5)+G$8*$AB11*(1-$U$5*$U$6)+$AD11*(1-$U$5*$U$7)) -> 7800 | H11: =IF(OR($AF11=0,H$8>$Y11),"",ROUND($W11*(1-$U$5)/ОКРУГЛЕННЯ,0)*ОКРУГЛЕННЯ+MAX(0,H$8-$Z11)*$AA11*(1-$U$5)+H$8*$AB11*(1-$U$5*$U$6)+$AD11*(1-$U$5*$U$7)) -> 7800 | I11: =IF(OR($AF11=0,I$8>$Y11),"",ROUND($W11*(1-$U$5)/ОКРУГЛЕННЯ,0)*ОКРУГЛЕННЯ+MAX(0,I$8-$Z11)*$AA11*(1-$U$5)+I$8*$AB11*(1-$U$5*$U$6)+$AD11*(1-$U$5*$U$7)) -> 7800 | J11: =IF(OR($AF11=0,J$8>$Y11),"",ROUND($W11*(1-$U$5)/ОКРУГЛЕННЯ,0)*ОКРУГЛЕННЯ+MAX(0,J$8-$Z11)*$AA11*(1-$U$5)+J$8*$AB11*(1-$U$5*$U$6)+$AD11*(1-$U$5*$U$7)) -> 8800 | K11: =IF(OR($AF11=0,K$8>$Y11),"",ROUND($W11*(1-$U$5)/ОКРУГЛЕННЯ,0)*ОКРУГЛЕННЯ+MAX(0,K$8-$Z11)*$AA11*(1-$U$5)+K$8*$AB11*(1-$U$5*$U$6)+$AD11*(1-$U$5*$U$7)) -> 9800 | M11: =IF(OR($AG11=0,M$8>$Y11),"",ROUND($X11*(1-$U$5)/ОКРУГЛЕННЯ,0)*ОКРУГЛЕННЯ+MAX(0,M$8-$Z11)*$AA11*(1-$U$5)+M$8*$AC11*(1-$U$5*$U$6)+$AE11*(1-$U$5*$U$7)) -> 9800 | N11: =IF(OR($AG11=0,N$8>$Y11),"",ROUND($X11*(1-$U$5)/ОКРУГЛЕННЯ,0)*ОКРУГЛЕННЯ+MAX(0,N$8-$Z11)*$AA11*(1-$U$5)+N$8*$AC11*(1-$U$5*$U$6)+$AE11*(1-$U$5*$U$7)) -> 9800 | O11: =IF(OR($AG11=0,O$8>$Y11),"",ROUND($X11*(1-$U$5)/ОКРУГЛЕННЯ,0)*ОКРУГЛЕННЯ+MAX(0,O$8-$Z11)*$AA11*(1-$U$5)+O$8*$AC11*(1-$U$5*$U$6)+$AE11*(1-$U$5*$U$7)) -> 9800 | P11: =IF(OR($AG11=0,P$8>$Y11),"",ROUND($X11*(1-$U$5)/ОКРУГЛЕННЯ,0)*ОКРУГЛЕННЯ+MAX(0,P$8-$Z11)*$AA11*(1-$U$5)+P$8*$AC11*(1-$U$5*$U$6)+$AE11*(1-$U$5*$U$7)) -> 9800 | Q11: =IF(OR($AG11=0,Q$8>$Y11),"",ROUND($X11*(1-$U$5)/ОКРУГЛЕННЯ,0)*ОКРУГЛЕННЯ+MAX(0,Q$8-$Z11)*$AA11*(1-$U$5)+Q$8*$AC11*(1-$U$5*$U$6)+$AE11*(1-$U$5*$U$7)) -> 9800 | R11: =IF(OR($AG11=0,R$8>$Y11),"",ROUND($X11*(1-$U$5)/ОКРУГЛЕННЯ,0)*ОКРУГЛЕННЯ+MAX(0,R$8-$Z11)*$AA11*(1-$U$5)+R$8*$AC11*(1-$U$5*$U$6)+$AE11*(1-$U$5*$U$7)) -> 9800 | S11: =IF(OR($AG11=0,S$8>$Y11),"",ROUND($X11*(1-$U$5)/ОКРУГЛЕННЯ,0)*ОКРУГЛЕННЯ+MAX(0,S$8-$Z11)*$AA11*(1-$U$5)+S$8*$AC11*(1-$U$5*$U$6)+$AE11*(1-$U$5*$U$7)) -> 10800 | T11: =IF(OR($AG11=0,T$8>$Y11),"",ROUND($X11*(1-$U$5)/ОКРУГЛЕННЯ,0)*ОКРУГЛЕННЯ+MAX(0,T$8-$Z11)*$AA11*(1-$U$5)+T$8*$AC11*(1-$U$5*$U$6)+$AE11*(1-$U$5*$U$7)) -> 11800 | U11: =IF($U$12=0,"період не заданий",IFERROR(IF(OR(INDEX(ПЛ_ДАТА_З,$U$12)="",INDEX(ПЛ_ДАТА_ПО,$U$12)=""),"період не заданий",TEXT(DAY(INDEX(ПЛ_ДАТА_З,$U$12)),"00")&"."&TEXT(MONTH(INDEX(ПЛ_ДАТА_З,$U$12)),"00")&"."&YEAR(INDEX(ПЛ_ДАТА_З,$U$12))&" – "&TEXT(DAY(INDEX(ПЛ_ДАТА_ПО,$U$12)),"00")&"."&TEXT(MONTH(INDEX(ПЛ_ДАТА_ПО,$U$12)),"00")&"."&YEAR(INDEX(ПЛ_ДАТА_ПО,$U$12))),"період не заданий")) -> 01.10.2026 – 30.11.2026 | V11: період (текст) | W11: =IF(OR($U$3=0,$A11=""),0,IFERROR(INDEX(БАЗА_ЦІНИ,MATCH($A11,БАЗА_КАТ,0),$U$3),0)) -> 7770 | X11: =IF(OR($U$3=0,$A11=""),0,IFERROR(INDEX(БАЗА_ЦІНИ,MATCH($A11,БАЗА_КАТ,0),$U$3+1),0)) -> 9770 | Y11: =IF($A11="",0,IFERROR(INDEX(ДОВ_МАКС,MATCH($A11,КАТЕГОРІЇ,0)),0)) -> 8 | Z11: =IF($A11="",0,IFERROR(INDEX(ДОВ_ВКЛ,MATCH($A11,КАТЕГОРІЇ,0)),0)) -> 6 | AA11: =IF($A11="",0,IFERROR(INDEX(ДОВ_ДОПЛ_ДОР,MATCH($A11,КАТЕГОРІЇ,0)),0)) -> 1000 | AB11: =IF(OR($U$3=0,$U$8=0),0,IFERROR(INDEX(ПАКЕТИ_ЦІНИ,MATCH($U$10&"|Будні",ПАКЕТИ_КЛЮЧ,0),$U$3),0)) -> 0 | AC11: =IF(OR($U$3=0,$U$8=0),0,IFERROR(INDEX(ПАКЕТИ_ЦІНИ,MATCH($U$10&"|Вихідні",ПАКЕТИ_КЛЮЧ,0),$U$3),0)) -> 0 | AD11: =IF(OR($U$3=0,$U$9=0,$A11=""),0,IFERROR(INDEX(SPA_ЦІНИ,MATCH(INDEX(ДОВ_SPA,MATCH($A11,КАТЕГОРІЇ,0)),SPA_РІВЕНЬ,0),$U$3),0)) -> 0 | AE11: =IF(OR($U$3=0,$U$9=0,$A11=""),0,IFERROR(INDEX(SPA_ЦІНИ,MATCH(INDEX(ДОВ_SPA,MATCH($A11,КАТЕГОРІЇ,0)),SPA_РІВЕНЬ,0),$U$3+1),0)) -> 0 | AF11: =IF(OR($A11="",W11=0,AND($U$8=1,AB11=0),AND($U$9=1,AD11=0)),0,1) -> 1 | AG11: =IF(OR($A11="",X11=0,AND($U$8=1,AC11=0),AND($U$9=1,AE11=0)),0,1) -> 1
A12: =IF('Довідник категорій'!B8="","",'Довідник категорій'!B8) | B12: =IF($A12="","",IFERROR(INDEX(ДОВ_BOOKING,MATCH($A12,КАТЕГОРІЇ,0)),"")) | C12: =IF($A12="","",IFERROR(INDEX(ДОВ_КОД,MATCH($A12,КАТЕГОРІЇ,0)),"")) | D12: =IF(OR($AF12=0,D$8>$Y12),"",ROUND($W12*(1-$U$5)/ОКРУГЛЕННЯ,0)*ОКРУГЛЕННЯ+MAX(0,D$8-$Z12)*$AA12*(1-$U$5)+D$8*$AB12*(1-$U$5*$U$6)+$AD12*(1-$U$5*$U$7)) | E12: =IF(OR($AF12=0,E$8>$Y12),"",ROUND($W12*(1-$U$5)/ОКРУГЛЕННЯ,0)*ОКРУГЛЕННЯ+MAX(0,E$8-$Z12)*$AA12*(1-$U$5)+E$8*$AB12*(1-$U$5*$U$6)+$AD12*(1-$U$5*$U$7)) | F12: =IF(OR($AF12=0,F$8>$Y12),"",ROUND($W12*(1-$U$5)/ОКРУГЛЕННЯ,0)*ОКРУГЛЕННЯ+MAX(0,F$8-$Z12)*$AA12*(1-$U$5)+F$8*$AB12*(1-$U$5*$U$6)+$AD12*(1-$U$5*$U$7)) | G12: =IF(OR($AF12=0,G$8>$Y12),"",ROUND($W12*(1-$U$5)/ОКРУГЛЕННЯ,0)*ОКРУГЛЕННЯ+MAX(0,G$8-$Z12)*$AA12*(1-$U$5)+G$8*$AB12*(1-$U$5*$U$6)+$AD12*(1-$U$5*$U$7)) | H12: =IF(OR($AF12=0,H$8>$Y12),"",ROUND($W12*(1-$U$5)/ОКРУГЛЕННЯ,0)*ОКРУГЛЕННЯ+MAX(0,H$8-$Z12)*$AA12*(1-$U$5)+H$8*$AB12*(1-$U$5*$U$6)+$AD12*(1-$U$5*$U$7)) | I12: =IF(OR($AF12=0,I$8>$Y12),"",ROUND($W12*(1-$U$5)/ОКРУГЛЕННЯ,0)*ОКРУГЛЕННЯ+MAX(0,I$8-$Z12)*$AA12*(1-$U$5)+I$8*$AB12*(1-$U$5*$U$6)+$AD12*(1-$U$5*$U$7)) | J12: =IF(OR($AF12=0,J$8>$Y12),"",ROUND($W12*(1-$U$5)/ОКРУГЛЕННЯ,0)*ОКРУГЛЕННЯ+MAX(0,J$8-$Z12)*$AA12*(1-$U$5)+J$8*$AB12*(1-$U$5*$U$6)+$AD12*(1-$U$5*$U$7)) | K12: =IF(OR($AF12=0,K$8>$Y12),"",ROUND($W12*(1-$U$5)/ОКРУГЛЕННЯ,0)*ОКРУГЛЕННЯ+MAX(0,K$8-$Z12)*$AA12*(1-$U$5)+K$8*$AB12*(1-$U$5*$U$6)+$AD12*(1-$U$5*$U$7)) | M12: =IF(OR($AG12=0,M$8>$Y12),"",ROUND($X12*(1-$U$5)/ОКРУГЛЕННЯ,0)*ОКРУГЛЕННЯ+MAX(0,M$8-$Z12)*$AA12*(1-$U$5)+M$8*$AC12*(1-$U$5*$U$6)+$AE12*(1-$U$5*$U$7)) | N12: =IF(OR($AG12=0,N$8>$Y12),"",ROUND($X12*(1-$U$5)/ОКРУГЛЕННЯ,0)*ОКРУГЛЕННЯ+MAX(0,N$8-$Z12)*$AA12*(1-$U$5)+N$8*$AC12*(1-$U$5*$U$6)+$AE12*(1-$U$5*$U$7)) | O12: =IF(OR($AG12=0,O$8>$Y12),"",ROUND($X12*(1-$U$5)/ОКРУГЛЕННЯ,0)*ОКРУГЛЕННЯ+MAX(0,O$8-$Z12)*$AA12*(1-$U$5)+O$8*$AC12*(1-$U$5*$U$6)+$AE12*(1-$U$5*$U$7)) | P12: =IF(OR($AG12=0,P$8>$Y12),"",ROUND($X12*(1-$U$5)/ОКРУГЛЕННЯ,0)*ОКРУГЛЕННЯ+MAX(0,P$8-$Z12)*$AA12*(1-$U$5)+P$8*$AC12*(1-$U$5*$U$6)+$AE12*(1-$U$5*$U$7)) | Q12: =IF(OR($AG12=0,Q$8>$Y12),"",ROUND($X12*(1-$U$5)/ОКРУГЛЕННЯ,0)*ОКРУГЛЕННЯ+MAX(0,Q$8-$Z12)*$AA12*(1-$U$5)+Q$8*$AC12*(1-$U$5*$U$6)+$AE12*(1-$U$5*$U$7)) | R12: =IF(OR($AG12=0,R$8>$Y12),"",ROUND($X12*(1-$U$5)/ОКРУГЛЕННЯ,0)*ОКРУГЛЕННЯ+MAX(0,R$8-$Z12)*$AA12*(1-$U$5)+R$8*$AC12*(1-$U$5*$U$6)+$AE12*(1-$U$5*$U$7)) | S12: =IF(OR($AG12=0,S$8>$Y12),"",ROUND($X12*(1-$U$5)/ОКРУГЛЕННЯ,0)*ОКРУГЛЕННЯ+MAX(0,S$8-$Z12)*$AA12*(1-$U$5)+S$8*$AC12*(1-$U$5*$U$6)+$AE12*(1-$U$5*$U$7)) | T12: =IF(OR($AG12=0,T$8>$Y12),"",ROUND($X12*(1-$U$5)/ОКРУГЛЕННЯ,0)*ОКРУГЛЕННЯ+MAX(0,T$8-$Z12)*$AA12*(1-$U$5)+T$8*$AC12*(1-$U$5*$U$6)+$AE12*(1-$U$5*$U$7)) | U12: =IFERROR(MATCH($B$3,ПРАЙС_ЛИСТИ,0),0) -> 3 | V12: рядок прайс-листа | W12: =IF(OR($U$3=0,$A12=""),0,IFERROR(INDEX(БАЗА_ЦІНИ,MATCH($A12,БАЗА_КАТ,0),$U$3),0)) -> 0 | X12: =IF(OR($U$3=0,$A12=""),0,IFERROR(INDEX(БАЗА_ЦІНИ,MATCH($A12,БАЗА_КАТ,0),$U$3+1),0)) -> 0 | Y12: =IF($A12="",0,IFERROR(INDEX(ДОВ_МАКС,MATCH($A12,КАТЕГОРІЇ,0)),0)) -> 0 | Z12: =IF($A12="",0,IFERROR(INDEX(ДОВ_ВКЛ,MATCH($A12,КАТЕГОРІЇ,0)),0)) -> 0 | AA12: =IF($A12="",0,IFERROR(INDEX(ДОВ_ДОПЛ_ДОР,MATCH($A12,КАТЕГОРІЇ,0)),0)) -> 0 | AB12: =IF(OR($U$3=0,$U$8=0),0,IFERROR(INDEX(ПАКЕТИ_ЦІНИ,MATCH($U$10&"|Будні",ПАКЕТИ_КЛЮЧ,0),$U$3),0)) -> 0 | AC12: =IF(OR($U$3=0,$U$8=0),0,IFERROR(INDEX(ПАКЕТИ_ЦІНИ,MATCH($U$10&"|Вихідні",ПАКЕТИ_КЛЮЧ,0),$U$3),0)) -> 0 | AD12: =IF(OR($U$3=0,$U$9=0,$A12=""),0,IFERROR(INDEX(SPA_ЦІНИ,MATCH(INDEX(ДОВ_SPA,MATCH($A12,КАТЕГОРІЇ,0)),SPA_РІВЕНЬ,0),$U$3),0)) -> 0 | AE12: =IF(OR($U$3=0,$U$9=0,$A12=""),0,IFERROR(INDEX(SPA_ЦІНИ,MATCH(INDEX(ДОВ_SPA,MATCH($A12,КАТЕГОРІЇ,0)),SPA_РІВЕНЬ,0),$U$3+1),0)) -> 0 | AF12: =IF(OR($A12="",W12=0,AND($U$8=1,AB12=0),AND($U$9=1,AD12=0)),0,1) -> 0 | AG12: =IF(OR($A12="",X12=0,AND($U$8=1,AC12=0),AND($U$9=1,AE12=0)),0,1) -> 0
A13: =IF('Довідник категорій'!B9="","",'Довідник категорій'!B9) | B13: =IF($A13="","",IFERROR(INDEX(ДОВ_BOOKING,MATCH($A13,КАТЕГОРІЇ,0)),"")) | C13: =IF($A13="","",IFERROR(INDEX(ДОВ_КОД,MATCH($A13,КАТЕГОРІЇ,0)),"")) | D13: =IF(OR($AF13=0,D$8>$Y13),"",ROUND($W13*(1-$U$5)/ОКРУГЛЕННЯ,0)*ОКРУГЛЕННЯ+MAX(0,D$8-$Z13)*$AA13*(1-$U$5)+D$8*$AB13*(1-$U$5*$U$6)+$AD13*(1-$U$5*$U$7)) | E13: =IF(OR($AF13=0,E$8>$Y13),"",ROUND($W13*(1-$U$5)/ОКРУГЛЕННЯ,0)*ОКРУГЛЕННЯ+MAX(0,E$8-$Z13)*$AA13*(1-$U$5)+E$8*$AB13*(1-$U$5*$U$6)+$AD13*(1-$U$5*$U$7)) | F13: =IF(OR($AF13=0,F$8>$Y13),"",ROUND($W13*(1-$U$5)/ОКРУГЛЕННЯ,0)*ОКРУГЛЕННЯ+MAX(0,F$8-$Z13)*$AA13*(1-$U$5)+F$8*$AB13*(1-$U$5*$U$6)+$AD13*(1-$U$5*$U$7)) | G13: =IF(OR($AF13=0,G$8>$Y13),"",ROUND($W13*(1-$U$5)/ОКРУГЛЕННЯ,0)*ОКРУГЛЕННЯ+MAX(0,G$8-$Z13)*$AA13*(1-$U$5)+G$8*$AB13*(1-$U$5*$U$6)+$AD13*(1-$U$5*$U$7)) | H13: =IF(OR($AF13=0,H$8>$Y13),"",ROUND($W13*(1-$U$5)/ОКРУГЛЕННЯ,0)*ОКРУГЛЕННЯ+MAX(0,H$8-$Z13)*$AA13*(1-$U$5)+H$8*$AB13*(1-$U$5*$U$6)+$AD13*(1-$U$5*$U$7)) | I13: =IF(OR($AF13=0,I$8>$Y13),"",ROUND($W13*(1-$U$5)/ОКРУГЛЕННЯ,0)*ОКРУГЛЕННЯ+MAX(0,I$8-$Z13)*$AA13*(1-$U$5)+I$8*$AB13*(1-$U$5*$U$6)+$AD13*(1-$U$5*$U$7)) | J13: =IF(OR($AF13=0,J$8>$Y13),"",ROUND($W13*(1-$U$5)/ОКРУГЛЕННЯ,0)*ОКРУГЛЕННЯ+MAX(0,J$8-$Z13)*$AA13*(1-$U$5)+J$8*$AB13*(1-$U$5*$U$6)+$AD13*(1-$U$5*$U$7)) | K13: =IF(OR($AF13=0,K$8>$Y13),"",ROUND($W13*(1-$U$5)/ОКРУГЛЕННЯ,0)*ОКРУГЛЕННЯ+MAX(0,K$8-$Z13)*$AA13*(1-$U$5)+K$8*$AB13*(1-$U$5*$U$6)+$AD13*(1-$U$5*$U$7)) | M13: =IF(OR($AG13=0,M$8>$Y13),"",ROUND($X13*(1-$U$5)/ОКРУГЛЕННЯ,0)*ОКРУГЛЕННЯ+MAX(0,M$8-$Z13)*$AA13*(1-$U$5)+M$8*$AC13*(1-$U$5*$U$6)+$AE13*(1-$U$5*$U$7)) | N13: =IF(OR($AG13=0,N$8>$Y13),"",ROUND($X13*(1-$U$5)/ОКРУГЛЕННЯ,0)*ОКРУГЛЕННЯ+MAX(0,N$8-$Z13)*$AA13*(1-$U$5)+N$8*$AC13*(1-$U$5*$U$6)+$AE13*(1-$U$5*$U$7)) | O13: =IF(OR($AG13=0,O$8>$Y13),"",ROUND($X13*(1-$U$5)/ОКРУГЛЕННЯ,0)*ОКРУГЛЕННЯ+MAX(0,O$8-$Z13)*$AA13*(1-$U$5)+O$8*$AC13*(1-$U$5*$U$6)+$AE13*(1-$U$5*$U$7)) | P13: =IF(OR($AG13=0,P$8>$Y13),"",ROUND($X13*(1-$U$5)/ОКРУГЛЕННЯ,0)*ОКРУГЛЕННЯ+MAX(0,P$8-$Z13)*$AA13*(1-$U$5)+P$8*$AC13*(1-$U$5*$U$6)+$AE13*(1-$U$5*$U$7)) | Q13: =IF(OR($AG13=0,Q$8>$Y13),"",ROUND($X13*(1-$U$5)/ОКРУГЛЕННЯ,0)*ОКРУГЛЕННЯ+MAX(0,Q$8-$Z13)*$AA13*(1-$U$5)+Q$8*$AC13*(1-$U$5*$U$6)+$AE13*(1-$U$5*$U$7)) | R13: =IF(OR($AG13=0,R$8>$Y13),"",ROUND($X13*(1-$U$5)/ОКРУГЛЕННЯ,0)*ОКРУГЛЕННЯ+MAX(0,R$8-$Z13)*$AA13*(1-$U$5)+R$8*$AC13*(1-$U$5*$U$6)+$AE13*(1-$U$5*$U$7)) | S13: =IF(OR($AG13=0,S$8>$Y13),"",ROUND($X13*(1-$U$5)/ОКРУГЛЕННЯ,0)*ОКРУГЛЕННЯ+MAX(0,S$8-$Z13)*$AA13*(1-$U$5)+S$8*$AC13*(1-$U$5*$U$6)+$AE13*(1-$U$5*$U$7)) | T13: =IF(OR($AG13=0,T$8>$Y13),"",ROUND($X13*(1-$U$5)/ОКРУГЛЕННЯ,0)*ОКРУГЛЕННЯ+MAX(0,T$8-$Z13)*$AA13*(1-$U$5)+T$8*$AC13*(1-$U$5*$U$6)+$AE13*(1-$U$5*$U$7)) | U13: =IF($U$3=0,0,SUMPRODUCT(--(INDEX(БАЗА_ЦІНИ,0,$U$3)<>""))) -> 3 | V13: заповнених баз | W13: =IF(OR($U$3=0,$A13=""),0,IFERROR(INDEX(БАЗА_ЦІНИ,MATCH($A13,БАЗА_КАТ,0),$U$3),0)) -> 0 | X13: =IF(OR($U$3=0,$A13=""),0,IFERROR(INDEX(БАЗА_ЦІНИ,MATCH($A13,БАЗА_КАТ,0),$U$3+1),0)) -> 0 | Y13: =IF($A13="",0,IFERROR(INDEX(ДОВ_МАКС,MATCH($A13,КАТЕГОРІЇ,0)),0)) -> 0 | Z13: =IF($A13="",0,IFERROR(INDEX(ДОВ_ВКЛ,MATCH($A13,КАТЕГОРІЇ,0)),0)) -> 0 | AA13: =IF($A13="",0,IFERROR(INDEX(ДОВ_ДОПЛ_ДОР,MATCH($A13,КАТЕГОРІЇ,0)),0)) -> 0 | AB13: =IF(OR($U$3=0,$U$8=0),0,IFERROR(INDEX(ПАКЕТИ_ЦІНИ,MATCH($U$10&"|Будні",ПАКЕТИ_КЛЮЧ,0),$U$3),0)) -> 0 | AC13: =IF(OR($U$3=0,$U$8=0),0,IFERROR(INDEX(ПАКЕТИ_ЦІНИ,MATCH($U$10&"|Вихідні",ПАКЕТИ_КЛЮЧ,0),$U$3),0)) -> 0 | AD13: =IF(OR($U$3=0,$U$9=0,$A13=""),0,IFERROR(INDEX(SPA_ЦІНИ,MATCH(INDEX(ДОВ_SPA,MATCH($A13,КАТЕГОРІЇ,0)),SPA_РІВЕНЬ,0),$U$3),0)) -> 0 | AE13: =IF(OR($U$3=0,$U$9=0,$A13=""),0,IFERROR(INDEX(SPA_ЦІНИ,MATCH(INDEX(ДОВ_SPA,MATCH($A13,КАТЕГОРІЇ,0)),SPA_РІВЕНЬ,0),$U$3+1),0)) -> 0 | AF13: =IF(OR($A13="",W13=0,AND($U$8=1,AB13=0),AND($U$9=1,AD13=0)),0,1) -> 0 | AG13: =IF(OR($A13="",X13=0,AND($U$8=1,AC13=0),AND($U$9=1,AE13=0)),0,1) -> 0
A14: =IF('Довідник категорій'!B10="","",'Довідник категорій'!B10) | B14: =IF($A14="","",IFERROR(INDEX(ДОВ_BOOKING,MATCH($A14,КАТЕГОРІЇ,0)),"")) | C14: =IF($A14="","",IFERROR(INDEX(ДОВ_КОД,MATCH($A14,КАТЕГОРІЇ,0)),"")) | D14: =IF(OR($AF14=0,D$8>$Y14),"",ROUND($W14*(1-$U$5)/ОКРУГЛЕННЯ,0)*ОКРУГЛЕННЯ+MAX(0,D$8-$Z14)*$AA14*(1-$U$5)+D$8*$AB14*(1-$U$5*$U$6)+$AD14*(1-$U$5*$U$7)) | E14: =IF(OR($AF14=0,E$8>$Y14),"",ROUND($W14*(1-$U$5)/ОКРУГЛЕННЯ,0)*ОКРУГЛЕННЯ+MAX(0,E$8-$Z14)*$AA14*(1-$U$5)+E$8*$AB14*(1-$U$5*$U$6)+$AD14*(1-$U$5*$U$7)) | F14: =IF(OR($AF14=0,F$8>$Y14),"",ROUND($W14*(1-$U$5)/ОКРУГЛЕННЯ,0)*ОКРУГЛЕННЯ+MAX(0,F$8-$Z14)*$AA14*(1-$U$5)+F$8*$AB14*(1-$U$5*$U$6)+$AD14*(1-$U$5*$U$7)) | G14: =IF(OR($AF14=0,G$8>$Y14),"",ROUND($W14*(1-$U$5)/ОКРУГЛЕННЯ,0)*ОКРУГЛЕННЯ+MAX(0,G$8-$Z14)*$AA14*(1-$U$5)+G$8*$AB14*(1-$U$5*$U$6)+$AD14*(1-$U$5*$U$7)) | H14: =IF(OR($AF14=0,H$8>$Y14),"",ROUND($W14*(1-$U$5)/ОКРУГЛЕННЯ,0)*ОКРУГЛЕННЯ+MAX(0,H$8-$Z14)*$AA14*(1-$U$5)+H$8*$AB14*(1-$U$5*$U$6)+$AD14*(1-$U$5*$U$7)) | I14: =IF(OR($AF14=0,I$8>$Y14),"",ROUND($W14*(1-$U$5)/ОКРУГЛЕННЯ,0)*ОКРУГЛЕННЯ+MAX(0,I$8-$Z14)*$AA14*(1-$U$5)+I$8*$AB14*(1-$U$5*$U$6)+$AD14*(1-$U$5*$U$7)) | J14: =IF(OR($AF14=0,J$8>$Y14),"",ROUND($W14*(1-$U$5)/ОКРУГЛЕННЯ,0)*ОКРУГЛЕННЯ+MAX(0,J$8-$Z14)*$AA14*(1-$U$5)+J$8*$AB14*(1-$U$5*$U$6)+$AD14*(1-$U$5*$U$7)) | K14: =IF(OR($AF14=0,K$8>$Y14),"",ROUND($W14*(1-$U$5)/ОКРУГЛЕННЯ,0)*ОКРУГЛЕННЯ+MAX(0,K$8-$Z14)*$AA14*(1-$U$5)+K$8*$AB14*(1-$U$5*$U$6)+$AD14*(1-$U$5*$U$7)) | M14: =IF(OR($AG14=0,M$8>$Y14),"",ROUND($X14*(1-$U$5)/ОКРУГЛЕННЯ,0)*ОКРУГЛЕННЯ+MAX(0,M$8-$Z14)*$AA14*(1-$U$5)+M$8*$AC14*(1-$U$5*$U$6)+$AE14*(1-$U$5*$U$7)) | N14: =IF(OR($AG14=0,N$8>$Y14),"",ROUND($X14*(1-$U$5)/ОКРУГЛЕННЯ,0)*ОКРУГЛЕННЯ+MAX(0,N$8-$Z14)*$AA14*(1-$U$5)+N$8*$AC14*(1-$U$5*$U$6)+$AE14*(1-$U$5*$U$7)) | O14: =IF(OR($AG14=0,O$8>$Y14),"",ROUND($X14*(1-$U$5)/ОКРУГЛЕННЯ,0)*ОКРУГЛЕННЯ+MAX(0,O$8-$Z14)*$AA14*(1-$U$5)+O$8*$AC14*(1-$U$5*$U$6)+$AE14*(1-$U$5*$U$7)) | P14: =IF(OR($AG14=0,P$8>$Y14),"",ROUND($X14*(1-$U$5)/ОКРУГЛЕННЯ,0)*ОКРУГЛЕННЯ+MAX(0,P$8-$Z14)*$AA14*(1-$U$5)+P$8*$AC14*(1-$U$5*$U$6)+$AE14*(1-$U$5*$U$7)) | Q14: =IF(OR($AG14=0,Q$8>$Y14),"",ROUND($X14*(1-$U$5)/ОКРУГЛЕННЯ,0)*ОКРУГЛЕННЯ+MAX(0,Q$8-$Z14)*$AA14*(1-$U$5)+Q$8*$AC14*(1-$U$5*$U$6)+$AE14*(1-$U$5*$U$7)) | R14: =IF(OR($AG14=0,R$8>$Y14),"",ROUND($X14*(1-$U$5)/ОКРУГЛЕННЯ,0)*ОКРУГЛЕННЯ+MAX(0,R$8-$Z14)*$AA14*(1-$U$5)+R$8*$AC14*(1-$U$5*$U$6)+$AE14*(1-$U$5*$U$7)) | S14: =IF(OR($AG14=0,S$8>$Y14),"",ROUND($X14*(1-$U$5)/ОКРУГЛЕННЯ,0)*ОКРУГЛЕННЯ+MAX(0,S$8-$Z14)*$AA14*(1-$U$5)+S$8*$AC14*(1-$U$5*$U$6)+$AE14*(1-$U$5*$U$7)) | T14: =IF(OR($AG14=0,T$8>$Y14),"",ROUND($X14*(1-$U$5)/ОКРУГЛЕННЯ,0)*ОКРУГЛЕННЯ+MAX(0,T$8-$Z14)*$AA14*(1-$U$5)+T$8*$AC14*(1-$U$5*$U$6)+$AE14*(1-$U$5*$U$7)) | W14: =IF(OR($U$3=0,$A14=""),0,IFERROR(INDEX(БАЗА_ЦІНИ,MATCH($A14,БАЗА_КАТ,0),$U$3),0)) -> 0 | X14: =IF(OR($U$3=0,$A14=""),0,IFERROR(INDEX(БАЗА_ЦІНИ,MATCH($A14,БАЗА_КАТ,0),$U$3+1),0)) -> 0 | Y14: =IF($A14="",0,IFERROR(INDEX(ДОВ_МАКС,MATCH($A14,КАТЕГОРІЇ,0)),0)) -> 0 | Z14: =IF($A14="",0,IFERROR(INDEX(ДОВ_ВКЛ,MATCH($A14,КАТЕГОРІЇ,0)),0)) -> 0 | AA14: =IF($A14="",0,IFERROR(INDEX(ДОВ_ДОПЛ_ДОР,MATCH($A14,КАТЕГОРІЇ,0)),0)) -> 0 | AB14: =IF(OR($U$3=0,$U$8=0),0,IFERROR(INDEX(ПАКЕТИ_ЦІНИ,MATCH($U$10&"|Будні",ПАКЕТИ_КЛЮЧ,0),$U$3),0)) -> 0 | AC14: =IF(OR($U$3=0,$U$8=0),0,IFERROR(INDEX(ПАКЕТИ_ЦІНИ,MATCH($U$10&"|Вихідні",ПАКЕТИ_КЛЮЧ,0),$U$3),0)) -> 0 | AD14: =IF(OR($U$3=0,$U$9=0,$A14=""),0,IFERROR(INDEX(SPA_ЦІНИ,MATCH(INDEX(ДОВ_SPA,MATCH($A14,КАТЕГОРІЇ,0)),SPA_РІВЕНЬ,0),$U$3),0)) -> 0 | AE14: =IF(OR($U$3=0,$U$9=0,$A14=""),0,IFERROR(INDEX(SPA_ЦІНИ,MATCH(INDEX(ДОВ_SPA,MATCH($A14,КАТЕГОРІЇ,0)),SPA_РІВЕНЬ,0),$U$3+1),0)) -> 0 | AF14: =IF(OR($A14="",W14=0,AND($U$8=1,AB14=0),AND($U$9=1,AD14=0)),0,1) -> 0 | AG14: =IF(OR($A14="",X14=0,AND($U$8=1,AC14=0),AND($U$9=1,AE14=0)),0,1) -> 0
A15: =IF('Довідник категорій'!B11="","",'Довідник категорій'!B11) | B15: =IF($A15="","",IFERROR(INDEX(ДОВ_BOOKING,MATCH($A15,КАТЕГОРІЇ,0)),"")) | C15: =IF($A15="","",IFERROR(INDEX(ДОВ_КОД,MATCH($A15,КАТЕГОРІЇ,0)),"")) | D15: =IF(OR($AF15=0,D$8>$Y15),"",ROUND($W15*(1-$U$5)/ОКРУГЛЕННЯ,0)*ОКРУГЛЕННЯ+MAX(0,D$8-$Z15)*$AA15*(1-$U$5)+D$8*$AB15*(1-$U$5*$U$6)+$AD15*(1-$U$5*$U$7)) | E15: =IF(OR($AF15=0,E$8>$Y15),"",ROUND($W15*(1-$U$5)/ОКРУГЛЕННЯ,0)*ОКРУГЛЕННЯ+MAX(0,E$8-$Z15)*$AA15*(1-$U$5)+E$8*$AB15*(1-$U$5*$U$6)+$AD15*(1-$U$5*$U$7)) | F15: =IF(OR($AF15=0,F$8>$Y15),"",ROUND($W15*(1-$U$5)/ОКРУГЛЕННЯ,0)*ОКРУГЛЕННЯ+MAX(0,F$8-$Z15)*$AA15*(1-$U$5)+F$8*$AB15*(1-$U$5*$U$6)+$AD15*(1-$U$5*$U$7)) | G15: =IF(OR($AF15=0,G$8>$Y15),"",ROUND($W15*(1-$U$5)/ОКРУГЛЕННЯ,0)*ОКРУГЛЕННЯ+MAX(0,G$8-$Z15)*$AA15*(1-$U$5)+G$8*$AB15*(1-$U$5*$U$6)+$AD15*(1-$U$5*$U$7)) | H15: =IF(OR($AF15=0,H$8>$Y15),"",ROUND($W15*(1-$U$5)/ОКРУГЛЕННЯ,0)*ОКРУГЛЕННЯ+MAX(0,H$8-$Z15)*$AA15*(1-$U$5)+H$8*$AB15*(1-$U$5*$U$6)+$AD15*(1-$U$5*$U$7)) | I15: =IF(OR($AF15=0,I$8>$Y15),"",ROUND($W15*(1-$U$5)/ОКРУГЛЕННЯ,0)*ОКРУГЛЕННЯ+MAX(0,I$8-$Z15)*$AA15*(1-$U$5)+I$8*$AB15*(1-$U$5*$U$6)+$AD15*(1-$U$5*$U$7)) | J15: =IF(OR($AF15=0,J$8>$Y15),"",ROUND($W15*(1-$U$5)/ОКРУГЛЕННЯ,0)*ОКРУГЛЕННЯ+MAX(0,J$8-$Z15)*$AA15*(1-$U$5)+J$8*$AB15*(1-$U$5*$U$6)+$AD15*(1-$U$5*$U$7)) | K15: =IF(OR($AF15=0,K$8>$Y15),"",ROUND($W15*(1-$U$5)/ОКРУГЛЕННЯ,0)*ОКРУГЛЕННЯ+MAX(0,K$8-$Z15)*$AA15*(1-$U$5)+K$8*$AB15*(1-$U$5*$U$6)+$AD15*(1-$U$5*$U$7)) | M15: =IF(OR($AG15=0,M$8>$Y15),"",ROUND($X15*(1-$U$5)/ОКРУГЛЕННЯ,0)*ОКРУГЛЕННЯ+MAX(0,M$8-$Z15)*$AA15*(1-$U$5)+M$8*$AC15*(1-$U$5*$U$6)+$AE15*(1-$U$5*$U$7)) | N15: =IF(OR($AG15=0,N$8>$Y15),"",ROUND($X15*(1-$U$5)/ОКРУГЛЕННЯ,0)*ОКРУГЛЕННЯ+MAX(0,N$8-$Z15)*$AA15*(1-$U$5)+N$8*$AC15*(1-$U$5*$U$6)+$AE15*(1-$U$5*$U$7)) | O15: =IF(OR($AG15=0,O$8>$Y15),"",ROUND($X15*(1-$U$5)/ОКРУГЛЕННЯ,0)*ОКРУГЛЕННЯ+MAX(0,O$8-$Z15)*$AA15*(1-$U$5)+O$8*$AC15*(1-$U$5*$U$6)+$AE15*(1-$U$5*$U$7)) | P15: =IF(OR($AG15=0,P$8>$Y15),"",ROUND($X15*(1-$U$5)/ОКРУГЛЕННЯ,0)*ОКРУГЛЕННЯ+MAX(0,P$8-$Z15)*$AA15*(1-$U$5)+P$8*$AC15*(1-$U$5*$U$6)+$AE15*(1-$U$5*$U$7)) | Q15: =IF(OR($AG15=0,Q$8>$Y15),"",ROUND($X15*(1-$U$5)/ОКРУГЛЕННЯ,0)*ОКРУГЛЕННЯ+MAX(0,Q$8-$Z15)*$AA15*(1-$U$5)+Q$8*$AC15*(1-$U$5*$U$6)+$AE15*(1-$U$5*$U$7)) | R15: =IF(OR($AG15=0,R$8>$Y15),"",ROUND($X15*(1-$U$5)/ОКРУГЛЕННЯ,0)*ОКРУГЛЕННЯ+MAX(0,R$8-$Z15)*$AA15*(1-$U$5)+R$8*$AC15*(1-$U$5*$U$6)+$AE15*(1-$U$5*$U$7)) | S15: =IF(OR($AG15=0,S$8>$Y15),"",ROUND($X15*(1-$U$5)/ОКРУГЛЕННЯ,0)*ОКРУГЛЕННЯ+MAX(0,S$8-$Z15)*$AA15*(1-$U$5)+S$8*$AC15*(1-$U$5*$U$6)+$AE15*(1-$U$5*$U$7)) | T15: =IF(OR($AG15=0,T$8>$Y15),"",ROUND($X15*(1-$U$5)/ОКРУГЛЕННЯ,0)*ОКРУГЛЕННЯ+MAX(0,T$8-$Z15)*$AA15*(1-$U$5)+T$8*$AC15*(1-$U$5*$U$6)+$AE15*(1-$U$5*$U$7)) | W15: =IF(OR($U$3=0,$A15=""),0,IFERROR(INDEX(БАЗА_ЦІНИ,MATCH($A15,БАЗА_КАТ,0),$U$3),0)) -> 0 | X15: =IF(OR($U$3=0,$A15=""),0,IFERROR(INDEX(БАЗА_ЦІНИ,MATCH($A15,БАЗА_КАТ,0),$U$3+1),0)) -> 0 | Y15: =IF($A15="",0,IFERROR(INDEX(ДОВ_МАКС,MATCH($A15,КАТЕГОРІЇ,0)),0)) -> 0 | Z15: =IF($A15="",0,IFERROR(INDEX(ДОВ_ВКЛ,MATCH($A15,КАТЕГОРІЇ,0)),0)) -> 0 | AA15: =IF($A15="",0,IFERROR(INDEX(ДОВ_ДОПЛ_ДОР,MATCH($A15,КАТЕГОРІЇ,0)),0)) -> 0 | AB15: =IF(OR($U$3=0,$U$8=0),0,IFERROR(INDEX(ПАКЕТИ_ЦІНИ,MATCH($U$10&"|Будні",ПАКЕТИ_КЛЮЧ,0),$U$3),0)) -> 0 | AC15: =IF(OR($U$3=0,$U$8=0),0,IFERROR(INDEX(ПАКЕТИ_ЦІНИ,MATCH($U$10&"|Вихідні",ПАКЕТИ_КЛЮЧ,0),$U$3),0)) -> 0 | AD15: =IF(OR($U$3=0,$U$9=0,$A15=""),0,IFERROR(INDEX(SPA_ЦІНИ,MATCH(INDEX(ДОВ_SPA,MATCH($A15,КАТЕГОРІЇ,0)),SPA_РІВЕНЬ,0),$U$3),0)) -> 0 | AE15: =IF(OR($U$3=0,$U$9=0,$A15=""),0,IFERROR(INDEX(SPA_ЦІНИ,MATCH(INDEX(ДОВ_SPA,MATCH($A15,КАТЕГОРІЇ,0)),SPA_РІВЕНЬ,0),$U$3+1),0)) -> 0 | AF15: =IF(OR($A15="",W15=0,AND($U$8=1,AB15=0),AND($U$9=1,AD15=0)),0,1) -> 0 | AG15: =IF(OR($A15="",X15=0,AND($U$8=1,AC15=0),AND($U$9=1,AE15=0)),0,1) -> 0
A16: =IF('Довідник категорій'!B12="","",'Довідник категорій'!B12) | B16: =IF($A16="","",IFERROR(INDEX(ДОВ_BOOKING,MATCH($A16,КАТЕГОРІЇ,0)),"")) | C16: =IF($A16="","",IFERROR(INDEX(ДОВ_КОД,MATCH($A16,КАТЕГОРІЇ,0)),"")) | D16: =IF(OR($AF16=0,D$8>$Y16),"",ROUND($W16*(1-$U$5)/ОКРУГЛЕННЯ,0)*ОКРУГЛЕННЯ+MAX(0,D$8-$Z16)*$AA16*(1-$U$5)+D$8*$AB16*(1-$U$5*$U$6)+$AD16*(1-$U$5*$U$7)) | E16: =IF(OR($AF16=0,E$8>$Y16),"",ROUND($W16*(1-$U$5)/ОКРУГЛЕННЯ,0)*ОКРУГЛЕННЯ+MAX(0,E$8-$Z16)*$AA16*(1-$U$5)+E$8*$AB16*(1-$U$5*$U$6)+$AD16*(1-$U$5*$U$7)) | F16: =IF(OR($AF16=0,F$8>$Y16),"",ROUND($W16*(1-$U$5)/ОКРУГЛЕННЯ,0)*ОКРУГЛЕННЯ+MAX(0,F$8-$Z16)*$AA16*(1-$U$5)+F$8*$AB16*(1-$U$5*$U$6)+$AD16*(1-$U$5*$U$7)) | G16: =IF(OR($AF16=0,G$8>$Y16),"",ROUND($W16*(1-$U$5)/ОКРУГЛЕННЯ,0)*ОКРУГЛЕННЯ+MAX(0,G$8-$Z16)*$AA16*(1-$U$5)+G$8*$AB16*(1-$U$5*$U$6)+$AD16*(1-$U$5*$U$7)) | H16: =IF(OR($AF16=0,H$8>$Y16),"",ROUND($W16*(1-$U$5)/ОКРУГЛЕННЯ,0)*ОКРУГЛЕННЯ+MAX(0,H$8-$Z16)*$AA16*(1-$U$5)+H$8*$AB16*(1-$U$5*$U$6)+$AD16*(1-$U$5*$U$7)) | I16: =IF(OR($AF16=0,I$8>$Y16),"",ROUND($W16*(1-$U$5)/ОКРУГЛЕННЯ,0)*ОКРУГЛЕННЯ+MAX(0,I$8-$Z16)*$AA16*(1-$U$5)+I$8*$AB16*(1-$U$5*$U$6)+$AD16*(1-$U$5*$U$7)) | J16: =IF(OR($AF16=0,J$8>$Y16),"",ROUND($W16*(1-$U$5)/ОКРУГЛЕННЯ,0)*ОКРУГЛЕННЯ+MAX(0,J$8-$Z16)*$AA16*(1-$U$5)+J$8*$AB16*(1-$U$5*$U$6)+$AD16*(1-$U$5*$U$7)) | K16: =IF(OR($AF16=0,K$8>$Y16),"",ROUND($W16*(1-$U$5)/ОКРУГЛЕННЯ,0)*ОКРУГЛЕННЯ+MAX(0,K$8-$Z16)*$AA16*(1-$U$5)+K$8*$AB16*(1-$U$5*$U$6)+$AD16*(1-$U$5*$U$7)) | M16: =IF(OR($AG16=0,M$8>$Y16),"",ROUND($X16*(1-$U$5)/ОКРУГЛЕННЯ,0)*ОКРУГЛЕННЯ+MAX(0,M$8-$Z16)*$AA16*(1-$U$5)+M$8*$AC16*(1-$U$5*$U$6)+$AE16*(1-$U$5*$U$7)) | N16: =IF(OR($AG16=0,N$8>$Y16),"",ROUND($X16*(1-$U$5)/ОКРУГЛЕННЯ,0)*ОКРУГЛЕННЯ+MAX(0,N$8-$Z16)*$AA16*(1-$U$5)+N$8*$AC16*(1-$U$5*$U$6)+$AE16*(1-$U$5*$U$7)) | O16: =IF(OR($AG16=0,O$8>$Y16),"",ROUND($X16*(1-$U$5)/ОКРУГЛЕННЯ,0)*ОКРУГЛЕННЯ+MAX(0,O$8-$Z16)*$AA16*(1-$U$5)+O$8*$AC16*(1-$U$5*$U$6)+$AE16*(1-$U$5*$U$7)) | P16: =IF(OR($AG16=0,P$8>$Y16),"",ROUND($X16*(1-$U$5)/ОКРУГЛЕННЯ,0)*ОКРУГЛЕННЯ+MAX(0,P$8-$Z16)*$AA16*(1-$U$5)+P$8*$AC16*(1-$U$5*$U$6)+$AE16*(1-$U$5*$U$7)) | Q16: =IF(OR($AG16=0,Q$8>$Y16),"",ROUND($X16*(1-$U$5)/ОКРУГЛЕННЯ,0)*ОКРУГЛЕННЯ+MAX(0,Q$8-$Z16)*$AA16*(1-$U$5)+Q$8*$AC16*(1-$U$5*$U$6)+$AE16*(1-$U$5*$U$7)) | R16: =IF(OR($AG16=0,R$8>$Y16),"",ROUND($X16*(1-$U$5)/ОКРУГЛЕННЯ,0)*ОКРУГЛЕННЯ+MAX(0,R$8-$Z16)*$AA16*(1-$U$5)+R$8*$AC16*(1-$U$5*$U$6)+$AE16*(1-$U$5*$U$7)) | S16: =IF(OR($AG16=0,S$8>$Y16),"",ROUND($X16*(1-$U$5)/ОКРУГЛЕННЯ,0)*ОКРУГЛЕННЯ+MAX(0,S$8-$Z16)*$AA16*(1-$U$5)+S$8*$AC16*(1-$U$5*$U$6)+$AE16*(1-$U$5*$U$7)) | T16: =IF(OR($AG16=0,T$8>$Y16),"",ROUND($X16*(1-$U$5)/ОКРУГЛЕННЯ,0)*ОКРУГЛЕННЯ+MAX(0,T$8-$Z16)*$AA16*(1-$U$5)+T$8*$AC16*(1-$U$5*$U$6)+$AE16*(1-$U$5*$U$7)) | W16: =IF(OR($U$3=0,$A16=""),0,IFERROR(INDEX(БАЗА_ЦІНИ,MATCH($A16,БАЗА_КАТ,0),$U$3),0)) -> 0 | X16: =IF(OR($U$3=0,$A16=""),0,IFERROR(INDEX(БАЗА_ЦІНИ,MATCH($A16,БАЗА_КАТ,0),$U$3+1),0)) -> 0 | Y16: =IF($A16="",0,IFERROR(INDEX(ДОВ_МАКС,MATCH($A16,КАТЕГОРІЇ,0)),0)) -> 0 | Z16: =IF($A16="",0,IFERROR(INDEX(ДОВ_ВКЛ,MATCH($A16,КАТЕГОРІЇ,0)),0)) -> 0 | AA16: =IF($A16="",0,IFERROR(INDEX(ДОВ_ДОПЛ_ДОР,MATCH($A16,КАТЕГОРІЇ,0)),0)) -> 0 | AB16: =IF(OR($U$3=0,$U$8=0),0,IFERROR(INDEX(ПАКЕТИ_ЦІНИ,MATCH($U$10&"|Будні",ПАКЕТИ_КЛЮЧ,0),$U$3),0)) -> 0 | AC16: =IF(OR($U$3=0,$U$8=0),0,IFERROR(INDEX(ПАКЕТИ_ЦІНИ,MATCH($U$10&"|Вихідні",ПАКЕТИ_КЛЮЧ,0),$U$3),0)) -> 0 | AD16: =IF(OR($U$3=0,$U$9=0,$A16=""),0,IFERROR(INDEX(SPA_ЦІНИ,MATCH(INDEX(ДОВ_SPA,MATCH($A16,КАТЕГОРІЇ,0)),SPA_РІВЕНЬ,0),$U$3),0)) -> 0 | AE16: =IF(OR($U$3=0,$U$9=0,$A16=""),0,IFERROR(INDEX(SPA_ЦІНИ,MATCH(INDEX(ДОВ_SPA,MATCH($A16,КАТЕГОРІЇ,0)),SPA_РІВЕНЬ,0),$U$3+1),0)) -> 0 | AF16: =IF(OR($A16="",W16=0,AND($U$8=1,AB16=0),AND($U$9=1,AD16=0)),0,1) -> 0 | AG16: =IF(OR($A16="",X16=0,AND($U$8=1,AC16=0),AND($U$9=1,AE16=0)),0,1) -> 0
A17: =IF('Довідник категорій'!B13="","",'Довідник категорій'!B13) | B17: =IF($A17="","",IFERROR(INDEX(ДОВ_BOOKING,MATCH($A17,КАТЕГОРІЇ,0)),"")) | C17: =IF($A17="","",IFERROR(INDEX(ДОВ_КОД,MATCH($A17,КАТЕГОРІЇ,0)),"")) | D17: =IF(OR($AF17=0,D$8>$Y17),"",ROUND($W17*(1-$U$5)/ОКРУГЛЕННЯ,0)*ОКРУГЛЕННЯ+MAX(0,D$8-$Z17)*$AA17*(1-$U$5)+D$8*$AB17*(1-$U$5*$U$6)+$AD17*(1-$U$5*$U$7)) | E17: =IF(OR($AF17=0,E$8>$Y17),"",ROUND($W17*(1-$U$5)/ОКРУГЛЕННЯ,0)*ОКРУГЛЕННЯ+MAX(0,E$8-$Z17)*$AA17*(1-$U$5)+E$8*$AB17*(1-$U$5*$U$6)+$AD17*(1-$U$5*$U$7)) | F17: =IF(OR($AF17=0,F$8>$Y17),"",ROUND($W17*(1-$U$5)/ОКРУГЛЕННЯ,0)*ОКРУГЛЕННЯ+MAX(0,F$8-$Z17)*$AA17*(1-$U$5)+F$8*$AB17*(1-$U$5*$U$6)+$AD17*(1-$U$5*$U$7)) | G17: =IF(OR($AF17=0,G$8>$Y17),"",ROUND($W17*(1-$U$5)/ОКРУГЛЕННЯ,0)*ОКРУГЛЕННЯ+MAX(0,G$8-$Z17)*$AA17*(1-$U$5)+G$8*$AB17*(1-$U$5*$U$6)+$AD17*(1-$U$5*$U$7)) | H17: =IF(OR($AF17=0,H$8>$Y17),"",ROUND($W17*(1-$U$5)/ОКРУГЛЕННЯ,0)*ОКРУГЛЕННЯ+MAX(0,H$8-$Z17)*$AA17*(1-$U$5)+H$8*$AB17*(1-$U$5*$U$6)+$AD17*(1-$U$5*$U$7)) | I17: =IF(OR($AF17=0,I$8>$Y17),"",ROUND($W17*(1-$U$5)/ОКРУГЛЕННЯ,0)*ОКРУГЛЕННЯ+MAX(0,I$8-$Z17)*$AA17*(1-$U$5)+I$8*$AB17*(1-$U$5*$U$6)+$AD17*(1-$U$5*$U$7)) | J17: =IF(OR($AF17=0,J$8>$Y17),"",ROUND($W17*(1-$U$5)/ОКРУГЛЕННЯ,0)*ОКРУГЛЕННЯ+MAX(0,J$8-$Z17)*$AA17*(1-$U$5)+J$8*$AB17*(1-$U$5*$U$6)+$AD17*(1-$U$5*$U$7)) | K17: =IF(OR($AF17=0,K$8>$Y17),"",ROUND($W17*(1-$U$5)/ОКРУГЛЕННЯ,0)*ОКРУГЛЕННЯ+MAX(0,K$8-$Z17)*$AA17*(1-$U$5)+K$8*$AB17*(1-$U$5*$U$6)+$AD17*(1-$U$5*$U$7)) | M17: =IF(OR($AG17=0,M$8>$Y17),"",ROUND($X17*(1-$U$5)/ОКРУГЛЕННЯ,0)*ОКРУГЛЕННЯ+MAX(0,M$8-$Z17)*$AA17*(1-$U$5)+M$8*$AC17*(1-$U$5*$U$6)+$AE17*(1-$U$5*$U$7)) | N17: =IF(OR($AG17=0,N$8>$Y17),"",ROUND($X17*(1-$U$5)/ОКРУГЛЕННЯ,0)*ОКРУГЛЕННЯ+MAX(0,N$8-$Z17)*$AA17*(1-$U$5)+N$8*$AC17*(1-$U$5*$U$6)+$AE17*(1-$U$5*$U$7)) | O17: =IF(OR($AG17=0,O$8>$Y17),"",ROUND($X17*(1-$U$5)/ОКРУГЛЕННЯ,0)*ОКРУГЛЕННЯ+MAX(0,O$8-$Z17)*$AA17*(1-$U$5)+O$8*$AC17*(1-$U$5*$U$6)+$AE17*(1-$U$5*$U$7)) | P17: =IF(OR($AG17=0,P$8>$Y17),"",ROUND($X17*(1-$U$5)/ОКРУГЛЕННЯ,0)*ОКРУГЛЕННЯ+MAX(0,P$8-$Z17)*$AA17*(1-$U$5)+P$8*$AC17*(1-$U$5*$U$6)+$AE17*(1-$U$5*$U$7)) | Q17: =IF(OR($AG17=0,Q$8>$Y17),"",ROUND($X17*(1-$U$5)/ОКРУГЛЕННЯ,0)*ОКРУГЛЕННЯ+MAX(0,Q$8-$Z17)*$AA17*(1-$U$5)+Q$8*$AC17*(1-$U$5*$U$6)+$AE17*(1-$U$5*$U$7)) | R17: =IF(OR($AG17=0,R$8>$Y17),"",ROUND($X17*(1-$U$5)/ОКРУГЛЕННЯ,0)*ОКРУГЛЕННЯ+MAX(0,R$8-$Z17)*$AA17*(1-$U$5)+R$8*$AC17*(1-$U$5*$U$6)+$AE17*(1-$U$5*$U$7)) | S17: =IF(OR($AG17=0,S$8>$Y17),"",ROUND($X17*(1-$U$5)/ОКРУГЛЕННЯ,0)*ОКРУГЛЕННЯ+MAX(0,S$8-$Z17)*$AA17*(1-$U$5)+S$8*$AC17*(1-$U$5*$U$6)+$AE17*(1-$U$5*$U$7)) | T17: =IF(OR($AG17=0,T$8>$Y17),"",ROUND($X17*(1-$U$5)/ОКРУГЛЕННЯ,0)*ОКРУГЛЕННЯ+MAX(0,T$8-$Z17)*$AA17*(1-$U$5)+T$8*$AC17*(1-$U$5*$U$6)+$AE17*(1-$U$5*$U$7)) | W17: =IF(OR($U$3=0,$A17=""),0,IFERROR(INDEX(БАЗА_ЦІНИ,MATCH($A17,БАЗА_КАТ,0),$U$3),0)) -> 0 | X17: =IF(OR($U$3=0,$A17=""),0,IFERROR(INDEX(БАЗА_ЦІНИ,MATCH($A17,БАЗА_КАТ,0),$U$3+1),0)) -> 0 | Y17: =IF($A17="",0,IFERROR(INDEX(ДОВ_МАКС,MATCH($A17,КАТЕГОРІЇ,0)),0)) -> 0 | Z17: =IF($A17="",0,IFERROR(INDEX(ДОВ_ВКЛ,MATCH($A17,КАТЕГОРІЇ,0)),0)) -> 0 | AA17: =IF($A17="",0,IFERROR(INDEX(ДОВ_ДОПЛ_ДОР,MATCH($A17,КАТЕГОРІЇ,0)),0)) -> 0 | AB17: =IF(OR($U$3=0,$U$8=0),0,IFERROR(INDEX(ПАКЕТИ_ЦІНИ,MATCH($U$10&"|Будні",ПАКЕТИ_КЛЮЧ,0),$U$3),0)) -> 0 | AC17: =IF(OR($U$3=0,$U$8=0),0,IFERROR(INDEX(ПАКЕТИ_ЦІНИ,MATCH($U$10&"|Вихідні",ПАКЕТИ_КЛЮЧ,0),$U$3),0)) -> 0 | AD17: =IF(OR($U$3=0,$U$9=0,$A17=""),0,IFERROR(INDEX(SPA_ЦІНИ,MATCH(INDEX(ДОВ_SPA,MATCH($A17,КАТЕГОРІЇ,0)),SPA_РІВЕНЬ,0),$U$3),0)) -> 0 | AE17: =IF(OR($U$3=0,$U$9=0,$A17=""),0,IFERROR(INDEX(SPA_ЦІНИ,MATCH(INDEX(ДОВ_SPA,MATCH($A17,КАТЕГОРІЇ,0)),SPA_РІВЕНЬ,0),$U$3+1),0)) -> 0 | AF17: =IF(OR($A17="",W17=0,AND($U$8=1,AB17=0),AND($U$9=1,AD17=0)),0,1) -> 0 | AG17: =IF(OR($A17="",X17=0,AND($U$8=1,AC17=0),AND($U$9=1,AE17=0)),0,1) -> 0
A18: =IF('Довідник категорій'!B14="","",'Довідник категорій'!B14) | B18: =IF($A18="","",IFERROR(INDEX(ДОВ_BOOKING,MATCH($A18,КАТЕГОРІЇ,0)),"")) | C18: =IF($A18="","",IFERROR(INDEX(ДОВ_КОД,MATCH($A18,КАТЕГОРІЇ,0)),"")) | D18: =IF(OR($AF18=0,D$8>$Y18),"",ROUND($W18*(1-$U$5)/ОКРУГЛЕННЯ,0)*ОКРУГЛЕННЯ+MAX(0,D$8-$Z18)*$AA18*(1-$U$5)+D$8*$AB18*(1-$U$5*$U$6)+$AD18*(1-$U$5*$U$7)) | E18: =IF(OR($AF18=0,E$8>$Y18),"",ROUND($W18*(1-$U$5)/ОКРУГЛЕННЯ,0)*ОКРУГЛЕННЯ+MAX(0,E$8-$Z18)*$AA18*(1-$U$5)+E$8*$AB18*(1-$U$5*$U$6)+$AD18*(1-$U$5*$U$7)) | F18: =IF(OR($AF18=0,F$8>$Y18),"",ROUND($W18*(1-$U$5)/ОКРУГЛЕННЯ,0)*ОКРУГЛЕННЯ+MAX(0,F$8-$Z18)*$AA18*(1-$U$5)+F$8*$AB18*(1-$U$5*$U$6)+$AD18*(1-$U$5*$U$7)) | G18: =IF(OR($AF18=0,G$8>$Y18),"",ROUND($W18*(1-$U$5)/ОКРУГЛЕННЯ,0)*ОКРУГЛЕННЯ+MAX(0,G$8-$Z18)*$AA18*(1-$U$5)+G$8*$AB18*(1-$U$5*$U$6)+$AD18*(1-$U$5*$U$7)) | H18: =IF(OR($AF18=0,H$8>$Y18),"",ROUND($W18*(1-$U$5)/ОКРУГЛЕННЯ,0)*ОКРУГЛЕННЯ+MAX(0,H$8-$Z18)*$AA18*(1-$U$5)+H$8*$AB18*(1-$U$5*$U$6)+$AD18*(1-$U$5*$U$7)) | I18: =IF(OR($AF18=0,I$8>$Y18),"",ROUND($W18*(1-$U$5)/ОКРУГЛЕННЯ,0)*ОКРУГЛЕННЯ+MAX(0,I$8-$Z18)*$AA18*(1-$U$5)+I$8*$AB18*(1-$U$5*$U$6)+$AD18*(1-$U$5*$U$7)) | J18: =IF(OR($AF18=0,J$8>$Y18),"",ROUND($W18*(1-$U$5)/ОКРУГЛЕННЯ,0)*ОКРУГЛЕННЯ+MAX(0,J$8-$Z18)*$AA18*(1-$U$5)+J$8*$AB18*(1-$U$5*$U$6)+$AD18*(1-$U$5*$U$7)) | K18: =IF(OR($AF18=0,K$8>$Y18),"",ROUND($W18*(1-$U$5)/ОКРУГЛЕННЯ,0)*ОКРУГЛЕННЯ+MAX(0,K$8-$Z18)*$AA18*(1-$U$5)+K$8*$AB18*(1-$U$5*$U$6)+$AD18*(1-$U$5*$U$7)) | M18: =IF(OR($AG18=0,M$8>$Y18),"",ROUND($X18*(1-$U$5)/ОКРУГЛЕННЯ,0)*ОКРУГЛЕННЯ+MAX(0,M$8-$Z18)*$AA18*(1-$U$5)+M$8*$AC18*(1-$U$5*$U$6)+$AE18*(1-$U$5*$U$7)) | N18: =IF(OR($AG18=0,N$8>$Y18),"",ROUND($X18*(1-$U$5)/ОКРУГЛЕННЯ,0)*ОКРУГЛЕННЯ+MAX(0,N$8-$Z18)*$AA18*(1-$U$5)+N$8*$AC18*(1-$U$5*$U$6)+$AE18*(1-$U$5*$U$7)) | O18: =IF(OR($AG18=0,O$8>$Y18),"",ROUND($X18*(1-$U$5)/ОКРУГЛЕННЯ,0)*ОКРУГЛЕННЯ+MAX(0,O$8-$Z18)*$AA18*(1-$U$5)+O$8*$AC18*(1-$U$5*$U$6)+$AE18*(1-$U$5*$U$7)) | P18: =IF(OR($AG18=0,P$8>$Y18),"",ROUND($X18*(1-$U$5)/ОКРУГЛЕННЯ,0)*ОКРУГЛЕННЯ+MAX(0,P$8-$Z18)*$AA18*(1-$U$5)+P$8*$AC18*(1-$U$5*$U$6)+$AE18*(1-$U$5*$U$7)) | Q18: =IF(OR($AG18=0,Q$8>$Y18),"",ROUND($X18*(1-$U$5)/ОКРУГЛЕННЯ,0)*ОКРУГЛЕННЯ+MAX(0,Q$8-$Z18)*$AA18*(1-$U$5)+Q$8*$AC18*(1-$U$5*$U$6)+$AE18*(1-$U$5*$U$7)) | R18: =IF(OR($AG18=0,R$8>$Y18),"",ROUND($X18*(1-$U$5)/ОКРУГЛЕННЯ,0)*ОКРУГЛЕННЯ+MAX(0,R$8-$Z18)*$AA18*(1-$U$5)+R$8*$AC18*(1-$U$5*$U$6)+$AE18*(1-$U$5*$U$7)) | S18: =IF(OR($AG18=0,S$8>$Y18),"",ROUND($X18*(1-$U$5)/ОКРУГЛЕННЯ,0)*ОКРУГЛЕННЯ+MAX(0,S$8-$Z18)*$AA18*(1-$U$5)+S$8*$AC18*(1-$U$5*$U$6)+$AE18*(1-$U$5*$U$7)) | T18: =IF(OR($AG18=0,T$8>$Y18),"",ROUND($X18*(1-$U$5)/ОКРУГЛЕННЯ,0)*ОКРУГЛЕННЯ+MAX(0,T$8-$Z18)*$AA18*(1-$U$5)+T$8*$AC18*(1-$U$5*$U$6)+$AE18*(1-$U$5*$U$7)) | W18: =IF(OR($U$3=0,$A18=""),0,IFERROR(INDEX(БАЗА_ЦІНИ,MATCH($A18,БАЗА_КАТ,0),$U$3),0)) -> 0 | X18: =IF(OR($U$3=0,$A18=""),0,IFERROR(INDEX(БАЗА_ЦІНИ,MATCH($A18,БАЗА_КАТ,0),$U$3+1),0)) -> 0 | Y18: =IF($A18="",0,IFERROR(INDEX(ДОВ_МАКС,MATCH($A18,КАТЕГОРІЇ,0)),0)) -> 0 | Z18: =IF($A18="",0,IFERROR(INDEX(ДОВ_ВКЛ,MATCH($A18,КАТЕГОРІЇ,0)),0)) -> 0 | AA18: =IF($A18="",0,IFERROR(INDEX(ДОВ_ДОПЛ_ДОР,MATCH($A18,КАТЕГОРІЇ,0)),0)) -> 0 | AB18: =IF(OR($U$3=0,$U$8=0),0,IFERROR(INDEX(ПАКЕТИ_ЦІНИ,MATCH($U$10&"|Будні",ПАКЕТИ_КЛЮЧ,0),$U$3),0)) -> 0 | AC18: =IF(OR($U$3=0,$U$8=0),0,IFERROR(INDEX(ПАКЕТИ_ЦІНИ,MATCH($U$10&"|Вихідні",ПАКЕТИ_КЛЮЧ,0),$U$3),0)) -> 0 | AD18: =IF(OR($U$3=0,$U$9=0,$A18=""),0,IFERROR(INDEX(SPA_ЦІНИ,MATCH(INDEX(ДОВ_SPA,MATCH($A18,КАТЕГОРІЇ,0)),SPA_РІВЕНЬ,0),$U$3),0)) -> 0 | AE18: =IF(OR($U$3=0,$U$9=0,$A18=""),0,IFERROR(INDEX(SPA_ЦІНИ,MATCH(INDEX(ДОВ_SPA,MATCH($A18,КАТЕГОРІЇ,0)),SPA_РІВЕНЬ,0),$U$3+1),0)) -> 0 | AF18: =IF(OR($A18="",W18=0,AND($U$8=1,AB18=0),AND($U$9=1,AD18=0)),0,1) -> 0 | AG18: =IF(OR($A18="",X18=0,AND($U$8=1,AC18=0),AND($U$9=1,AE18=0)),0,1) -> 0
A19: =IF('Довідник категорій'!B15="","",'Довідник категорій'!B15) | B19: =IF($A19="","",IFERROR(INDEX(ДОВ_BOOKING,MATCH($A19,КАТЕГОРІЇ,0)),"")) | C19: =IF($A19="","",IFERROR(INDEX(ДОВ_КОД,MATCH($A19,КАТЕГОРІЇ,0)),"")) | D19: =IF(OR($AF19=0,D$8>$Y19),"",ROUND($W19*(1-$U$5)/ОКРУГЛЕННЯ,0)*ОКРУГЛЕННЯ+MAX(0,D$8-$Z19)*$AA19*(1-$U$5)+D$8*$AB19*(1-$U$5*$U$6)+$AD19*(1-$U$5*$U$7)) | E19: =IF(OR($AF19=0,E$8>$Y19),"",ROUND($W19*(1-$U$5)/ОКРУГЛЕННЯ,0)*ОКРУГЛЕННЯ+MAX(0,E$8-$Z19)*$AA19*(1-$U$5)+E$8*$AB19*(1-$U$5*$U$6)+$AD19*(1-$U$5*$U$7)) | F19: =IF(OR($AF19=0,F$8>$Y19),"",ROUND($W19*(1-$U$5)/ОКРУГЛЕННЯ,0)*ОКРУГЛЕННЯ+MAX(0,F$8-$Z19)*$AA19*(1-$U$5)+F$8*$AB19*(1-$U$5*$U$6)+$AD19*(1-$U$5*$U$7)) | G19: =IF(OR($AF19=0,G$8>$Y19),"",ROUND($W19*(1-$U$5)/ОКРУГЛЕННЯ,0)*ОКРУГЛЕННЯ+MAX(0,G$8-$Z19)*$AA19*(1-$U$5)+G$8*$AB19*(1-$U$5*$U$6)+$AD19*(1-$U$5*$U$7)) | H19: =IF(OR($AF19=0,H$8>$Y19),"",ROUND($W19*(1-$U$5)/ОКРУГЛЕННЯ,0)*ОКРУГЛЕННЯ+MAX(0,H$8-$Z19)*$AA19*(1-$U$5)+H$8*$AB19*(1-$U$5*$U$6)+$AD19*(1-$U$5*$U$7)) | I19: =IF(OR($AF19=0,I$8>$Y19),"",ROUND($W19*(1-$U$5)/ОКРУГЛЕННЯ,0)*ОКРУГЛЕННЯ+MAX(0,I$8-$Z19)*$AA19*(1-$U$5)+I$8*$AB19*(1-$U$5*$U$6)+$AD19*(1-$U$5*$U$7)) | J19: =IF(OR($AF19=0,J$8>$Y19),"",ROUND($W19*(1-$U$5)/ОКРУГЛЕННЯ,0)*ОКРУГЛЕННЯ+MAX(0,J$8-$Z19)*$AA19*(1-$U$5)+J$8*$AB19*(1-$U$5*$U$6)+$AD19*(1-$U$5*$U$7)) | K19: =IF(OR($AF19=0,K$8>$Y19),"",ROUND($W19*(1-$U$5)/ОКРУГЛЕННЯ,0)*ОКРУГЛЕННЯ+MAX(0,K$8-$Z19)*$AA19*(1-$U$5)+K$8*$AB19*(1-$U$5*$U$6)+$AD19*(1-$U$5*$U$7)) | M19: =IF(OR($AG19=0,M$8>$Y19),"",ROUND($X19*(1-$U$5)/ОКРУГЛЕННЯ,0)*ОКРУГЛЕННЯ+MAX(0,M$8-$Z19)*$AA19*(1-$U$5)+M$8*$AC19*(1-$U$5*$U$6)+$AE19*(1-$U$5*$U$7)) | N19: =IF(OR($AG19=0,N$8>$Y19),"",ROUND($X19*(1-$U$5)/ОКРУГЛЕННЯ,0)*ОКРУГЛЕННЯ+MAX(0,N$8-$Z19)*$AA19*(1-$U$5)+N$8*$AC19*(1-$U$5*$U$6)+$AE19*(1-$U$5*$U$7)) | O19: =IF(OR($AG19=0,O$8>$Y19),"",ROUND($X19*(1-$U$5)/ОКРУГЛЕННЯ,0)*ОКРУГЛЕННЯ+MAX(0,O$8-$Z19)*$AA19*(1-$U$5)+O$8*$AC19*(1-$U$5*$U$6)+$AE19*(1-$U$5*$U$7)) | P19: =IF(OR($AG19=0,P$8>$Y19),"",ROUND($X19*(1-$U$5)/ОКРУГЛЕННЯ,0)*ОКРУГЛЕННЯ+MAX(0,P$8-$Z19)*$AA19*(1-$U$5)+P$8*$AC19*(1-$U$5*$U$6)+$AE19*(1-$U$5*$U$7)) | Q19: =IF(OR($AG19=0,Q$8>$Y19),"",ROUND($X19*(1-$U$5)/ОКРУГЛЕННЯ,0)*ОКРУГЛЕННЯ+MAX(0,Q$8-$Z19)*$AA19*(1-$U$5)+Q$8*$AC19*(1-$U$5*$U$6)+$AE19*(1-$U$5*$U$7)) | R19: =IF(OR($AG19=0,R$8>$Y19),"",ROUND($X19*(1-$U$5)/ОКРУГЛЕННЯ,0)*ОКРУГЛЕННЯ+MAX(0,R$8-$Z19)*$AA19*(1-$U$5)+R$8*$AC19*(1-$U$5*$U$6)+$AE19*(1-$U$5*$U$7)) | S19: =IF(OR($AG19=0,S$8>$Y19),"",ROUND($X19*(1-$U$5)/ОКРУГЛЕННЯ,0)*ОКРУГЛЕННЯ+MAX(0,S$8-$Z19)*$AA19*(1-$U$5)+S$8*$AC19*(1-$U$5*$U$6)+$AE19*(1-$U$5*$U$7)) | T19: =IF(OR($AG19=0,T$8>$Y19),"",ROUND($X19*(1-$U$5)/ОКРУГЛЕННЯ,0)*ОКРУГЛЕННЯ+MAX(0,T$8-$Z19)*$AA19*(1-$U$5)+T$8*$AC19*(1-$U$5*$U$6)+$AE19*(1-$U$5*$U$7)) | W19: =IF(OR($U$3=0,$A19=""),0,IFERROR(INDEX(БАЗА_ЦІНИ,MATCH($A19,БАЗА_КАТ,0),$U$3),0)) -> 0 | X19: =IF(OR($U$3=0,$A19=""),0,IFERROR(INDEX(БАЗА_ЦІНИ,MATCH($A19,БАЗА_КАТ,0),$U$3+1),0)) -> 0 | Y19: =IF($A19="",0,IFERROR(INDEX(ДОВ_МАКС,MATCH($A19,КАТЕГОРІЇ,0)),0)) -> 0 | Z19: =IF($A19="",0,IFERROR(INDEX(ДОВ_ВКЛ,MATCH($A19,КАТЕГОРІЇ,0)),0)) -> 0 | AA19: =IF($A19="",0,IFERROR(INDEX(ДОВ_ДОПЛ_ДОР,MATCH($A19,КАТЕГОРІЇ,0)),0)) -> 0 | AB19: =IF(OR($U$3=0,$U$8=0),0,IFERROR(INDEX(ПАКЕТИ_ЦІНИ,MATCH($U$10&"|Будні",ПАКЕТИ_КЛЮЧ,0),$U$3),0)) -> 0 | AC19: =IF(OR($U$3=0,$U$8=0),0,IFERROR(INDEX(ПАКЕТИ_ЦІНИ,MATCH($U$10&"|Вихідні",ПАКЕТИ_КЛЮЧ,0),$U$3),0)) -> 0 | AD19: =IF(OR($U$3=0,$U$9=0,$A19=""),0,IFERROR(INDEX(SPA_ЦІНИ,MATCH(INDEX(ДОВ_SPA,MATCH($A19,КАТЕГОРІЇ,0)),SPA_РІВЕНЬ,0),$U$3),0)) -> 0 | AE19: =IF(OR($U$3=0,$U$9=0,$A19=""),0,IFERROR(INDEX(SPA_ЦІНИ,MATCH(INDEX(ДОВ_SPA,MATCH($A19,КАТЕГОРІЇ,0)),SPA_РІВЕНЬ,0),$U$3+1),0)) -> 0 | AF19: =IF(OR($A19="",W19=0,AND($U$8=1,AB19=0),AND($U$9=1,AD19=0)),0,1) -> 0 | AG19: =IF(OR($A19="",X19=0,AND($U$8=1,AC19=0),AND($U$9=1,AE19=0)),0,1) -> 0
A20: =IF('Довідник категорій'!B16="","",'Довідник категорій'!B16) | B20: =IF($A20="","",IFERROR(INDEX(ДОВ_BOOKING,MATCH($A20,КАТЕГОРІЇ,0)),"")) | C20: =IF($A20="","",IFERROR(INDEX(ДОВ_КОД,MATCH($A20,КАТЕГОРІЇ,0)),"")) | D20: =IF(OR($AF20=0,D$8>$Y20),"",ROUND($W20*(1-$U$5)/ОКРУГЛЕННЯ,0)*ОКРУГЛЕННЯ+MAX(0,D$8-$Z20)*$AA20*(1-$U$5)+D$8*$AB20*(1-$U$5*$U$6)+$AD20*(1-$U$5*$U$7)) | E20: =IF(OR($AF20=0,E$8>$Y20),"",ROUND($W20*(1-$U$5)/ОКРУГЛЕННЯ,0)*ОКРУГЛЕННЯ+MAX(0,E$8-$Z20)*$AA20*(1-$U$5)+E$8*$AB20*(1-$U$5*$U$6)+$AD20*(1-$U$5*$U$7)) | F20: =IF(OR($AF20=0,F$8>$Y20),"",ROUND($W20*(1-$U$5)/ОКРУГЛЕННЯ,0)*ОКРУГЛЕННЯ+MAX(0,F$8-$Z20)*$AA20*(1-$U$5)+F$8*$AB20*(1-$U$5*$U$6)+$AD20*(1-$U$5*$U$7)) | G20: =IF(OR($AF20=0,G$8>$Y20),"",ROUND($W20*(1-$U$5)/ОКРУГЛЕННЯ,0)*ОКРУГЛЕННЯ+MAX(0,G$8-$Z20)*$AA20*(1-$U$5)+G$8*$AB20*(1-$U$5*$U$6)+$AD20*(1-$U$5*$U$7)) | H20: =IF(OR($AF20=0,H$8>$Y20),"",ROUND($W20*(1-$U$5)/ОКРУГЛЕННЯ,0)*ОКРУГЛЕННЯ+MAX(0,H$8-$Z20)*$AA20*(1-$U$5)+H$8*$AB20*(1-$U$5*$U$6)+$AD20*(1-$U$5*$U$7)) | I20: =IF(OR($AF20=0,I$8>$Y20),"",ROUND($W20*(1-$U$5)/ОКРУГЛЕННЯ,0)*ОКРУГЛЕННЯ+MAX(0,I$8-$Z20)*$AA20*(1-$U$5)+I$8*$AB20*(1-$U$5*$U$6)+$AD20*(1-$U$5*$U$7)) | J20: =IF(OR($AF20=0,J$8>$Y20),"",ROUND($W20*(1-$U$5)/ОКРУГЛЕННЯ,0)*ОКРУГЛЕННЯ+MAX(0,J$8-$Z20)*$AA20*(1-$U$5)+J$8*$AB20*(1-$U$5*$U$6)+$AD20*(1-$U$5*$U$7)) | K20: =IF(OR($AF20=0,K$8>$Y20),"",ROUND($W20*(1-$U$5)/ОКРУГЛЕННЯ,0)*ОКРУГЛЕННЯ+MAX(0,K$8-$Z20)*$AA20*(1-$U$5)+K$8*$AB20*(1-$U$5*$U$6)+$AD20*(1-$U$5*$U$7)) | M20: =IF(OR($AG20=0,M$8>$Y20),"",ROUND($X20*(1-$U$5)/ОКРУГЛЕННЯ,0)*ОКРУГЛЕННЯ+MAX(0,M$8-$Z20)*$AA20*(1-$U$5)+M$8*$AC20*(1-$U$5*$U$6)+$AE20*(1-$U$5*$U$7)) | N20: =IF(OR($AG20=0,N$8>$Y20),"",ROUND($X20*(1-$U$5)/ОКРУГЛЕННЯ,0)*ОКРУГЛЕННЯ+MAX(0,N$8-$Z20)*$AA20*(1-$U$5)+N$8*$AC20*(1-$U$5*$U$6)+$AE20*(1-$U$5*$U$7)) | O20: =IF(OR($AG20=0,O$8>$Y20),"",ROUND($X20*(1-$U$5)/ОКРУГЛЕННЯ,0)*ОКРУГЛЕННЯ+MAX(0,O$8-$Z20)*$AA20*(1-$U$5)+O$8*$AC20*(1-$U$5*$U$6)+$AE20*(1-$U$5*$U$7)) | P20: =IF(OR($AG20=0,P$8>$Y20),"",ROUND($X20*(1-$U$5)/ОКРУГЛЕННЯ,0)*ОКРУГЛЕННЯ+MAX(0,P$8-$Z20)*$AA20*(1-$U$5)+P$8*$AC20*(1-$U$5*$U$6)+$AE20*(1-$U$5*$U$7)) | Q20: =IF(OR($AG20=0,Q$8>$Y20),"",ROUND($X20*(1-$U$5)/ОКРУГЛЕННЯ,0)*ОКРУГЛЕННЯ+MAX(0,Q$8-$Z20)*$AA20*(1-$U$5)+Q$8*$AC20*(1-$U$5*$U$6)+$AE20*(1-$U$5*$U$7)) | R20: =IF(OR($AG20=0,R$8>$Y20),"",ROUND($X20*(1-$U$5)/ОКРУГЛЕННЯ,0)*ОКРУГЛЕННЯ+MAX(0,R$8-$Z20)*$AA20*(1-$U$5)+R$8*$AC20*(1-$U$5*$U$6)+$AE20*(1-$U$5*$U$7)) | S20: =IF(OR($AG20=0,S$8>$Y20),"",ROUND($X20*(1-$U$5)/ОКРУГЛЕННЯ,0)*ОКРУГЛЕННЯ+MAX(0,S$8-$Z20)*$AA20*(1-$U$5)+S$8*$AC20*(1-$U$5*$U$6)+$AE20*(1-$U$5*$U$7)) | T20: =IF(OR($AG20=0,T$8>$Y20),"",ROUND($X20*(1-$U$5)/ОКРУГЛЕННЯ,0)*ОКРУГЛЕННЯ+MAX(0,T$8-$Z20)*$AA20*(1-$U$5)+T$8*$AC20*(1-$U$5*$U$6)+$AE20*(1-$U$5*$U$7)) | W20: =IF(OR($U$3=0,$A20=""),0,IFERROR(INDEX(БАЗА_ЦІНИ,MATCH($A20,БАЗА_КАТ,0),$U$3),0)) -> 0 | X20: =IF(OR($U$3=0,$A20=""),0,IFERROR(INDEX(БАЗА_ЦІНИ,MATCH($A20,БАЗА_КАТ,0),$U$3+1),0)) -> 0 | Y20: =IF($A20="",0,IFERROR(INDEX(ДОВ_МАКС,MATCH($A20,КАТЕГОРІЇ,0)),0)) -> 0 | Z20: =IF($A20="",0,IFERROR(INDEX(ДОВ_ВКЛ,MATCH($A20,КАТЕГОРІЇ,0)),0)) -> 0 | AA20: =IF($A20="",0,IFERROR(INDEX(ДОВ_ДОПЛ_ДОР,MATCH($A20,КАТЕГОРІЇ,0)),0)) -> 0 | AB20: =IF(OR($U$3=0,$U$8=0),0,IFERROR(INDEX(ПАКЕТИ_ЦІНИ,MATCH($U$10&"|Будні",ПАКЕТИ_КЛЮЧ,0),$U$3),0)) -> 0 | AC20: =IF(OR($U$3=0,$U$8=0),0,IFERROR(INDEX(ПАКЕТИ_ЦІНИ,MATCH($U$10&"|Вихідні",ПАКЕТИ_КЛЮЧ,0),$U$3),0)) -> 0 | AD20: =IF(OR($U$3=0,$U$9=0,$A20=""),0,IFERROR(INDEX(SPA_ЦІНИ,MATCH(INDEX(ДОВ_SPA,MATCH($A20,КАТЕГОРІЇ,0)),SPA_РІВЕНЬ,0),$U$3),0)) -> 0 | AE20: =IF(OR($U$3=0,$U$9=0,$A20=""),0,IFERROR(INDEX(SPA_ЦІНИ,MATCH(INDEX(ДОВ_SPA,MATCH($A20,КАТЕГОРІЇ,0)),SPA_РІВЕНЬ,0),$U$3+1),0)) -> 0 | AF20: =IF(OR($A20="",W20=0,AND($U$8=1,AB20=0),AND($U$9=1,AD20=0)),0,1) -> 0 | AG20: =IF(OR($A20="",X20=0,AND($U$8=1,AC20=0),AND($U$9=1,AE20=0)),0,1) -> 0

Sheet Калькулятор
A1: КАЛЬКУЛЯТОР ВАРТОСТІ БРОНЮВАННЯ — PHOENIX СХІДНИЦЯ | U1: ТЕХНІЧНІ ДАНІ — НЕ РЕДАГУВАТИ
A3: Заповнюйте лише жовті клітинки. Рахує тією самою формулою, що й лист «Прайс», але додатково розділяє дорослих і дітей: базову місткість заповнюють спершу дорослі, решта гостей іде як додаткові місця. Поле «Дата заїзду» необовʼязкове — воно лише підказує прайс-лист і тип дня. | U3: =IFERROR(MATCH($B$6,ПЛ_РЯДОК,0),0) -> 5 | V3: колонка прайс-листа
A5: ВХІДНІ ПАРАМЕТРИ | D5: РОЗРАХУНОК
A6: Активний прайс-лист | B6: =Прайс!$B$3 -> 0сінь 26 0-10% | D6: Статус | F6: =IF(OR($B$6="",$B$8="",$U$3=0,F7<F8,F7>F10,F11=0,AND($U$8=1,OR(AND($B$10>0,F18=0),AND($B$11>0,F19=0))),AND($U$9=1,F20=0)),"ПЕРЕВІРТЕ ПАРАМЕТРИ","OK") -> OK
A7: Тариф (знижка) | B7: Rack Rate | D7: Усього гостей | F7: =$B$10+$B$11 -> 2
A8: Категорія | B8: Classic Chalet | D8: Мін. гостей | F8: =IFERROR(INDEX(ДОВ_МІН,MATCH($B$8,КАТЕГОРІЇ,0)),0) -> 2 | U8: =IF(OR($B$12="BB",$B$12="BBSPA",$B$12="ROSPABB"),1,0) -> 0 | V8: потрібен пакет
A9: Тип дня | B9: Будні | D9: Включено у базову ціну | F9: =IFERROR(INDEX(ДОВ_ВКЛ,MATCH($B$8,КАТЕГОРІЇ,0)),0) -> 2 | U9: =IF(OR($B$12="ROSPA",$B$12="ROSPABB"),1,0) -> 0 | V9: потрібен SPA
A10: Дорослих | B10: 2 | D10: Макс. гостей | F10: =IFERROR(INDEX(ДОВ_МАКС,MATCH($B$8,КАТЕГОРІЇ,0)),0) -> 3 | U10: =IF($U$8=0,"",IF($B$12="ROSPABB","BB",$B$12)) | V10: ключ пакета
A11: Дітей | B11: 0 | D11: RO база за типом дня, грн | F11: =IF($U$3=0,0,IFERROR(INDEX(БАЗА_ЦІНИ,MATCH($B$8,БАЗА_КАТ,0),$U$3+IF($B$9="Вихідні",1,0)),0)) -> 4200
A12: Пакет | B12: RO | D12: Додаткових дорослих | F12: =MAX(0,$B$10-F9) -> 0
A13: Кількість тварин | B13: 0 | D13: Додаткових дітей | F13: =MAX(0,F7-F9)-F12 -> 0
A14: Кількість ночей | B14: 1 | D14: Доплата за додаткові місця, грн | F14: =F12*IFERROR(INDEX(ДОВ_ДОПЛ_ДОР,MATCH($B$8,КАТЕГОРІЇ,0)),0)+F13*IFERROR(INDEX(ДОВ_ДОПЛ_ДІТ,MATCH($B$8,КАТЕГОРІЇ,0)),0) -> 0
A15: Дата заїзду (необовʼязково) | D15: Знижка на проживання | F15: =IF($B$12="BBSPA",ЗНИЖКА_BBSPA,IFERROR(SUMIFS(ТАРИФИ_ЗНИЖКИ,ТАРИФИ_НАЗВИ,$B$7),0)) -> 0
D16: Перемикач: знижка на пакет | F16: =IF($U$3=0,0,IFERROR(INDEX(ПЕРЕМИКАЧІ,IF($B$12="BBSPA",2,1),$U$3),0)) -> 0
D17: Перемикач: знижка на SPA | F17: =IF($U$3=0,0,IFERROR(INDEX(ПЕРЕМИКАЧІ,3,$U$3),0)) -> 0
D18: Пакет, дорослий, грн | F18: =IF(OR($U$3=0,$U$8=0),0,IFERROR(INDEX(ПАКЕТИ_ЦІНИ,MATCH($U$10&"|"&$B$9,ПАКЕТИ_КЛЮЧ,0),$U$3),0)) -> 0
D19: Пакет, дитина, грн | F19: =IF(OR($U$3=0,$U$8=0),0,IFERROR(INDEX(ПАКЕТИ_ЦІНИ,MATCH($U$10&"|"&$B$9,ПАКЕТИ_КЛЮЧ,0),$U$3+1),0)) -> 0
D20: Фіксований SPA-візит, грн | F20: =IF(OR($U$3=0,$U$9=0),0,IFERROR(INDEX(SPA_ЦІНИ,MATCH(INDEX(ДОВ_SPA,MATCH($B$8,КАТЕГОРІЇ,0)),SPA_РІВЕНЬ,0),$U$3+IF($B$9="Вихідні",1,0)),0)) -> 0
D21: Проживання з тваринами, грн | F21: =$B$13*ТВАРИНИ -> 0
D22: Проживання за базовою місткістю до знижки, грн | F22: =F11 -> 4200
D23: ЦІНА ЗА НІЧ, грн | F23: =IF($F$6<>"OK","",ROUND(F22*(1-F15)/ОКРУГЛЕННЯ,0)*ОКРУГЛЕННЯ+F14*(1-F15)+($B$10*F18+$B$11*F19)*(1-F15*F16)+F20*(1-F15*F17)+F21) -> 4200
D24: ВАРТІСТЬ ПРОЖИВАННЯ, грн | F24: =IF(F23="","",F23*$B$14) -> 4200
D26: ПІДКАЗКА ЗА ДАТОЮ ЗАЇЗДУ
D27: Прайс-лист, що покриває дату | F27: =IF($B$15="","",IFERROR(INDEX(ПРАЙС_ЛИСТИ,SUMPRODUCT(MAX((ПЛ_ДАТА_З<=$B$15)*(ПЛ_ДАТА_ПО>=$B$15)*(ПЛ_СТАТУС="Активний")*(ПРАЙС_ЛИСТИ<>"")*ROW(ПРАЙС_ЛИСТИ)))-5),"— не знайдено —"))
D28: Тип дня за датою | F28: =IF($B$15="","",IF(WEEKDAY($B$15,2)>=ПЕРШИЙ_ВИХІДНИЙ,"Вихідні","Будні"))
D29: Підказка не змінює розрахунок — прайс-лист і тип дня обираються вручну вище.

Sheet Керування прайсом
A1: КЕРУВАННЯ ПРАЙСОМ — PHOENIX СХІДНИЦЯ
A2: Три кроки: 1) додайте прайс-лист у наступному вільному рядку зліва; 2) заповніть його двоколонковий блок праворуч (будні / вихідні); 3) перевірте результат у листі «Прайс». Жовті клітинки — ввід. | H2: технічний рядок — не редагувати | I2: =IF($A$6="","",$A$6) -> Осінь 2025 | J2: =IF($A$6="","",$A$6) -> Осінь 2025 | K2: =IF($A$7="","",$A$7) -> Осінь 2026 Базовий Прайс | L2: =IF($A$7="","",$A$7) -> Осінь 2026 Базовий Прайс | M2: =IF($A$8="","",$A$8) -> 0сінь 26 0-10% | N2: =IF($A$8="","",$A$8) -> 0сінь 26 0-10% | O2: =IF($A$9="","",$A$9) -> Осінь 26 канікули 0-10% | P2: =IF($A$9="","",$A$9) -> Осінь 26 канікули 0-10% | Q2: =IF($A$10="","",$A$10) -> 0сінь 26 10-20% | R2: =IF($A$10="","",$A$10) -> 0сінь 26 10-20% | S2: =IF($A$11="","",$A$11) -> Осінь 26 канікули 10-20% | T2: =IF($A$11="","",$A$11) -> Осінь 26 канікули 10-20% | U2: =IF($A$12="","",$A$12) -> 0сінь 26 20-30% | V2: =IF($A$12="","",$A$12) -> 0сінь 26 20-30% | W2: =IF($A$13="","",$A$13) -> Осінь 26 канікули 20-30% | X2: =IF($A$13="","",$A$13) -> Осінь 26 канікули 20-30% | Y2: =IF($A$14="","",$A$14) -> 0сінь 26 30-40% | Z2: =IF($A$14="","",$A$14) -> 0сінь 26 30-40% | AA2: =IF($A$15="","",$A$15) -> Осінь 26 канікули 30-40% | AB2: =IF($A$15="","",$A$15) -> Осінь 26 канікули 30-40% | AC2: =IF($A$16="","",$A$16) -> 0сінь 26 40-50% | AD2: =IF($A$16="","",$A$16) -> 0сінь 26 40-50% | AE2: =IF($A$17="","",$A$17) -> Осінь 26 канікули 40-50% | AF2: =IF($A$17="","",$A$17) -> Осінь 26 канікули 40-50% | AG2: =IF($A$18="","",$A$18) | AH2: =IF($A$18="","",$A$18) | AI2: =IF($A$19="","",$A$19) | AJ2: =IF($A$19="","",$A$19) | AK2: =IF($A$20="","",$A$20) | AL2: =IF($A$20="","",$A$20) | AM2: =IF($A$21="","",$A$21) | AN2: =IF($A$21="","",$A$21) | AO2: =IF($A$22="","",$A$22) | AP2: =IF($A$22="","",$A$22) | AQ2: =IF($A$23="","",$A$23) | AR2: =IF($A$23="","",$A$23) | AS2: =IF($A$24="","",$A$24) | AT2: =IF($A$24="","",$A$24) | AU2: =IF($A$25="","",$A$25) | AV2: =IF($A$25="","",$A$25) | AW2: =IF($A$26="","",$A$26) | AX2: =IF($A$26="","",$A$26) | AY2: =IF($A$27="","",$A$27) | AZ2: =IF($A$27="","",$A$27) | BA2: =IF($A$28="","",$A$28) | BB2: =IF($A$28="","",$A$28) | BC2: =IF($A$29="","",$A$29) | BD2: =IF($A$29="","",$A$29) | BE2: =IF($A$30="","",$A$30) | BF2: =IF($A$30="","",$A$30) | BG2: =IF($A$31="","",$A$31) | BH2: =IF($A$31="","",$A$31) | BI2: =IF($A$32="","",$A$32) | BJ2: =IF($A$32="","",$A$32) | BK2: =IF($A$33="","",$A$33) | BL2: =IF($A$33="","",$A$33) | BM2: =IF($A$34="","",$A$34) | BN2: =IF($A$34="","",$A$34) | BO2: =IF($A$35="","",$A$35) | BP2: =IF($A$35="","",$A$35) | BQ2: =IF($A$36="","",$A$36) | BR2: =IF($A$36="","",$A$36) | BS2: =IF($A$37="","",$A$37) | BT2: =IF($A$37="","",$A$37) | BU2: =IF($A$38="","",$A$38) | BV2: =IF($A$38="","",$A$38) | BW2: =IF($A$39="","",$A$39) | BX2: =IF($A$39="","",$A$39) | BY2: =IF($A$40="","",$A$40) | BZ2: =IF($A$40="","",$A$40) | CA2: =IF($A$41="","",$A$41) | CB2: =IF($A$41="","",$A$41) | CC2: =IF($A$42="","",$A$42) | CD2: =IF($A$42="","",$A$42) | CE2: =IF($A$43="","",$A$43) | CF2: =IF($A$43="","",$A$43) | CG2: =IF($A$44="","",$A$44) | CH2: =IF($A$44="","",$A$44) | CI2: =IF($A$45="","",$A$45) | CJ2: =IF($A$45="","",$A$45) | CK2: =IF($A$46="","",$A$46) | CL2: =IF($A$46="","",$A$46) | CM2: =IF($A$47="","",$A$47) | CN2: =IF($A$47="","",$A$47) | CO2: =IF($A$48="","",$A$48) | CP2: =IF($A$48="","",$A$48) | CQ2: =IF($A$49="","",$A$49) | CR2: =IF($A$49="","",$A$49) | CS2: =IF($A$50="","",$A$50) | CT2: =IF($A$50="","",$A$50) | CU2: =IF($A$51="","",$A$51) | CV2: =IF($A$51="","",$A$51) | CW2: =IF($A$52="","",$A$52) | CX2: =IF($A$52="","",$A$52) | CY2: =IF($A$53="","",$A$53) | CZ2: =IF($A$53="","",$A$53) | DA2: =IF($A$54="","",$A$54) | DB2: =IF($A$54="","",$A$54) | DC2: =IF($A$55="","",$A$55) | DD2: =IF($A$55="","",$A$55) | DE2: =IF($A$56="","",$A$56) | DF2: =IF($A$56="","",$A$56) | DG2: =IF($A$57="","",$A$57) | DH2: =IF($A$57="","",$A$57) | DI2: =IF($A$58="","",$A$58) | DJ2: =IF($A$58="","",$A$58) | DK2: =IF($A$59="","",$A$59) | DL2: =IF($A$59="","",$A$59) | DM2: =IF($A$60="","",$A$60) | DN2: =IF($A$60="","",$A$60) | DO2: =IF($A$61="","",$A$61) | DP2: =IF($A$61="","",$A$61) | DQ2: =IF($A$62="","",$A$62) | DR2: =IF($A$62="","",$A$62) | DS2: =IF($A$63="","",$A$63) | DT2: =IF($A$63="","",$A$63) | DU2: =IF($A$64="","",$A$64) | DV2: =IF($A$64="","",$A$64) | DW2: =IF($A$65="","",$A$65) | DX2: =IF($A$65="","",$A$65) | DY2: =IF($A$66="","",$A$66) | DZ2: =IF($A$66="","",$A$66) | EA2: =IF($A$67="","",$A$67) | EB2: =IF($A$67="","",$A$67) | EC2: =IF($A$68="","",$A$68) | ED2: =IF($A$68="","",$A$68) | EE2: =IF($A$69="","",$A$69) | EF2: =IF($A$69="","",$A$69) | EG2: =IF($A$70="","",$A$70) | EH2: =IF($A$70="","",$A$70) | EI2: =IF($A$71="","",$A$71) | EJ2: =IF($A$71="","",$A$71) | EK2: =IF($A$72="","",$A$72) | EL2: =IF($A$72="","",$A$72) | EM2: =IF($A$73="","",$A$73) | EN2: =IF($A$73="","",$A$73) | EO2: =IF($A$74="","",$A$74) | EP2: =IF($A$74="","",$A$74) | EQ2: =IF($A$75="","",$A$75) | ER2: =IF($A$75="","",$A$75) | ES2: =IF($A$76="","",$A$76) | ET2: =IF($A$76="","",$A$76) | EU2: =IF($A$77="","",$A$77) | EV2: =IF($A$77="","",$A$77) | EW2: =IF($A$78="","",$A$78) | EX2: =IF($A$78="","",$A$78) | EY2: =IF($A$79="","",$A$79) | EZ2: =IF($A$79="","",$A$79) | FA2: =IF($A$80="","",$A$80) | FB2: =IF($A$80="","",$A$80) | FC2: =IF($A$81="","",$A$81) | FD2: =IF($A$81="","",$A$81) | FE2: =IF($A$82="","",$A$82) | FF2: =IF($A$82="","",$A$82) | FG2: =IF($A$83="","",$A$83) | FH2: =IF($A$83="","",$A$83) | FI2: =IF($A$84="","",$A$84) | FJ2: =IF($A$84="","",$A$84) | FK2: =IF($A$85="","",$A$85) | FL2: =IF($A$85="","",$A$85) | FM2: =IF($A$86="","",$A$86) | FN2: =IF($A$86="","",$A$86) | FO2: =IF($A$87="","",$A$87) | FP2: =IF($A$87="","",$A$87) | FQ2: =IF($A$88="","",$A$88) | FR2: =IF($A$88="","",$A$88) | FS2: =IF($A$89="","",$A$89) | FT2: =IF($A$89="","",$A$89) | FU2: =IF($A$90="","",$A$90) | FV2: =IF($A$90="","",$A$90) | FW2: =IF($A$91="","",$A$91) | FX2: =IF($A$91="","",$A$91) | FY2: =IF($A$92="","",$A$92) | FZ2: =IF($A$92="","",$A$92) | GA2: =IF($A$93="","",$A$93) | GB2: =IF($A$93="","",$A$93) | GC2: =IF($A$94="","",$A$94) | GD2: =IF($A$94="","",$A$94) | GE2: =IF($A$95="","",$A$95) | GF2: =IF($A$95="","",$A$95) | GG2: =IF($A$96="","",$A$96) | GH2: =IF($A$96="","",$A$96) | GI2: =IF($A$97="","",$A$97) | GJ2: =IF($A$97="","",$A$97) | GK2: =IF($A$98="","",$A$98) | GL2: =IF($A$98="","",$A$98) | GM2: =IF($A$99="","",$A$99) | GN2: =IF($A$99="","",$A$99) | GO2: =IF($A$100="","",$A$100) | GP2: =IF($A$100="","",$A$100) | GQ2: =IF($A$101="","",$A$101) | GR2: =IF($A$101="","",$A$101) | GS2: =IF($A$102="","",$A$102) | GT2: =IF($A$102="","",$A$102) | GU2: =IF($A$103="","",$A$103) | GV2: =IF($A$103="","",$A$103) | GW2: =IF($A$104="","",$A$104) | GX2: =IF($A$104="","",$A$104) | GY2: =IF($A$105="","",$A$105) | GZ2: =IF($A$105="","",$A$105)
A4: 1. ПРАЙС-ЛИСТИ / ПЕРІОДИ | F4: 2. ГЛОБАЛЬНІ ПАРАМЕТРИ
A5: Прайс-лист | B5: Дата з | C5: Дата по | D5: Статус | E5: Примітка / оновлено | F5: Активний прайс-лист (показується у «Прайс») | G5: =Прайс!$B$3 -> 0сінь 26 0-10% | H5: ПРАЙС-ЛИСТ | I5: =IF($A$6="","",$A$6) -> Осінь 2025 | K5: =IF($A$7="","",$A$7) -> Осінь 2026 Базовий Прайс | M5: =IF($A$8="","",$A$8) -> 0сінь 26 0-10% | O5: =IF($A$9="","",$A$9) -> Осінь 26 канікули 0-10% | Q5: =IF($A$10="","",$A$10) -> 0сінь 26 10-20% | S5: =IF($A$11="","",$A$11) -> Осінь 26 канікули 10-20% | U5: =IF($A$12="","",$A$12) -> 0сінь 26 20-30% | W5: =IF($A$13="","",$A$13) -> Осінь 26 канікули 20-30% | Y5: =IF($A$14="","",$A$14) -> 0сінь 26 30-40% | AA5: =IF($A$15="","",$A$15) -> Осінь 26 канікули 30-40% | AC5: =IF($A$16="","",$A$16) -> 0сінь 26 40-50% | AE5: =IF($A$17="","",$A$17) -> Осінь 26 канікули 40-50% | AG5: =IF($A$18="","",$A$18) | AI5: =IF($A$19="","",$A$19) | AK5: =IF($A$20="","",$A$20) | AM5: =IF($A$21="","",$A$21) | AO5: =IF($A$22="","",$A$22) | AQ5: =IF($A$23="","",$A$23) | AS5: =IF($A$24="","",$A$24) | AU5: =IF($A$25="","",$A$25) | AW5: =IF($A$26="","",$A$26) | AY5: =IF($A$27="","",$A$27) | BA5: =IF($A$28="","",$A$28) | BC5: =IF($A$29="","",$A$29) | BE5: =IF($A$30="","",$A$30) | BG5: =IF($A$31="","",$A$31) | BI5: =IF($A$32="","",$A$32) | BK5: =IF($A$33="","",$A$33) | BM5: =IF($A$34="","",$A$34) | BO5: =IF($A$35="","",$A$35) | BQ5: =IF($A$36="","",$A$36) | BS5: =IF($A$37="","",$A$37) | BU5: =IF($A$38="","",$A$38) | BW5: =IF($A$39="","",$A$39) | BY5: =IF($A$40="","",$A$40) | CA5: =IF($A$41="","",$A$41) | CC5: =IF($A$42="","",$A$42) | CE5: =IF($A$43="","",$A$43) | CG5: =IF($A$44="","",$A$44) | CI5: =IF($A$45="","",$A$45) | CK5: =IF($A$46="","",$A$46) | CM5: =IF($A$47="","",$A$47) | CO5: =IF($A$48="","",$A$48) | CQ5: =IF($A$49="","",$A$49) | CS5: =IF($A$50="","",$A$50) | CU5: =IF($A$51="","",$A$51) | CW5: =IF($A$52="","",$A$52) | CY5: =IF($A$53="","",$A$53) | DA5: =IF($A$54="","",$A$54) | DC5: =IF($A$55="","",$A$55) | DE5: =IF($A$56="","",$A$56) | DG5: =IF($A$57="","",$A$57) | DI5: =IF($A$58="","",$A$58) | DK5: =IF($A$59="","",$A$59) | DM5: =IF($A$60="","",$A$60) | DO5: =IF($A$61="","",$A$61) | DQ5: =IF($A$62="","",$A$62) | DS5: =IF($A$63="","",$A$63) | DU5: =IF($A$64="","",$A$64) | DW5: =IF($A$65="","",$A$65) | DY5: =IF($A$66="","",$A$66) | EA5: =IF($A$67="","",$A$67) | EC5: =IF($A$68="","",$A$68) | EE5: =IF($A$69="","",$A$69) | EG5: =IF($A$70="","",$A$70) | EI5: =IF($A$71="","",$A$71) | EK5: =IF($A$72="","",$A$72) | EM5: =IF($A$73="","",$A$73) | EO5: =IF($A$74="","",$A$74) | EQ5: =IF($A$75="","",$A$75) | ES5: =IF($A$76="","",$A$76) | EU5: =IF($A$77="","",$A$77) | EW5: =IF($A$78="","",$A$78) | EY5: =IF($A$79="","",$A$79) | FA5: =IF($A$80="","",$A$80) | FC5: =IF($A$81="","",$A$81) | FE5: =IF($A$82="","",$A$82) | FG5: =IF($A$83="","",$A$83) | FI5: =IF($A$84="","",$A$84) | FK5: =IF($A$85="","",$A$85) | FM5: =IF($A$86="","",$A$86) | FO5: =IF($A$87="","",$A$87) | FQ5: =IF($A$88="","",$A$88) | FS5: =IF($A$89="","",$A$89) | FU5: =IF($A$90="","",$A$90) | FW5: =IF($A$91="","",$A$91) | FY5: =IF($A$92="","",$A$92) | GA5: =IF($A$93="","",$A$93) | GC5: =IF($A$94="","",$A$94) | GE5: =IF($A$95="","",$A$95) | GG5: =IF($A$96="","",$A$96) | GI5: =IF($A$97="","",$A$97) | GK5: =IF($A$98="","",$A$98) | GM5: =IF($A$99="","",$A$99) | GO5: =IF($A$100="","",$A$100) | GQ5: =IF($A$101="","",$A$101) | GS5: =IF($A$102="","",$A$102) | GU5: =IF($A$103="","",$A$103) | GW5: =IF($A$104="","",$A$104) | GY5: =IF($A$105="","",$A$105)
A6: Осінь 2025 | B6: 45901 | C6: 45991 | D6: Неактивний | F6: Крок округлення, грн | G6: 100 | H6: Період дії | I6: =IF($A$6="","",IF(OR($B$6="",$C$6=""),IF($E$6="","— період не заданий —",$E$6),TEXT(DAY($B$6),"00")&"."&TEXT(MONTH($B$6),"00")&"."&YEAR($B$6)&" – "&TEXT(DAY($C$6),"00")&"."&TEXT(MONTH($C$6),"00")&"."&YEAR($C$6))) -> 01.09.2025 – 30.11.2025 | K6: =IF($A$7="","",IF(OR($B$7="",$C$7=""),IF($E$7="","— період не заданий —",$E$7),TEXT(DAY($B$7),"00")&"."&TEXT(MONTH($B$7),"00")&"."&YEAR($B$7)&" – "&TEXT(DAY($C$7),"00")&"."&TEXT(MONTH($C$7),"00")&"."&YEAR($C$7))) -> 01.09.2026 – 30.11.2026 | M6: =IF($A$8="","",IF(OR($B$8="",$C$8=""),IF($E$8="","— період не заданий —",$E$8),TEXT(DAY($B$8),"00")&"."&TEXT(MONTH($B$8),"00")&"."&YEAR($B$8)&" – "&TEXT(DAY($C$8),"00")&"."&TEXT(MONTH($C$8),"00")&"."&YEAR($C$8))) -> 01.10.2026 – 30.11.2026 | O6: =IF($A$9="","",IF(OR($B$9="",$C$9=""),IF($E$9="","— період не заданий —",$E$9),TEXT(DAY($B$9),"00")&"."&TEXT(MONTH($B$9),"00")&"."&YEAR($B$9)&" – "&TEXT(DAY($C$9),"00")&"."&TEXT(MONTH($C$9),"00")&"."&YEAR($C$9))) -> до 15.09 та 26.10 -01.11 | Q6: =IF($A$10="","",IF(OR($B$10="",$C$10=""),IF($E$10="","— період не заданий —",$E$10),TEXT(DAY($B$10),"00")&"."&TEXT(MONTH($B$10),"00")&"."&YEAR($B$10)&" – "&TEXT(DAY($C$10),"00")&"."&TEXT(MONTH($C$10),"00")&"."&YEAR($C$10))) -> — період не заданий — | S6: =IF($A$11="","",IF(OR($B$11="",$C$11=""),IF($E$11="","— період не заданий —",$E$11),TEXT(DAY($B$11),"00")&"."&TEXT(MONTH($B$11),"00")&"."&YEAR($B$11)&" – "&TEXT(DAY($C$11),"00")&"."&TEXT(MONTH($C$11),"00")&"."&YEAR($C$11))) -> — період не заданий — | U6: =IF($A$12="","",IF(OR($B$12="",$C$12=""),IF($E$12="","— період не заданий —",$E$12),TEXT(DAY($B$12),"00")&"."&TEXT(MONTH($B$12),"00")&"."&YEAR($B$12)&" – "&TEXT(DAY($C$12),"00")&"."&TEXT(MONTH($C$12),"00")&"."&YEAR($C$12))) -> 16.09.2026 – 30.09.2026 | W6: =IF($A$13="","",IF(OR($B$13="",$C$13=""),IF($E$13="","— період не заданий —",$E$13),TEXT(DAY($B$13),"00")&"."&TEXT(MONTH($B$13),"00")&"."&YEAR($B$13)&" – "&TEXT(DAY($C$13),"00")&"."&TEXT(MONTH($C$13),"00")&"."&YEAR($C$13))) -> — період не заданий — | Y6: =IF($A$14="","",IF(OR($B$14="",$C$14=""),IF($E$14="","— період не заданий —",$E$14),TEXT(DAY($B$14),"00")&"."&TEXT(MONTH($B$14),"00")&"."&YEAR($B$14)&" – "&TEXT(DAY($C$14),"00")&"."&TEXT(MONTH($C$14),"00")&"."&YEAR($C$14))) -> — період не заданий — | AA6: =IF($A$15="","",IF(OR($B$15="",$C$15=""),IF($E$15="","— період не заданий —",$E$15),TEXT(DAY($B$15),"00")&"."&TEXT(MONTH($B$15),"00")&"."&YEAR($B$15)&" – "&TEXT(DAY($C$15),"00")&"."&TEXT(MONTH($C$15),"00")&"."&YEAR($C$15))) -> — період не заданий — | AC6: =IF($A$16="","",IF(OR($B$16="",$C$16=""),IF($E$16="","— період не заданий —",$E$16),TEXT(DAY($B$16),"00")&"."&TEXT(MONTH($B$16),"00")&"."&YEAR($B$16)&" – "&TEXT(DAY($C$16),"00")&"."&TEXT(MONTH($C$16),"00")&"."&YEAR($C$16))) -> — період не заданий — | AE6: =IF($A$17="","",IF(OR($B$17="",$C$17=""),IF($E$17="","— період не заданий —",$E$17),TEXT(DAY($B$17),"00")&"."&TEXT(MONTH($B$17),"00")&"."&YEAR($B$17)&" – "&TEXT(DAY($C$17),"00")&"."&TEXT(MONTH($C$17),"00")&"."&YEAR($C$17))) -> — період не заданий — | AG6: =IF($A$18="","",IF(OR($B$18="",$C$18=""),IF($E$18="","— період не заданий —",$E$18),TEXT(DAY($B$18),"00")&"."&TEXT(MONTH($B$18),"00")&"."&YEAR($B$18)&" – "&TEXT(DAY($C$18),"00")&"."&TEXT(MONTH($C$18),"00")&"."&YEAR($C$18))) | AI6: =IF($A$19="","",IF(OR($B$19="",$C$19=""),IF($E$19="","— період не заданий —",$E$19),TEXT(DAY($B$19),"00")&"."&TEXT(MONTH($B$19),"00")&"."&YEAR($B$19)&" – "&TEXT(DAY($C$19),"00")&"."&TEXT(MONTH($C$19),"00")&"."&YEAR($C$19))) | AK6: =IF($A$20="","",IF(OR($B$20="",$C$20=""),IF($E$20="","— період не заданий —",$E$20),TEXT(DAY($B$20),"00")&"."&TEXT(MONTH($B$20),"00")&"."&YEAR($B$20)&" – "&TEXT(DAY($C$20),"00")&"."&TEXT(MONTH($C$20),"00")&"."&YEAR($C$20))) | AM6: =IF($A$21="","",IF(OR($B$21="",$C$21=""),IF($E$21="","— період не заданий —",$E$21),TEXT(DAY($B$21),"00")&"."&TEXT(MONTH($B$21),"00")&"."&YEAR($B$21)&" – "&TEXT(DAY($C$21),"00")&"."&TEXT(MONTH($C$21),"00")&"."&YEAR($C$21))) | AO6: =IF($A$22="","",IF(OR($B$22="",$C$22=""),IF($E$22="","— період не заданий —",$E$22),TEXT(DAY($B$22),"00")&"."&TEXT(MONTH($B$22),"00")&"."&YEAR($B$22)&" – "&TEXT(DAY($C$22),"00")&"."&TEXT(MONTH($C$22),"00")&"."&YEAR($C$22))) | AQ6: =IF($A$23="","",IF(OR($B$23="",$C$23=""),IF($E$23="","— період не заданий —",$E$23),TEXT(DAY($B$23),"00")&"."&TEXT(MONTH($B$23),"00")&"."&YEAR($B$23)&" – "&TEXT(DAY($C$23),"00")&"."&TEXT(MONTH($C$23),"00")&"."&YEAR($C$23))) | AS6: =IF($A$24="","",IF(OR($B$24="",$C$24=""),IF($E$24="","— період не заданий —",$E$24),TEXT(DAY($B$24),"00")&"."&TEXT(MONTH($B$24),"00")&"."&YEAR($B$24)&" – "&TEXT(DAY($C$24),"00")&"."&TEXT(MONTH($C$24),"00")&"."&YEAR($C$24))) | AU6: =IF($A$25="","",IF(OR($B$25="",$C$25=""),IF($E$25="","— період не заданий —",$E$25),TEXT(DAY($B$25),"00")&"."&TEXT(MONTH($B$25),"00")&"."&YEAR($B$25)&" – "&TEXT(DAY($C$25),"00")&"."&TEXT(MONTH($C$25),"00")&"."&YEAR($C$25))) | AW6: =IF($A$26="","",IF(OR($B$26="",$C$26=""),IF($E$26="","— період не заданий —",$E$26),TEXT(DAY($B$26),"00")&"."&TEXT(MONTH($B$26),"00")&"."&YEAR($B$26)&" – "&TEXT(DAY($C$26),"00")&"."&TEXT(MONTH($C$26),"00")&"."&YEAR($C$26))) | AY6: =IF($A$27="","",IF(OR($B$27="",$C$27=""),IF($E$27="","— період не заданий —",$E$27),TEXT(DAY($B$27),"00")&"."&TEXT(MONTH($B$27),"00")&"."&YEAR($B$27)&" – "&TEXT(DAY($C$27),"00")&"."&TEXT(MONTH($C$27),"00")&"."&YEAR($C$27))) | BA6: =IF($A$28="","",IF(OR($B$28="",$C$28=""),IF($E$28="","— період не заданий —",$E$28),TEXT(DAY($B$28),"00")&"."&TEXT(MONTH($B$28),"00")&"."&YEAR($B$28)&" – "&TEXT(DAY($C$28),"00")&"."&TEXT(MONTH($C$28),"00")&"."&YEAR($C$28))) | BC6: =IF($A$29="","",IF(OR($B$29="",$C$29=""),IF($E$29="","— період не заданий —",$E$29),TEXT(DAY($B$29),"00")&"."&TEXT(MONTH($B$29),"00")&"."&YEAR($B$29)&" – "&TEXT(DAY($C$29),"00")&"."&TEXT(MONTH($C$29),"00")&"."&YEAR($C$29))) | BE6: =IF($A$30="","",IF(OR($B$30="",$C$30=""),IF($E$30="","— період не заданий —",$E$30),TEXT(DAY($B$30),"00")&"."&TEXT(MONTH($B$30),"00")&"."&YEAR($B$30)&" – "&TEXT(DAY($C$30),"00")&"."&TEXT(MONTH($C$30),"00")&"."&YEAR($C$30))) | BG6: =IF($A$31="","",IF(OR($B$31="",$C$31=""),IF($E$31="","— період не заданий —",$E$31),TEXT(DAY($B$31),"00")&"."&TEXT(MONTH($B$31),"00")&"."&YEAR($B$31)&" – "&TEXT(DAY($C$31),"00")&"."&TEXT(MONTH($C$31),"00")&"."&YEAR($C$31))) | BI6: =IF($A$32="","",IF(OR($B$32="",$C$32=""),IF($E$32="","— період не заданий —",$E$32),TEXT(DAY($B$32),"00")&"."&TEXT(MONTH($B$32),"00")&"."&YEAR($B$32)&" – "&TEXT(DAY($C$32),"00")&"."&TEXT(MONTH($C$32),"00")&"."&YEAR($C$32))) | BK6: =IF($A$33="","",IF(OR($B$33="",$C$33=""),IF($E$33="","— період не заданий —",$E$33),TEXT(DAY($B$33),"00")&"."&TEXT(MONTH($B$33),"00")&"."&YEAR($B$33)&" – "&TEXT(DAY($C$33),"00")&"."&TEXT(MONTH($C$33),"00")&"."&YEAR($C$33))) | BM6: =IF($A$34="","",IF(OR($B$34="",$C$34=""),IF($E$34="","— період не заданий —",$E$34),TEXT(DAY($B$34),"00")&"."&TEXT(MONTH($B$34),"00")&"."&YEAR($B$34)&" – "&TEXT(DAY($C$34),"00")&"."&TEXT(MONTH($C$34),"00")&"."&YEAR($C$34))) | BO6: =IF($A$35="","",IF(OR($B$35="",$C$35=""),IF($E$35="","— період не заданий —",$E$35),TEXT(DAY($B$35),"00")&"."&TEXT(MONTH($B$35),"00")&"."&YEAR($B$35)&" – "&TEXT(DAY($C$35),"00")&"."&TEXT(MONTH($C$35),"00")&"."&YEAR($C$35))) | BQ6: =IF($A$36="","",IF(OR($B$36="",$C$36=""),IF($E$36="","— період не заданий —",$E$36),TEXT(DAY($B$36),"00")&"."&TEXT(MONTH($B$36),"00")&"."&YEAR($B$36)&" – "&TEXT(DAY($C$36),"00")&"."&TEXT(MONTH($C$36),"00")&"."&YEAR($C$36))) | BS6: =IF($A$37="","",IF(OR($B$37="",$C$37=""),IF($E$37="","— період не заданий —",$E$37),TEXT(DAY($B$37),"00")&"."&TEXT(MONTH($B$37),"00")&"."&YEAR($B$37)&" – "&TEXT(DAY($C$37),"00")&"."&TEXT(MONTH($C$37),"00")&"."&YEAR($C$37))) | BU6: =IF($A$38="","",IF(OR($B$38="",$C$38=""),IF($E$38="","— період не заданий —",$E$38),TEXT(DAY($B$38),"00")&"."&TEXT(MONTH($B$38),"00")&"."&YEAR($B$38)&" – "&TEXT(DAY($C$38),"00")&"."&TEXT(MONTH($C$38),"00")&"."&YEAR($C$38))) | BW6: =IF($A$39="","",IF(OR($B$39="",$C$39=""),IF($E$39="","— період не заданий —",$E$39),TEXT(DAY($B$39),"00")&"."&TEXT(MONTH($B$39),"00")&"."&YEAR($B$39)&" – "&TEXT(DAY($C$39),"00")&"."&TEXT(MONTH($C$39),"00")&"."&YEAR($C$39))) | BY6: =IF($A$40="","",IF(OR($B$40="",$C$40=""),IF($E$40="","— період не заданий —",$E$40),TEXT(DAY($B$40),"00")&"."&TEXT(MONTH($B$40),"00")&"."&YEAR($B$40)&" – "&TEXT(DAY($C$40),"00")&"."&TEXT(MONTH($C$40),"00")&"."&YEAR($C$40))) | CA6: =IF($A$41="","",IF(OR($B$41="",$C$41=""),IF($E$41="","— період не заданий —",$E$41),TEXT(DAY($B$41),"00")&"."&TEXT(MONTH($B$41),"00")&"."&YEAR($B$41)&" – "&TEXT(DAY($C$41),"00")&"."&TEXT(MONTH($C$41),"00")&"."&YEAR($C$41))) | CC6: =IF($A$42="","",IF(OR($B$42="",$C$42=""),IF($E$42="","— період не заданий —",$E$42),TEXT(DAY($B$42),"00")&"."&TEXT(MONTH($B$42),"00")&"."&YEAR($B$42)&" – "&TEXT(DAY($C$42),"00")&"."&TEXT(MONTH($C$42),"00")&"."&YEAR($C$42))) | CE6: =IF($A$43="","",IF(OR($B$43="",$C$43=""),IF($E$43="","— період не заданий —",$E$43),TEXT(DAY($B$43),"00")&"."&TEXT(MONTH($B$43),"00")&"."&YEAR($B$43)&" – "&TEXT(DAY($C$43),"00")&"."&TEXT(MONTH($C$43),"00")&"."&YEAR($C$43))) | CG6: =IF($A$44="","",IF(OR($B$44="",$C$44=""),IF($E$44="","— період не заданий —",$E$44),TEXT(DAY($B$44),"00")&"."&TEXT(MONTH($B$44),"00")&"."&YEAR($B$44)&" – "&TEXT(DAY($C$44),"00")&"."&TEXT(MONTH($C$44),"00")&"."&YEAR($C$44))) | CI6: =IF($A$45="","",IF(OR($B$45="",$C$45=""),IF($E$45="","— період не заданий —",$E$45),TEXT(DAY($B$45),"00")&"."&TEXT(MONTH($B$45),"00")&"."&YEAR($B$45)&" – "&TEXT(DAY($C$45),"00")&"."&TEXT(MONTH($C$45),"00")&"."&YEAR($C$45))) | CK6: =IF($A$46="","",IF(OR($B$46="",$C$46=""),IF($E$46="","— період не заданий —",$E$46),TEXT(DAY($B$46),"00")&"."&TEXT(MONTH($B$46),"00")&"."&YEAR($B$46)&" – "&TEXT(DAY($C$46),"00")&"."&TEXT(MONTH($C$46),"00")&"."&YEAR($C$46))) | CM6: =IF($A$47="","",IF(OR($B$47="",$C$47=""),IF($E$47="","— період не заданий —",$E$47),TEXT(DAY($B$47),"00")&"."&TEXT(MONTH($B$47),"00")&"."&YEAR($B$47)&" – "&TEXT(DAY($C$47),"00")&"."&TEXT(MONTH($C$47),"00")&"."&YEAR($C$47))) | CO6: =IF($A$48="","",IF(OR($B$48="",$C$48=""),IF($E$48="","— період не заданий —",$E$48),TEXT(DAY($B$48),"00")&"."&TEXT(MONTH($B$48),"00")&"."&YEAR($B$48)&" – "&TEXT(DAY($C$48),"00")&"."&TEXT(MONTH($C$48),"00")&"."&YEAR($C$48))) | CQ6: =IF($A$49="","",IF(OR($B$49="",$C$49=""),IF($E$49="","— період не заданий —",$E$49),TEXT(DAY($B$49),"00")&"."&TEXT(MONTH($B$49),"00")&"."&YEAR($B$49)&" – "&TEXT(DAY($C$49),"00")&"."&TEXT(MONTH($C$49),"00")&"."&YEAR($C$49))) | CS6: =IF($A$50="","",IF(OR($B$50="",$C$50=""),IF($E$50="","— період не заданий —",$E$50),TEXT(DAY($B$50),"00")&"."&TEXT(MONTH($B$50),"00")&"."&YEAR($B$50)&" – "&TEXT(DAY($C$50),"00")&"."&TEXT(MONTH($C$50),"00")&"."&YEAR($C$50))) | CU6: =IF($A$51="","",IF(OR($B$51="",$C$51=""),IF($E$51="","— період не заданий —",$E$51),TEXT(DAY($B$51),"00")&"."&TEXT(MONTH($B$51),"00")&"."&YEAR($B$51)&" – "&TEXT(DAY($C$51),"00")&"."&TEXT(MONTH($C$51),"00")&"."&YEAR($C$51))) | CW6: =IF($A$52="","",IF(OR($B$52="",$C$52=""),IF($E$52="","— період не заданий —",$E$52),TEXT(DAY($B$52),"00")&"."&TEXT(MONTH($B$52),"00")&"."&YEAR($B$52)&" – "&TEXT(DAY($C$52),"00")&"."&TEXT(MONTH($C$52),"00")&"."&YEAR($C$52))) | CY6: =IF($A$53="","",IF(OR($B$53="",$C$53=""),IF($E$53="","— період не заданий —",$E$53),TEXT(DAY($B$53),"00")&"."&TEXT(MONTH($B$53),"00")&"."&YEAR($B$53)&" – "&TEXT(DAY($C$53),"00")&"."&TEXT(MONTH($C$53),"00")&"."&YEAR($C$53))) | DA6: =IF($A$54="","",IF(OR($B$54="",$C$54=""),IF($E$54="","— період не заданий —",$E$54),TEXT(DAY($B$54),"00")&"."&TEXT(MONTH($B$54),"00")&"."&YEAR($B$54)&" – "&TEXT(DAY($C$54),"00")&"."&TEXT(MONTH($C$54),"00")&"."&YEAR($C$54))) | DC6: =IF($A$55="","",IF(OR($B$55="",$C$55=""),IF($E$55="","— період не заданий —",$E$55),TEXT(DAY($B$55),"00")&"."&TEXT(MONTH($B$55),"00")&"."&YEAR($B$55)&" – "&TEXT(DAY($C$55),"00")&"."&TEXT(MONTH($C$55),"00")&"."&YEAR($C$55))) | DE6: =IF($A$56="","",IF(OR($B$56="",$C$56=""),IF($E$56="","— період не заданий —",$E$56),TEXT(DAY($B$56),"00")&"."&TEXT(MONTH($B$56),"00")&"."&YEAR($B$56)&" – "&TEXT(DAY($C$56),"00")&"."&TEXT(MONTH($C$56),"00")&"."&YEAR($C$56))) | DG6: =IF($A$57="","",IF(OR($B$57="",$C$57=""),IF($E$57="","— період не заданий —",$E$57),TEXT(DAY($B$57),"00")&"."&TEXT(MONTH($B$57),"00")&"."&YEAR($B$57)&" – "&TEXT(DAY($C$57),"00")&"."&TEXT(MONTH($C$57),"00")&"."&YEAR($C$57))) | DI6: =IF($A$58="","",IF(OR($B$58="",$C$58=""),IF($E$58="","— період не заданий —",$E$58),TEXT(DAY($B$58),"00")&"."&TEXT(MONTH($B$58),"00")&"."&YEAR($B$58)&" – "&TEXT(DAY($C$58),"00")&"."&TEXT(MONTH($C$58),"00")&"."&YEAR($C$58))) | DK6: =IF($A$59="","",IF(OR($B$59="",$C$59=""),IF($E$59="","— період не заданий —",$E$59),TEXT(DAY($B$59),"00")&"."&TEXT(MONTH($B$59),"00")&"."&YEAR($B$59)&" – "&TEXT(DAY($C$59),"00")&"."&TEXT(MONTH($C$59),"00")&"."&YEAR($C$59))) | DM6: =IF($A$60="","",IF(OR($B$60="",$C$60=""),IF($E$60="","— період не заданий —",$E$60),TEXT(DAY($B$60),"00")&"."&TEXT(MONTH($B$60),"00")&"."&YEAR($B$60)&" – "&TEXT(DAY($C$60),"00")&"."&TEXT(MONTH($C$60),"00")&"."&YEAR($C$60))) | DO6: =IF($A$61="","",IF(OR($B$61="",$C$61=""),IF($E$61="","— період не заданий —",$E$61),TEXT(DAY($B$61),"00")&"."&TEXT(MONTH($B$61),"00")&"."&YEAR($B$61)&" – "&TEXT(DAY($C$61),"00")&"."&TEXT(MONTH($C$61),"00")&"."&YEAR($C$61))) | DQ6: =IF($A$62="","",IF(OR($B$62="",$C$62=""),IF($E$62="","— період не заданий —",$E$62),TEXT(DAY($B$62),"00")&"."&TEXT(MONTH($B$62),"00")&"."&YEAR($B$62)&" – "&TEXT(DAY($C$62),"00")&"."&TEXT(MONTH($C$62),"00")&"."&YEAR($C$62))) | DS6: =IF($A$63="","",IF(OR($B$63="",$C$63=""),IF($E$63="","— період не заданий —",$E$63),TEXT(DAY($B$63),"00")&"."&TEXT(MONTH($B$63),"00")&"."&YEAR($B$63)&" – "&TEXT(DAY($C$63),"00")&"."&TEXT(MONTH($C$63),"00")&"."&YEAR($C$63))) | DU6: =IF($A$64="","",IF(OR($B$64="",$C$64=""),IF($E$64="","— період не заданий —",$E$64),TEXT(DAY($B$64),"00")&"."&TEXT(MONTH($B$64),"00")&"."&YEAR($B$64)&" – "&TEXT(DAY($C$64),"00")&"."&TEXT(MONTH($C$64),"00")&"."&YEAR($C$64))) | DW6: =IF($A$65="","",IF(OR($B$65="",$C$65=""),IF($E$65="","— період не заданий —",$E$65),TEXT(DAY($B$65),"00")&"."&TEXT(MONTH($B$65),"00")&"."&YEAR($B$65)&" – "&TEXT(DAY($C$65),"00")&"."&TEXT(MONTH($C$65),"00")&"."&YEAR($C$65))) | DY6: =IF($A$66="","",IF(OR($B$66="",$C$66=""),IF($E$66="","— період не заданий —",$E$66),TEXT(DAY($B$66),"00")&"."&TEXT(MONTH($B$66),"00")&"."&YEAR($B$66)&" – "&TEXT(DAY($C$66),"00")&"."&TEXT(MONTH($C$66),"00")&"."&YEAR($C$66))) | EA6: =IF($A$67="","",IF(OR($B$67="",$C$67=""),IF($E$67="","— період не заданий —",$E$67),TEXT(DAY($B$67),"00")&"."&TEXT(MONTH($B$67),"00")&"."&YEAR($B$67)&" – "&TEXT(DAY($C$67),"00")&"."&TEXT(MONTH($C$67),"00")&"."&YEAR($C$67))) | EC6: =IF($A$68="","",IF(OR($B$68="",$C$68=""),IF($E$68="","— період не заданий —",$E$68),TEXT(DAY($B$68),"00")&"."&TEXT(MONTH($B$68),"00")&"."&YEAR($B$68)&" – "&TEXT(DAY($C$68),"00")&"."&TEXT(MONTH($C$68),"00")&"."&YEAR($C$68))) | EE6: =IF($A$69="","",IF(OR($B$69="",$C$69=""),IF($E$69="","— період не заданий —",$E$69),TEXT(DAY($B$69),"00")&"."&TEXT(MONTH($B$69),"00")&"."&YEAR($B$69)&" – "&TEXT(DAY($C$69),"00")&"."&TEXT(MONTH($C$69),"00")&"."&YEAR($C$69))) | EG6: =IF($A$70="","",IF(OR($B$70="",$C$70=""),IF($E$70="","— період не заданий —",$E$70),TEXT(DAY($B$70),"00")&"."&TEXT(MONTH($B$70),"00")&"."&YEAR($B$70)&" – "&TEXT(DAY($C$70),"00")&"."&TEXT(MONTH($C$70),"00")&"."&YEAR($C$70))) | EI6: =IF($A$71="","",IF(OR($B$71="",$C$71=""),IF($E$71="","— період не заданий —",$E$71),TEXT(DAY($B$71),"00")&"."&TEXT(MONTH($B$71),"00")&"."&YEAR($B$71)&" – "&TEXT(DAY($C$71),"00")&"."&TEXT(MONTH($C$71),"00")&"."&YEAR($C$71))) | EK6: =IF($A$72="","",IF(OR($B$72="",$C$72=""),IF($E$72="","— період не заданий —",$E$72),TEXT(DAY($B$72),"00")&"."&TEXT(MONTH($B$72),"00")&"."&YEAR($B$72)&" – "&TEXT(DAY($C$72),"00")&"."&TEXT(MONTH($C$72),"00")&"."&YEAR($C$72))) | EM6: =IF($A$73="","",IF(OR($B$73="",$C$73=""),IF($E$73="","— період не заданий —",$E$73),TEXT(DAY($B$73),"00")&"."&TEXT(MONTH($B$73),"00")&"."&YEAR($B$73)&" – "&TEXT(DAY($C$73),"00")&"."&TEXT(MONTH($C$73),"00")&"."&YEAR($C$73))) | EO6: =IF($A$74="","",IF(OR($B$74="",$C$74=""),IF($E$74="","— період не заданий —",$E$74),TEXT(DAY($B$74),"00")&"."&TEXT(MONTH($B$74),"00")&"."&YEAR($B$74)&" – "&TEXT(DAY($C$74),"00")&"."&TEXT(MONTH($C$74),"00")&"."&YEAR($C$74))) | EQ6: =IF($A$75="","",IF(OR($B$75="",$C$75=""),IF($E$75="","— період не заданий —",$E$75),TEXT(DAY($B$75),"00")&"."&TEXT(MONTH($B$75),"00")&"."&YEAR($B$75)&" – "&TEXT(DAY($C$75),"00")&"."&TEXT(MONTH($C$75),"00")&"."&YEAR($C$75))) | ES6: =IF($A$76="","",IF(OR($B$76="",$C$76=""),IF($E$76="","— період не заданий —",$E$76),TEXT(DAY($B$76),"00")&"."&TEXT(MONTH($B$76),"00")&"."&YEAR($B$76)&" – "&TEXT(DAY($C$76),"00")&"."&TEXT(MONTH($C$76),"00")&"."&YEAR($C$76))) | EU6: =IF($A$77="","",IF(OR($B$77="",$C$77=""),IF($E$77="","— період не заданий —",$E$77),TEXT(DAY($B$77),"00")&"."&TEXT(MONTH($B$77),"00")&"."&YEAR($B$77)&" – "&TEXT(DAY($C$77),"00")&"."&TEXT(MONTH($C$77),"00")&"."&YEAR($C$77))) | EW6: =IF($A$78="","",IF(OR($B$78="",$C$78=""),IF($E$78="","— період не заданий —",$E$78),TEXT(DAY($B$78),"00")&"."&TEXT(MONTH($B$78),"00")&"."&YEAR($B$78)&" – "&TEXT(DAY($C$78),"00")&"."&TEXT(MONTH($C$78),"00")&"."&YEAR($C$78))) | EY6: =IF($A$79="","",IF(OR($B$79="",$C$79=""),IF($E$79="","— період не заданий —",$E$79),TEXT(DAY($B$79),"00")&"."&TEXT(MONTH($B$79),"00")&"."&YEAR($B$79)&" – "&TEXT(DAY($C$79),"00")&"."&TEXT(MONTH($C$79),"00")&"."&YEAR($C$79))) | FA6: =IF($A$80="","",IF(OR($B$80="",$C$80=""),IF($E$80="","— період не заданий —",$E$80),TEXT(DAY($B$80),"00")&"."&TEXT(MONTH($B$80),"00")&"."&YEAR($B$80)&" – "&TEXT(DAY($C$80),"00")&"."&TEXT(MONTH($C$80),"00")&"."&YEAR($C$80))) | FC6: =IF($A$81="","",IF(OR($B$81="",$C$81=""),IF($E$81="","— період не заданий —",$E$81),TEXT(DAY($B$81),"00")&"."&TEXT(MONTH($B$81),"00")&"."&YEAR($B$81)&" – "&TEXT(DAY($C$81),"00")&"."&TEXT(MONTH($C$81),"00")&"."&YEAR($C$81))) | FE6: =IF($A$82="","",IF(OR($B$82="",$C$82=""),IF($E$82="","— період не заданий —",$E$82),TEXT(DAY($B$82),"00")&"."&TEXT(MONTH($B$82),"00")&"."&YEAR($B$82)&" – "&TEXT(DAY($C$82),"00")&"."&TEXT(MONTH($C$82),"00")&"."&YEAR($C$82))) | FG6: =IF($A$83="","",IF(OR($B$83="",$C$83=""),IF($E$83="","— період не заданий —",$E$83),TEXT(DAY($B$83),"00")&"."&TEXT(MONTH($B$83),"00")&"."&YEAR($B$83)&" – "&TEXT(DAY($C$83),"00")&"."&TEXT(MONTH($C$83),"00")&"."&YEAR($C$83))) | FI6: =IF($A$84="","",IF(OR($B$84="",$C$84=""),IF($E$84="","— період не заданий —",$E$84),TEXT(DAY($B$84),"00")&"."&TEXT(MONTH($B$84),"00")&"."&YEAR($B$84)&" – "&TEXT(DAY($C$84),"00")&"."&TEXT(MONTH($C$84),"00")&"."&YEAR($C$84))) | FK6: =IF($A$85="","",IF(OR($B$85="",$C$85=""),IF($E$85="","— період не заданий —",$E$85),TEXT(DAY($B$85),"00")&"."&TEXT(MONTH($B$85),"00")&"."&YEAR($B$85)&" – "&TEXT(DAY($C$85),"00")&"."&TEXT(MONTH($C$85),"00")&"."&YEAR($C$85))) | FM6: =IF($A$86="","",IF(OR($B$86="",$C$86=""),IF($E$86="","— період не заданий —",$E$86),TEXT(DAY($B$86),"00")&"."&TEXT(MONTH($B$86),"00")&"."&YEAR($B$86)&" – "&TEXT(DAY($C$86),"00")&"."&TEXT(MONTH($C$86),"00")&"."&YEAR($C$86))) | FO6: =IF($A$87="","",IF(OR($B$87="",$C$87=""),IF($E$87="","— період не заданий —",$E$87),TEXT(DAY($B$87),"00")&"."&TEXT(MONTH($B$87),"00")&"."&YEAR($B$87)&" – "&TEXT(DAY($C$87),"00")&"."&TEXT(MONTH($C$87),"00")&"."&YEAR($C$87))) | FQ6: =IF($A$88="","",IF(OR($B$88="",$C$88=""),IF($E$88="","— період не заданий —",$E$88),TEXT(DAY($B$88),"00")&"."&TEXT(MONTH($B$88),"00")&"."&YEAR($B$88)&" – "&TEXT(DAY($C$88),"00")&"."&TEXT(MONTH($C$88),"00")&"."&YEAR($C$88))) | FS6: =IF($A$89="","",IF(OR($B$89="",$C$89=""),IF($E$89="","— період не заданий —",$E$89),TEXT(DAY($B$89),"00")&"."&TEXT(MONTH($B$89),"00")&"."&YEAR($B$89)&" – "&TEXT(DAY($C$89),"00")&"."&TEXT(MONTH($C$89),"00")&"."&YEAR($C$89))) | FU6: =IF($A$90="","",IF(OR($B$90="",$C$90=""),IF($E$90="","— період не заданий —",$E$90),TEXT(DAY($B$90),"00")&"."&TEXT(MONTH($B$90),"00")&"."&YEAR($B$90)&" – "&TEXT(DAY($C$90),"00")&"."&TEXT(MONTH($C$90),"00")&"."&YEAR($C$90))) | FW6: =IF($A$91="","",IF(OR($B$91="",$C$91=""),IF($E$91="","— період не заданий —",$E$91),TEXT(DAY($B$91),"00")&"."&TEXT(MONTH($B$91),"00")&"."&YEAR($B$91)&" – "&TEXT(DAY($C$91),"00")&"."&TEXT(MONTH($C$91),"00")&"."&YEAR($C$91))) | FY6: =IF($A$92="","",IF(OR($B$92="",$C$92=""),IF($E$92="","— період не заданий —",$E$92),TEXT(DAY($B$92),"00")&"."&TEXT(MONTH($B$92),"00")&"."&YEAR($B$92)&" – "&TEXT(DAY($C$92),"00")&"."&TEXT(MONTH($C$92),"00")&"."&YEAR($C$92))) | GA6: =IF($A$93="","",IF(OR($B$93="",$C$93=""),IF($E$93="","— період не заданий —",$E$93),TEXT(DAY($B$93),"00")&"."&TEXT(MONTH($B$93),"00")&"."&YEAR($B$93)&" – "&TEXT(DAY($C$93),"00")&"."&TEXT(MONTH($C$93),"00")&"."&YEAR($C$93))) | GC6: =IF($A$94="","",IF(OR($B$94="",$C$94=""),IF($E$94="","— період не заданий —",$E$94),TEXT(DAY($B$94),"00")&"."&TEXT(MONTH($B$94),"00")&"."&YEAR($B$94)&" – "&TEXT(DAY($C$94),"00")&"."&TEXT(MONTH($C$94),"00")&"."&YEAR($C$94))) | GE6: =IF($A$95="","",IF(OR($B$95="",$C$95=""),IF($E$95="","— період не заданий —",$E$95),TEXT(DAY($B$95),"00")&"."&TEXT(MONTH($B$95),"00")&"."&YEAR($B$95)&" – "&TEXT(DAY($C$95),"00")&"."&TEXT(MONTH($C$95),"00")&"."&YEAR($C$95))) | GG6: =IF($A$96="","",IF(OR($B$96="",$C$96=""),IF($E$96="","— період не заданий —",$E$96),TEXT(DAY($B$96),"00")&"."&TEXT(MONTH($B$96),"00")&"."&YEAR($B$96)&" – "&TEXT(DAY($C$96),"00")&"."&TEXT(MONTH($C$96),"00")&"."&YEAR($C$96))) | GI6: =IF($A$97="","",IF(OR($B$97="",$C$97=""),IF($E$97="","— період не заданий —",$E$97),TEXT(DAY($B$97),"00")&"."&TEXT(MONTH($B$97),"00")&"."&YEAR($B$97)&" – "&TEXT(DAY($C$97),"00")&"."&TEXT(MONTH($C$97),"00")&"."&YEAR($C$97))) | GK6: =IF($A$98="","",IF(OR($B$98="",$C$98=""),IF($E$98="","— період не заданий —",$E$98),TEXT(DAY($B$98),"00")&"."&TEXT(MONTH($B$98),"00")&"."&YEAR($B$98)&" – "&TEXT(DAY($C$98),"00")&"."&TEXT(MONTH($C$98),"00")&"."&YEAR($C$98))) | GM6: =IF($A$99="","",IF(OR($B$99="",$C$99=""),IF($E$99="","— період не заданий —",$E$99),TEXT(DAY($B$99),"00")&"."&TEXT(MONTH($B$99),"00")&"."&YEAR($B$99)&" – "&TEXT(DAY($C$99),"00")&"."&TEXT(MONTH($C$99),"00")&"."&YEAR($C$99))) | GO6: =IF($A$100="","",IF(OR($B$100="",$C$100=""),IF($E$100="","— період не заданий —",$E$100),TEXT(DAY($B$100),"00")&"."&TEXT(MONTH($B$100),"00")&"."&YEAR($B$100)&" – "&TEXT(DAY($C$100),"00")&"."&TEXT(MONTH($C$100),"00")&"."&YEAR($C$100))) | GQ6: =IF($A$101="","",IF(OR($B$101="",$C$101=""),IF($E$101="","— період не заданий —",$E$101),TEXT(DAY($B$101),"00")&"."&TEXT(MONTH($B$101),"00")&"."&YEAR($B$101)&" – "&TEXT(DAY($C$101),"00")&"."&TEXT(MONTH($C$101),"00")&"."&YEAR($C$101))) | GS6: =IF($A$102="","",IF(OR($B$102="",$C$102=""),IF($E$102="","— період не заданий —",$E$102),TEXT(DAY($B$102),"00")&"."&TEXT(MONTH($B$102),"00")&"."&YEAR($B$102)&" – "&TEXT(DAY($C$102),"00")&"."&TEXT(MONTH($C$102),"00")&"."&YEAR($C$102))) | GU6: =IF($A$103="","",IF(OR($B$103="",$C$103=""),IF($E$103="","— період не заданий —",$E$103),TEXT(DAY($B$103),"00")&"."&TEXT(MONTH($B$103),"00")&"."&YEAR($B$103)&" – "&TEXT(DAY($C$103),"00")&"."&TEXT(MONTH($C$103),"00")&"."&YEAR($C$103))) | GW6: =IF($A$104="","",IF(OR($B$104="",$C$104=""),IF($E$104="","— період не заданий —",$E$104),TEXT(DAY($B$104),"00")&"."&TEXT(MONTH($B$104),"00")&"."&YEAR($B$104)&" – "&TEXT(DAY($C$104),"00")&"."&TEXT(MONTH($C$104),"00")&"."&YEAR($C$104))) | GY6: =IF($A$105="","",IF(OR($B$105="",$C$105=""),IF($E$105="","— період не заданий —",$E$105),TEXT(DAY($B$105),"00")&"."&TEXT(MONTH($B$105),"00")&"."&YEAR($B$105)&" – "&TEXT(DAY($C$105),"00")&"."&TEXT(MONTH($C$105),"00")&"."&YEAR($C$105)))
A7: Осінь 2026 Базовий Прайс | B7: 46266 | C7: 46356 | D7: Неактивний | F7: Знижка на проживання для пакета BBSPA | G7: 0.1 | H7: Статус | I7: =IF($A$6="","",$D$6) -> Неактивний | K7: =IF($A$7="","",$D$7) -> Неактивний | M7: =IF($A$8="","",$D$8) -> Активний | O7: =IF($A$9="","",$D$9) -> Активний | Q7: =IF($A$10="","",$D$10) -> Неактивний | S7: =IF($A$11="","",$D$11) -> Неактивний | U7: =IF($A$12="","",$D$12) -> Активний | W7: =IF($A$13="","",$D$13) -> Неактивний | Y7: =IF($A$14="","",$D$14) -> Неактивний | AA7: =IF($A$15="","",$D$15) -> Неактивний | AC7: =IF($A$16="","",$D$16) -> Неактивний | AE7: =IF($A$17="","",$D$17) -> Неактивний | AG7: =IF($A$18="","",$D$18) | AI7: =IF($A$19="","",$D$19) | AK7: =IF($A$20="","",$D$20) | AM7: =IF($A$21="","",$D$21) | AO7: =IF($A$22="","",$D$22) | AQ7: =IF($A$23="","",$D$23) | AS7: =IF($A$24="","",$D$24) | AU7: =IF($A$25="","",$D$25) | AW7: =IF($A$26="","",$D$26) | AY7: =IF($A$27="","",$D$27) | BA7: =IF($A$28="","",$D$28) | BC7: =IF($A$29="","",$D$29) | BE7: =IF($A$30="","",$D$30) | BG7: =IF($A$31="","",$D$31) | BI7: =IF($A$32="","",$D$32) | BK7: =IF($A$33="","",$D$33) | BM7: =IF($A$34="","",$D$34) | BO7: =IF($A$35="","",$D$35) | BQ7: =IF($A$36="","",$D$36) | BS7: =IF($A$37="","",$D$37) | BU7: =IF($A$38="","",$D$38) | BW7: =IF($A$39="","",$D$39) | BY7: =IF($A$40="","",$D$40) | CA7: =IF($A$41="","",$D$41) | CC7: =IF($A$42="","",$D$42) | CE7: =IF($A$43="","",$D$43) | CG7: =IF($A$44="","",$D$44) | CI7: =IF($A$45="","",$D$45) | CK7: =IF($A$46="","",$D$46) | CM7: =IF($A$47="","",$D$47) | CO7: =IF($A$48="","",$D$48) | CQ7: =IF($A$49="","",$D$49) | CS7: =IF($A$50="","",$D$50) | CU7: =IF($A$51="","",$D$51) | CW7: =IF($A$52="","",$D$52) | CY7: =IF($A$53="","",$D$53) | DA7: =IF($A$54="","",$D$54) | DC7: =IF($A$55="","",$D$55) | DE7: =IF($A$56="","",$D$56) | DG7: =IF($A$57="","",$D$57) | DI7: =IF($A$58="","",$D$58) | DK7: =IF($A$59="","",$D$59) | DM7: =IF($A$60="","",$D$60) | DO7: =IF($A$61="","",$D$61) | DQ7: =IF($A$62="","",$D$62) | DS7: =IF($A$63="","",$D$63) | DU7: =IF($A$64="","",$D$64) | DW7: =IF($A$65="","",$D$65) | DY7: =IF($A$66="","",$D$66) | EA7: =IF($A$67="","",$D$67) | EC7: =IF($A$68="","",$D$68) | EE7: =IF($A$69="","",$D$69) | EG7: =IF($A$70="","",$D$70) | EI7: =IF($A$71="","",$D$71) | EK7: =IF($A$72="","",$D$72) | EM7: =IF($A$73="","",$D$73) | EO7: =IF($A$74="","",$D$74) | EQ7: =IF($A$75="","",$D$75) | ES7: =IF($A$76="","",$D$76) | EU7: =IF($A$77="","",$D$77) | EW7: =IF($A$78="","",$D$78) | EY7: =IF($A$79="","",$D$79) | FA7: =IF($A$80="","",$D$80) | FC7: =IF($A$81="","",$D$81) | FE7: =IF($A$82="","",$D$82) | FG7: =IF($A$83="","",$D$83) | FI7: =IF($A$84="","",$D$84) | FK7: =IF($A$85="","",$D$85) | FM7: =IF($A$86="","",$D$86) | FO7: =IF($A$87="","",$D$87) | FQ7: =IF($A$88="","",$D$88) | FS7: =IF($A$89="","",$D$89) | FU7: =IF($A$90="","",$D$90) | FW7: =IF($A$91="","",$D$91) | FY7: =IF($A$92="","",$D$92) | GA7: =IF($A$93="","",$D$93) | GC7: =IF($A$94="","",$D$94) | GE7: =IF($A$95="","",$D$95) | GG7: =IF($A$96="","",$D$96) | GI7: =IF($A$97="","",$D$97) | GK7: =IF($A$98="","",$D$98) | GM7: =IF($A$99="","",$D$99) | GO7: =IF($A$100="","",$D$100) | GQ7: =IF($A$101="","",$D$101) | GS7: =IF($A$102="","",$D$102) | GU7: =IF($A$103="","",$D$103) | GW7: =IF($A$104="","",$D$104) | GY7: =IF($A$105="","",$D$105)
A8: 0сінь 26 0-10% | B8: 46296 | C8: 46356 | D8: Активний | F8: Проживання з тваринами, грн / ніч | G8: 500 | H8: Оновлено | I8: =IF($A$6="","",$E$6) -> 0 | K8: =IF($A$7="","",$E$7) -> 0 | M8: =IF($A$8="","",$E$8) -> 0 | O8: =IF($A$9="","",$E$9) -> до 15.09 та 26.10 -01.11 | Q8: =IF($A$10="","",$E$10) -> 0 | S8: =IF($A$11="","",$E$11) -> 0 | U8: =IF($A$12="","",$E$12) -> 0 | W8: =IF($A$13="","",$E$13) -> 0 | Y8: =IF($A$14="","",$E$14) -> 0 | AA8: =IF($A$15="","",$E$15) -> 0 | AC8: =IF($A$16="","",$E$16) -> 0 | AE8: =IF($A$17="","",$E$17) -> 0 | AG8: =IF($A$18="","",$E$18) | AI8: =IF($A$19="","",$E$19) | AK8: =IF($A$20="","",$E$20) | AM8: =IF($A$21="","",$E$21) | AO8: =IF($A$22="","",$E$22) | AQ8: =IF($A$23="","",$E$23) | AS8: =IF($A$24="","",$E$24) | AU8: =IF($A$25="","",$E$25) | AW8: =IF($A$26="","",$E$26) | AY8: =IF($A$27="","",$E$27) | BA8: =IF($A$28="","",$E$28) | BC8: =IF($A$29="","",$E$29) | BE8: =IF($A$30="","",$E$30) | BG8: =IF($A$31="","",$E$31) | BI8: =IF($A$32="","",$E$32) | BK8: =IF($A$33="","",$E$33) | BM8: =IF($A$34="","",$E$34) | BO8: =IF($A$35="","",$E$35) | BQ8: =IF($A$36="","",$E$36) | BS8: =IF($A$37="","",$E$37) | BU8: =IF($A$38="","",$E$38) | BW8: =IF($A$39="","",$E$39) | BY8: =IF($A$40="","",$E$40) | CA8: =IF($A$41="","",$E$41) | CC8: =IF($A$42="","",$E$42) | CE8: =IF($A$43="","",$E$43) | CG8: =IF($A$44="","",$E$44) | CI8: =IF($A$45="","",$E$45) | CK8: =IF($A$46="","",$E$46) | CM8: =IF($A$47="","",$E$47) | CO8: =IF($A$48="","",$E$48) | CQ8: =IF($A$49="","",$E$49) | CS8: =IF($A$50="","",$E$50) | CU8: =IF($A$51="","",$E$51) | CW8: =IF($A$52="","",$E$52) | CY8: =IF($A$53="","",$E$53) | DA8: =IF($A$54="","",$E$54) | DC8: =IF($A$55="","",$E$55) | DE8: =IF($A$56="","",$E$56) | DG8: =IF($A$57="","",$E$57) | DI8: =IF($A$58="","",$E$58) | DK8: =IF($A$59="","",$E$59) | DM8: =IF($A$60="","",$E$60) | DO8: =IF($A$61="","",$E$61) | DQ8: =IF($A$62="","",$E$62) | DS8: =IF($A$63="","",$E$63) | DU8: =IF($A$64="","",$E$64) | DW8: =IF($A$65="","",$E$65) | DY8: =IF($A$66="","",$E$66) | EA8: =IF($A$67="","",$E$67) | EC8: =IF($A$68="","",$E$68) | EE8: =IF($A$69="","",$E$69) | EG8: =IF($A$70="","",$E$70) | EI8: =IF($A$71="","",$E$71) | EK8: =IF($A$72="","",$E$72) | EM8: =IF($A$73="","",$E$73) | EO8: =IF($A$74="","",$E$74) | EQ8: =IF($A$75="","",$E$75) | ES8: =IF($A$76="","",$E$76) | EU8: =IF($A$77="","",$E$77) | EW8: =IF($A$78="","",$E$78) | EY8: =IF($A$79="","",$E$79) | FA8: =IF($A$80="","",$E$80) | FC8: =IF($A$81="","",$E$81) | FE8: =IF($A$82="","",$E$82) | FG8: =IF($A$83="","",$E$83) | FI8: =IF($A$84="","",$E$84) | FK8: =IF($A$85="","",$E$85) | FM8: =IF($A$86="","",$E$86) | FO8: =IF($A$87="","",$E$87) | FQ8: =IF($A$88="","",$E$88) | FS8: =IF($A$89="","",$E$89) | FU8: =IF($A$90="","",$E$90) | FW8: =IF($A$91="","",$E$91) | FY8: =IF($A$92="","",$E$92) | GA8: =IF($A$93="","",$E$93) | GC8: =IF($A$94="","",$E$94) | GE8: =IF($A$95="","",$E$95) | GG8: =IF($A$96="","",$E$96) | GI8: =IF($A$97="","",$E$97) | GK8: =IF($A$98="","",$E$98) | GM8: =IF($A$99="","",$E$99) | GO8: =IF($A$100="","",$E$100) | GQ8: =IF($A$101="","",$E$101) | GS8: =IF($A$102="","",$E$102) | GU8: =IF($A$103="","",$E$103) | GW8: =IF($A$104="","",$E$104) | GY8: =IF($A$105="","",$E$105)
A9: Осінь 26 канікули 0-10% | D9: Активний | E9: до 15.09 та 26.10 -01.11 | F9: Еталонний прайс-лист для Δ (варіант B) | G9: Осінь 2026 Базовий Прайс
A10: 0сінь 26 10-20% | D10: Неактивний | F10: Вихідні починаються з дня тижня (1=Пн … 7=Нд) | G10: 5 | H10: БАЗОВІ RO-ЦІНИ — ЗА БАЗОВОЮ МІСТКІСТЮ КАТЕГОРІЇ
A11: Осінь 26 канікули 10-20% | D11: Неактивний | F11: Доплата за додаткове місце задається по кожній категорії у «Довіднику категорій». | H11: Категорія | I11: RO будні | J11: RO вихідні | K11: RO будні | L11: RO вихідні | M11: RO будні | N11: RO вихідні | O11: RO будні | P11: RO вихідні | Q11: RO будні | R11: RO вихідні | S11: RO будні | T11: RO вихідні | U11: RO будні | V11: RO вихідні | W11: RO будні | X11: RO вихідні | Y11: RO будні | Z11: RO вихідні | AA11: RO будні | AB11: RO вихідні | AC11: RO будні | AD11: RO вихідні | AE11: RO будні | AF11: RO вихідні | AG11: RO будні | AH11: RO вихідні | AI11: RO будні | AJ11: RO вихідні | AK11: RO будні | AL11: RO вихідні | AM11: RO будні | AN11: RO вихідні | AO11: RO будні | AP11: RO вихідні | AQ11: RO будні | AR11: RO вихідні | AS11: RO будні | AT11: RO вихідні | AU11: RO будні | AV11: RO вихідні | AW11: RO будні | AX11: RO вихідні | AY11: RO будні | AZ11: RO вихідні | BA11: RO будні | BB11: RO вихідні | BC11: RO будні | BD11: RO вихідні | BE11: RO будні | BF11: RO вихідні | BG11: RO будні | BH11: RO вихідні | BI11: RO будні | BJ11: RO вихідні | BK11: RO будні | BL11: RO вихідні | BM11: RO будні | BN11: RO вихідні | BO11: RO будні | BP11: RO вихідні | BQ11: RO будні | BR11: RO вихідні | BS11: RO будні | BT11: RO вихідні | BU11: RO будні | BV11: RO вихідні | BW11: RO будні | BX11: RO вихідні | BY11: RO будні | BZ11: RO вихідні | CA11: RO будні | CB11: RO вихідні | CC11: RO будні | CD11: RO вихідні | CE11: RO будні | CF11: RO вихідні | CG11: RO будні | CH11: RO вихідні | CI11: RO будні | CJ11: RO вихідні | CK11: RO будні | CL11: RO вихідні | CM11: RO будні | CN11: RO вихідні | CO11: RO будні | CP11: RO вихідні | CQ11: RO будні | CR11: RO вихідні | CS11: RO будні | CT11: RO вихідні | CU11: RO будні | CV11: RO вихідні | CW11: RO будні | CX11: RO вихідні | CY11: RO будні | CZ11: RO вихідні | DA11: RO будні | DB11: RO вихідні | DC11: RO будні | DD11: RO вихідні | DE11: RO будні | DF11: RO вихідні | DG11: RO будні | DH11: RO вихідні | DI11: RO будні | DJ11: RO вихідні | DK11: RO будні | DL11: RO вихідні | DM11: RO будні | DN11: RO вихідні | DO11: RO будні | DP11: RO вихідні | DQ11: RO будні | DR11: RO вихідні | DS11: RO будні | DT11: RO вихідні | DU11: RO будні | DV11: RO вихідні | DW11: RO будні | DX11: RO вихідні | DY11: RO будні | DZ11: RO вихідні | EA11: RO будні | EB11: RO вихідні | EC11: RO будні | ED11: RO вихідні | EE11: RO будні | EF11: RO вихідні | EG11: RO будні | EH11: RO вихідні | EI11: RO будні | EJ11: RO вихідні | EK11: RO будні | EL11: RO вихідні | EM11: RO будні | EN11: RO вихідні | EO11: RO будні | EP11: RO вихідні | EQ11: RO будні | ER11: RO вихідні | ES11: RO будні | ET11: RO вихідні | EU11: RO будні | EV11: RO вихідні | EW11: RO будні | EX11: RO вихідні | EY11: RO будні | EZ11: RO вихідні | FA11: RO будні | FB11: RO вихідні | FC11: RO будні | FD11: RO вихідні | FE11: RO будні | FF11: RO вихідні | FG11: RO будні | FH11: RO вихідні | FI11: RO будні | FJ11: RO вихідні | FK11: RO будні | FL11: RO вихідні | FM11: RO будні | FN11: RO вихідні | FO11: RO будні | FP11: RO вихідні | FQ11: RO будні | FR11: RO вихідні | FS11: RO будні | FT11: RO вихідні | FU11: RO будні | FV11: RO вихідні | FW11: RO будні | FX11: RO вихідні | FY11: RO будні | FZ11: RO вихідні | GA11: RO будні | GB11: RO вихідні | GC11: RO будні | GD11: RO вихідні | GE11: RO будні | GF11: RO вихідні | GG11: RO будні | GH11: RO вихідні | GI11: RO будні | GJ11: RO вихідні | GK11: RO будні | GL11: RO вихідні | GM11: RO будні | GN11: RO вихідні | GO11: RO будні | GP11: RO вихідні | GQ11: RO будні | GR11: RO вихідні | GS11: RO будні | GT11: RO вихідні | GU11: RO будні | GV11: RO вихідні | GW11: RO будні | GX11: RO вихідні | GY11: RO будні | GZ11: RO вихідні
A12: 0сінь 26 20-30% | B12: 46281 | C12: 46295 | D12: Активний | F12: 3. ТАРИФИ — ЗНИЖКИ НА ПРОЖИВАННЯ | H12: =IF('Довідник категорій'!B5="","",'Довідник категорій'!B5) -> Classic Chalet | I12: 3500 | J12: 4000 | K12: 6000 | L12: 6500 | M12: 4200 | N12: 4700 | O12: 5100 | P12: 5600 | Q12: 4499.88 | R12: 4999.88 | S12: 5464.14 | T12: 5964.14 | U12: 4821.1714 | V12: 5321.1714 | W12: 5854.2796 | X12: 6354.2796 | Y12: 5165.4031 | Z12: 5665.4031 | AA12: 6272.2752 | AB12: 6772.2752 | AC12: 5534.2129 | AD12: 6034.2129 | AE12: 6720.1156 | AF12: 7220.1156
A13: Осінь 26 канікули 20-30% | D13: Неактивний | F13: Тариф | G13: Знижка | H13: =IF('Довідник категорій'!B6="","",'Довідник категорій'!B6) -> Forest View Chalet | I13: 4000 | J13: 4500 | K13: 6500 | L13: 6600 | M13: 4550 | N13: 5150 | O13: 5525 | P13: 6125 | Q13: 4874.87 | R13: 5474.87 | S13: 5919.485 | T13: 6519.485 | U13: 5222.9357 | V13: 5822.9357 | W13: 6342.1362 | X13: 6942.1362 | Y13: 5595.8533 | Z13: 6195.8533 | AA13: 6794.9648 | AB13: 7394.9648 | AC13: 5995.3973 | AD13: 6595.3973 | AE13: 7280.1252 | AF13: 7880.1252
A14: 0сінь 26 30-40% | D14: Неактивний | F14: Rack Rate | G14: 0 | H14: =IF('Довідник категорій'!B7="","",'Довідник категорій'!B7) -> Premium Chalet | I14: 7000 | J14: 9000 | K14: 11100 | L14: 13100 | M14: 7770 | N14: 9770 | O14: 9435 | P14: 11435 | Q14: 8324.778 | R14: 10324.778 | S14: 10108.659 | T14: 12108.659 | U14: 8919.1671 | V14: 10919.167 | W14: 10830.417 | X14: 12830.417 | Y14: 9555.9957 | Z14: 11555.996 | AA14: 11603.709 | AB14: 13603.709 | AC14: 10238.294 | AD14: 12238.294 | AE14: 12432.214 | AF14: 14432.214
A15: Осінь 26 канікули 30-40% | D15: Неактивний | F15: Раннє бронювання -10% | G15: 0.1 | H15: =IF('Довідник категорій'!B8="","",'Довідник категорій'!B8)
A16: 0сінь 26 40-50% | D16: Неактивний | F16: NON REF -20% | G16: 0.2 | H16: =IF('Довідник категорій'!B9="","",'Довідник категорій'!B9)
A17: Осінь 26 канікули 40-50% | D17: Неактивний | F17: HAPPY -15% | G17: 0.15 | H17: =IF('Довідник категорій'!B10="","",'Довідник категорій'!B10)
F18: Військовий -30% | G18: 0.3 | H18: =IF('Довідник категорій'!B11="","",'Довідник категорій'!B11)
F19: Інвестор -70% | G19: 0.7 | H19: =IF('Довідник категорій'!B12="","",'Довідник категорій'!B12)
H20: =IF('Довідник категорій'!B13="","",'Довідник категорій'!B13)
H21: =IF('Довідник категорій'!B14="","",'Довідник категорій'!B14)
H22: =IF('Довідник категорій'!B15="","",'Довідник категорій'!B15)
F23: 4. ДОВІДНИКИ ДЛЯ ВИПАДАЮЧИХ СПИСКІВ | H23: =IF('Довідник категорій'!B16="","",'Довідник категорій'!B16)
F24: Пакети
F25: RO | H25: Δ МІЖ КАТЕГОРІЯМИ (варіант A)
F26: BB | H26: Порівняння з попередньою категорією | I26: Δ грн | J26: Δ % | K26: Δ грн | L26: Δ % | M26: Δ грн | N26: Δ % | O26: Δ грн | P26: Δ % | Q26: Δ грн | R26: Δ % | S26: Δ грн | T26: Δ % | U26: Δ грн | V26: Δ % | W26: Δ грн | X26: Δ % | Y26: Δ грн | Z26: Δ % | AA26: Δ грн | AB26: Δ % | AC26: Δ грн | AD26: Δ % | AE26: Δ грн | AF26: Δ % | AG26: Δ грн | AH26: Δ % | AI26: Δ грн | AJ26: Δ % | AK26: Δ грн | AL26: Δ % | AM26: Δ грн | AN26: Δ % | AO26: Δ грн | AP26: Δ % | AQ26: Δ грн | AR26: Δ % | AS26: Δ грн | AT26: Δ % | AU26: Δ грн | AV26: Δ % | AW26: Δ грн | AX26: Δ % | AY26: Δ грн | AZ26: Δ % | BA26: Δ грн | BB26: Δ % | BC26: Δ грн | BD26: Δ % | BE26: Δ грн | BF26: Δ % | BG26: Δ грн | BH26: Δ % | BI26: Δ грн | BJ26: Δ % | BK26: Δ грн | BL26: Δ % | BM26: Δ грн | BN26: Δ % | BO26: Δ грн | BP26: Δ % | BQ26: Δ грн | BR26: Δ % | BS26: Δ грн | BT26: Δ % | BU26: Δ грн | BV26: Δ % | BW26: Δ грн | BX26: Δ % | BY26: Δ грн | BZ26: Δ % | CA26: Δ грн | CB26: Δ % | CC26: Δ грн | CD26: Δ % | CE26: Δ грн | CF26: Δ % | CG26: Δ грн | CH26: Δ % | CI26: Δ грн | CJ26: Δ % | CK26: Δ грн | CL26: Δ % | CM26: Δ грн | CN26: Δ % | CO26: Δ грн | CP26: Δ % | CQ26: Δ грн | CR26: Δ % | CS26: Δ грн | CT26: Δ % | CU26: Δ грн | CV26: Δ % | CW26: Δ грн | CX26: Δ % | CY26: Δ грн | CZ26: Δ % | DA26: Δ грн | DB26: Δ % | DC26: Δ грн | DD26: Δ % | DE26: Δ грн | DF26: Δ % | DG26: Δ грн | DH26: Δ % | DI26: Δ грн | DJ26: Δ % | DK26: Δ грн | DL26: Δ % | DM26: Δ грн | DN26: Δ % | DO26: Δ грн | DP26: Δ % | DQ26: Δ грн | DR26: Δ % | DS26: Δ грн | DT26: Δ % | DU26: Δ грн | DV26: Δ % | DW26: Δ грн | DX26: Δ % | DY26: Δ грн | DZ26: Δ % | EA26: Δ грн | EB26: Δ % | EC26: Δ грн | ED26: Δ % | EE26: Δ грн | EF26: Δ % | EG26: Δ грн | EH26: Δ % | EI26: Δ грн | EJ26: Δ % | EK26: Δ грн | EL26: Δ % | EM26: Δ грн | EN26: Δ % | EO26: Δ грн | EP26: Δ % | EQ26: Δ грн | ER26: Δ % | ES26: Δ грн | ET26: Δ % | EU26: Δ грн | EV26: Δ % | EW26: Δ грн | EX26: Δ % | EY26: Δ грн | EZ26: Δ % | FA26: Δ грн | FB26: Δ % | FC26: Δ грн | FD26: Δ % | FE26: Δ грн | FF26: Δ % | FG26: Δ грн | FH26: Δ % | FI26: Δ грн | FJ26: Δ % | FK26: Δ грн | FL26: Δ % | FM26: Δ грн | FN26: Δ % | FO26: Δ грн | FP26: Δ % | FQ26: Δ грн | FR26: Δ % | FS26: Δ грн | FT26: Δ % | FU26: Δ грн | FV26: Δ % | FW26: Δ грн | FX26: Δ % | FY26: Δ грн | FZ26: Δ % | GA26: Δ грн | GB26: Δ % | GC26: Δ грн | GD26: Δ % | GE26: Δ грн | GF26: Δ % | GG26: Δ грн | GH26: Δ % | GI26: Δ грн | GJ26: Δ % | GK26: Δ грн | GL26: Δ % | GM26: Δ грн | GN26: Δ % | GO26: Δ грн | GP26: Δ % | GQ26: Δ грн | GR26: Δ % | GS26: Δ грн | GT26: Δ % | GU26: Δ грн | GV26: Δ % | GW26: Δ грн | GX26: Δ % | GY26: Δ грн | GZ26: Δ %
F27: BBSPA | H27: =""
F28: ROSPA | H28: =IF(OR('Довідник категорій'!B6="",'Довідник категорій'!B5=""),"",'Довідник категорій'!B6&" ↔ "&'Довідник категорій'!B5) -> Forest View Chalet ↔ Classic Chalet | I28: =IF(OR(I13="",I12=""),"",I13-I12) -> 500 | J28: =IF(OR(I13="",I12="",I12=0),"",I13/I12-1) -> 0.14285714 | K28: =IF(OR(K13="",K12=""),"",K13-K12) -> 500 | L28: =IF(OR(K13="",K12="",K12=0),"",K13/K12-1) -> 0.083333333 | M28: =IF(OR(M13="",M12=""),"",M13-M12) -> 350 | N28: =IF(OR(M13="",M12="",M12=0),"",M13/M12-1) -> 0.083333333 | O28: =IF(OR(O13="",O12=""),"",O13-O12) -> 425 | P28: =IF(OR(O13="",O12="",O12=0),"",O13/O12-1) -> 0.083333333 | Q28: =IF(OR(Q13="",Q12=""),"",Q13-Q12) -> 374.99 | R28: =IF(OR(Q13="",Q12="",Q12=0),"",Q13/Q12-1) -> 0.083333333 | S28: =IF(OR(S13="",S12=""),"",S13-S12) -> 455.345 | T28: =IF(OR(S13="",S12="",S12=0),"",S13/S12-1) -> 0.083333333 | U28: =IF(OR(U13="",U12=""),"",U13-U12) -> 401.76429 | V28: =IF(OR(U13="",U12="",U12=0),"",U13/U12-1) -> 0.083333333 | W28: =IF(OR(W13="",W12=""),"",W13-W12) -> 487.85663 | X28: =IF(OR(W13="",W12="",W12=0),"",W13/W12-1) -> 0.083333333 | Y28: =IF(OR(Y13="",Y12=""),"",Y13-Y12) -> 430.45026 | Z28: =IF(OR(Y13="",Y12="",Y12=0),"",Y13/Y12-1) -> 0.083333333 | AA28: =IF(OR(AA13="",AA12=""),"",AA13-AA12) -> 522.6896 | AB28: =IF(OR(AA13="",AA12="",AA12=0),"",AA13/AA12-1) -> 0.083333333 | AC28: =IF(OR(AC13="",AC12=""),"",AC13-AC12) -> 461.1844 | AD28: =IF(OR(AC13="",AC12="",AC12=0),"",AC13/AC12-1) -> 0.083333333 | AE28: =IF(OR(AE13="",AE12=""),"",AE13-AE12) -> 560.00963 | AF28: =IF(OR(AE13="",AE12="",AE12=0),"",AE13/AE12-1) -> 0.083333333 | AG28: =IF(OR(AG13="",AG12=""),"",AG13-AG12) | AH28: =IF(OR(AG13="",AG12="",AG12=0),"",AG13/AG12-1) | AI28: =IF(OR(AI13="",AI12=""),"",AI13-AI12) | AJ28: =IF(OR(AI13="",AI12="",AI12=0),"",AI13/AI12-1) | AK28: =IF(OR(AK13="",AK12=""),"",AK13-AK12) | AL28: =IF(OR(AK13="",AK12="",AK12=0),"",AK13/AK12-1) | AM28: =IF(OR(AM13="",AM12=""),"",AM13-AM12) | AN28: =IF(OR(AM13="",AM12="",AM12=0),"",AM13/AM12-1) | AO28: =IF(OR(AO13="",AO12=""),"",AO13-AO12) | AP28: =IF(OR(AO13="",AO12="",AO12=0),"",AO13/AO12-1) | AQ28: =IF(OR(AQ13="",AQ12=""),"",AQ13-AQ12) | AR28: =IF(OR(AQ13="",AQ12="",AQ12=0),"",AQ13/AQ12-1) | AS28: =IF(OR(AS13="",AS12=""),"",AS13-AS12) | AT28: =IF(OR(AS13="",AS12="",AS12=0),"",AS13/AS12-1) | AU28: =IF(OR(AU13="",AU12=""),"",AU13-AU12) | AV28: =IF(OR(AU13="",AU12="",AU12=0),"",AU13/AU12-1) | AW28: =IF(OR(AW13="",AW12=""),"",AW13-AW12) | AX28: =IF(OR(AW13="",AW12="",AW12=0),"",AW13/AW12-1) | AY28: =IF(OR(AY13="",AY12=""),"",AY13-AY12) | AZ28: =IF(OR(AY13="",AY12="",AY12=0),"",AY13/AY12-1) | BA28: =IF(OR(BA13="",BA12=""),"",BA13-BA12) | BB28: =IF(OR(BA13="",BA12="",BA12=0),"",BA13/BA12-1) | BC28: =IF(OR(BC13="",BC12=""),"",BC13-BC12) | BD28: =IF(OR(BC13="",BC12="",BC12=0),"",BC13/BC12-1) | BE28: =IF(OR(BE13="",BE12=""),"",BE13-BE12) | BF28: =IF(OR(BE13="",BE12="",BE12=0),"",BE13/BE12-1) | BG28: =IF(OR(BG13="",BG12=""),"",BG13-BG12) | BH28: =IF(OR(BG13="",BG12="",BG12=0),"",BG13/BG12-1) | BI28: =IF(OR(BI13="",BI12=""),"",BI13-BI12) | BJ28: =IF(OR(BI13="",BI12="",BI12=0),"",BI13/BI12-1) | BK28: =IF(OR(BK13="",BK12=""),"",BK13-BK12) | BL28: =IF(OR(BK13="",BK12="",BK12=0),"",BK13/BK12-1) | BM28: =IF(OR(BM13="",BM12=""),"",BM13-BM12) | BN28: =IF(OR(BM13="",BM12="",BM12=0),"",BM13/BM12-1) | BO28: =IF(OR(BO13="",BO12=""),"",BO13-BO12) | BP28: =IF(OR(BO13="",BO12="",BO12=0),"",BO13/BO12-1) | BQ28: =IF(OR(BQ13="",BQ12=""),"",BQ13-BQ12) | BR28: =IF(OR(BQ13="",BQ12="",BQ12=0),"",BQ13/BQ12-1) | BS28: =IF(OR(BS13="",BS12=""),"",BS13-BS12) | BT28: =IF(OR(BS13="",BS12="",BS12=0),"",BS13/BS12-1) | BU28: =IF(OR(BU13="",BU12=""),"",BU13-BU12) | BV28: =IF(OR(BU13="",BU12="",BU12=0),"",BU13/BU12-1) | BW28: =IF(OR(BW13="",BW12=""),"",BW13-BW12) | BX28: =IF(OR(BW13="",BW12="",BW12=0),"",BW13/BW12-1) | BY28: =IF(OR(BY13="",BY12=""),"",BY13-BY12) | BZ28: =IF(OR(BY13="",BY12="",BY12=0),"",BY13/BY12-1) | CA28: =IF(OR(CA13="",CA12=""),"",CA13-CA12) | CB28: =IF(OR(CA13="",CA12="",CA12=0),"",CA13/CA12-1) | CC28: =IF(OR(CC13="",CC12=""),"",CC13-CC12) | CD28: =IF(OR(CC13="",CC12="",CC12=0),"",CC13/CC12-1) | CE28: =IF(OR(CE13="",CE12=""),"",CE13-CE12) | CF28: =IF(OR(CE13="",CE12="",CE12=0),"",CE13/CE12-1) | CG28: =IF(OR(CG13="",CG12=""),"",CG13-CG12) | CH28: =IF(OR(CG13="",CG12="",CG12=0),"",CG13/CG12-1) | CI28: =IF(OR(CI13="",CI12=""),"",CI13-CI12) | CJ28: =IF(OR(CI13="",CI12="",CI12=0),"",CI13/CI12-1) | CK28: =IF(OR(CK13="",CK12=""),"",CK13-CK12) | CL28: =IF(OR(CK13="",CK12="",CK12=0),"",CK13/CK12-1) | CM28: =IF(OR(CM13="",CM12=""),"",CM13-CM12) | CN28: =IF(OR(CM13="",CM12="",CM12=0),"",CM13/CM12-1) | CO28: =IF(OR(CO13="",CO12=""),"",CO13-CO12) | CP28: =IF(OR(CO13="",CO12="",CO12=0),"",CO13/CO12-1) | CQ28: =IF(OR(CQ13="",CQ12=""),"",CQ13-CQ12) | CR28: =IF(OR(CQ13="",CQ12="",CQ12=0),"",CQ13/CQ12-1) | CS28: =IF(OR(CS13="",CS12=""),"",CS13-CS12) | CT28: =IF(OR(CS13="",CS12="",CS12=0),"",CS13/CS12-1) | CU28: =IF(OR(CU13="",CU12=""),"",CU13-CU12) | CV28: =IF(OR(CU13="",CU12="",CU12=0),"",CU13/CU12-1) | CW28: =IF(OR(CW13="",CW12=""),"",CW13-CW12) | CX28: =IF(OR(CW13="",CW12="",CW12=0),"",CW13/CW12-1) | CY28: =IF(OR(CY13="",CY12=""),"",CY13-CY12) | CZ28: =IF(OR(CY13="",CY12="",CY12=0),"",CY13/CY12-1) | DA28: =IF(OR(DA13="",DA12=""),"",DA13-DA12) | DB28: =IF(OR(DA13="",DA12="",DA12=0),"",DA13/DA12-1) | DC28: =IF(OR(DC13="",DC12=""),"",DC13-DC12) | DD28: =IF(OR(DC13="",DC12="",DC12=0),"",DC13/DC12-1) | DE28: =IF(OR(DE13="",DE12=""),"",DE13-DE12) | DF28: =IF(OR(DE13="",DE12="",DE12=0),"",DE13/DE12-1) | DG28: =IF(OR(DG13="",DG12=""),"",DG13-DG12) | DH28: =IF(OR(DG13="",DG12="",DG12=0),"",DG13/DG12-1) | DI28: =IF(OR(DI13="",DI12=""),"",DI13-DI12) | DJ28: =IF(OR(DI13="",DI12="",DI12=0),"",DI13/DI12-1) | DK28: =IF(OR(DK13="",DK12=""),"",DK13-DK12) | DL28: =IF(OR(DK13="",DK12="",DK12=0),"",DK13/DK12-1) | DM28: =IF(OR(DM13="",DM12=""),"",DM13-DM12) | DN28: =IF(OR(DM13="",DM12="",DM12=0),"",DM13/DM12-1) | DO28: =IF(OR(DO13="",DO12=""),"",DO13-DO12) | DP28: =IF(OR(DO13="",DO12="",DO12=0),"",DO13/DO12-1) | DQ28: =IF(OR(DQ13="",DQ12=""),"",DQ13-DQ12) | DR28: =IF(OR(DQ13="",DQ12="",DQ12=0),"",DQ13/DQ12-1) | DS28: =IF(OR(DS13="",DS12=""),"",DS13-DS12) | DT28: =IF(OR(DS13="",DS12="",DS12=0),"",DS13/DS12-1) | DU28: =IF(OR(DU13="",DU12=""),"",DU13-DU12) | DV28: =IF(OR(DU13="",DU12="",DU12=0),"",DU13/DU12-1) | DW28: =IF(OR(DW13="",DW12=""),"",DW13-DW12) | DX28: =IF(OR(DW13="",DW12="",DW12=0),"",DW13/DW12-1) | DY28: =IF(OR(DY13="",DY12=""),"",DY13-DY12) | DZ28: =IF(OR(DY13="",DY12="",DY12=0),"",DY13/DY12-1) | EA28: =IF(OR(EA13="",EA12=""),"",EA13-EA12) | EB28: =IF(OR(EA13="",EA12="",EA12=0),"",EA13/EA12-1) | EC28: =IF(OR(EC13="",EC12=""),"",EC13-EC12) | ED28: =IF(OR(EC13="",EC12="",EC12=0),"",EC13/EC12-1) | EE28: =IF(OR(EE13="",EE12=""),"",EE13-EE12) | EF28: =IF(OR(EE13="",EE12="",EE12=0),"",EE13/EE12-1) | EG28: =IF(OR(EG13="",EG12=""),"",EG13-EG12) | EH28: =IF(OR(EG13="",EG12="",EG12=0),"",EG13/EG12-1) | EI28: =IF(OR(EI13="",EI12=""),"",EI13-EI12) | EJ28: =IF(OR(EI13="",EI12="",EI12=0),"",EI13/EI12-1) | EK28: =IF(OR(EK13="",EK12=""),"",EK13-EK12) | EL28: =IF(OR(EK13="",EK12="",EK12=0),"",EK13/EK12-1) | EM28: =IF(OR(EM13="",EM12=""),"",EM13-EM12) | EN28: =IF(OR(EM13="",EM12="",EM12=0),"",EM13/EM12-1) | EO28: =IF(OR(EO13="",EO12=""),"",EO13-EO12) | EP28: =IF(OR(EO13="",EO12="",EO12=0),"",EO13/EO12-1) | EQ28: =IF(OR(EQ13="",EQ12=""),"",EQ13-EQ12) | ER28: =IF(OR(EQ13="",EQ12="",EQ12=0),"",EQ13/EQ12-1) | ES28: =IF(OR(ES13="",ES12=""),"",ES13-ES12) | ET28: =IF(OR(ES13="",ES12="",ES12=0),"",ES13/ES12-1) | EU28: =IF(OR(EU13="",EU12=""),"",EU13-EU12) | EV28: =IF(OR(EU13="",EU12="",EU12=0),"",EU13/EU12-1) | EW28: =IF(OR(EW13="",EW12=""),"",EW13-EW12) | EX28: =IF(OR(EW13="",EW12="",EW12=0),"",EW13/EW12-1) | EY28: =IF(OR(EY13="",EY12=""),"",EY13-EY12) | EZ28: =IF(OR(EY13="",EY12="",EY12=0),"",EY13/EY12-1) | FA28: =IF(OR(FA13="",FA12=""),"",FA13-FA12) | FB28: =IF(OR(FA13="",FA12="",FA12=0),"",FA13/FA12-1) | FC28: =IF(OR(FC13="",FC12=""),"",FC13-FC12) | FD28: =IF(OR(FC13="",FC12="",FC12=0),"",FC13/FC12-1) | FE28: =IF(OR(FE13="",FE12=""),"",FE13-FE12) | FF28: =IF(OR(FE13="",FE12="",FE12=0),"",FE13/FE12-1) | FG28: =IF(OR(FG13="",FG12=""),"",FG13-FG12) | FH28: =IF(OR(FG13="",FG12="",FG12=0),"",FG13/FG12-1) | FI28: =IF(OR(FI13="",FI12=""),"",FI13-FI12) | FJ28: =IF(OR(FI13="",FI12="",FI12=0),"",FI13/FI12-1) | FK28: =IF(OR(FK13="",FK12=""),"",FK13-FK12) | FL28: =IF(OR(FK13="",FK12="",FK12=0),"",FK13/FK12-1) | FM28: =IF(OR(FM13="",FM12=""),"",FM13-FM12) | FN28: =IF(OR(FM13="",FM12="",FM12=0),"",FM13/FM12-1) | FO28: =IF(OR(FO13="",FO12=""),"",FO13-FO12) | FP28: =IF(OR(FO13="",FO12="",FO12=0),"",FO13/FO12-1) | FQ28: =IF(OR(FQ13="",FQ12=""),"",FQ13-FQ12) | FR28: =IF(OR(FQ13="",FQ12="",FQ12=0),"",FQ13/FQ12-1) | FS28: =IF(OR(FS13="",FS12=""),"",FS13-FS12) | FT28: =IF(OR(FS13="",FS12="",FS12=0),"",FS13/FS12-1) | FU28: =IF(OR(FU13="",FU12=""),"",FU13-FU12) | FV28: =IF(OR(FU13="",FU12="",FU12=0),"",FU13/FU12-1) | FW28: =IF(OR(FW13="",FW12=""),"",FW13-FW12) | FX28: =IF(OR(FW13="",FW12="",FW12=0),"",FW13/FW12-1) | FY28: =IF(OR(FY13="",FY12=""),"",FY13-FY12) | FZ28: =IF(OR(FY13="",FY12="",FY12=0),"",FY13/FY12-1) | GA28: =IF(OR(GA13="",GA12=""),"",GA13-GA12) | GB28: =IF(OR(GA13="",GA12="",GA12=0),"",GA13/GA12-1) | GC28: =IF(OR(GC13="",GC12=""),"",GC13-GC12) | GD28: =IF(OR(GC13="",GC12="",GC12=0),"",GC13/GC12-1) | GE28: =IF(OR(GE13="",GE12=""),"",GE13-GE12) | GF28: =IF(OR(GE13="",GE12="",GE12=0),"",GE13/GE12-1) | GG28: =IF(OR(GG13="",GG12=""),"",GG13-GG12) | GH28: =IF(OR(GG13="",GG12="",GG12=0),"",GG13/GG12-1) | GI28: =IF(OR(GI13="",GI12=""),"",GI13-GI12) | GJ28: =IF(OR(GI13="",GI12="",GI12=0),"",GI13/GI12-1) | GK28: =IF(OR(GK13="",GK12=""),"",GK13-GK12) | GL28: =IF(OR(GK13="",GK12="",GK12=0),"",GK13/GK12-1) | GM28: =IF(OR(GM13="",GM12=""),"",GM13-GM12) | GN28: =IF(OR(GM13="",GM12="",GM12=0),"",GM13/GM12-1) | GO28: =IF(OR(GO13="",GO12=""),"",GO13-GO12) | GP28: =IF(OR(GO13="",GO12="",GO12=0),"",GO13/GO12-1) | GQ28: =IF(OR(GQ13="",GQ12=""),"",GQ13-GQ12) | GR28: =IF(OR(GQ13="",GQ12="",GQ12=0),"",GQ13/GQ12-1) | GS28: =IF(OR(GS13="",GS12=""),"",GS13-GS12) | GT28: =IF(OR(GS13="",GS12="",GS12=0),"",GS13/GS12-1) | GU28: =IF(OR(GU13="",GU12=""),"",GU13-GU12) | GV28: =IF(OR(GU13="",GU12="",GU12=0),"",GU13/GU12-1) | GW28: =IF(OR(GW13="",GW12=""),"",GW13-GW12) | GX28: =IF(OR(GW13="",GW12="",GW12=0),"",GW13/GW12-1) | GY28: =IF(OR(GY13="",GY12=""),"",GY13-GY12) | GZ28: =IF(OR(GY13="",GY12="",GY12=0),"",GY13/GY12-1)
F29: ROSPABB | H29: =IF(OR('Довідник категорій'!B7="",'Довідник категорій'!B6=""),"",'Довідник категорій'!B7&" ↔ "&'Довідник категорій'!B6) -> Premium Chalet ↔ Forest View Chalet | I29: =IF(OR(I14="",I13=""),"",I14-I13) -> 3000 | J29: =IF(OR(I14="",I13="",I13=0),"",I14/I13-1) -> 0.75 | K29: =IF(OR(K14="",K13=""),"",K14-K13) -> 4600 | L29: =IF(OR(K14="",K13="",K13=0),"",K14/K13-1) -> 0.70769231 | M29: =IF(OR(M14="",M13=""),"",M14-M13) -> 3220 | N29: =IF(OR(M14="",M13="",M13=0),"",M14/M13-1) -> 0.70769231 | O29: =IF(OR(O14="",O13=""),"",O14-O13) -> 3910 | P29: =IF(OR(O14="",O13="",O13=0),"",O14/O13-1) -> 0.70769231 | Q29: =IF(OR(Q14="",Q13=""),"",Q14-Q13) -> 3449.908 | R29: =IF(OR(Q14="",Q13="",Q13=0),"",Q14/Q13-1) -> 0.70769231 | S29: =IF(OR(S14="",S13=""),"",S14-S13) -> 4189.174 | T29: =IF(OR(S14="",S13="",S13=0),"",S14/S13-1) -> 0.70769231 | U29: =IF(OR(U14="",U13=""),"",U14-U13) -> 3696.2314 | V29: =IF(OR(U14="",U13="",U13=0),"",U14/U13-1) -> 0.70769231 | W29: =IF(OR(W14="",W13=""),"",W14-W13) -> 4488.281 | X29: =IF(OR(W14="",W13="",W13=0),"",W14/W13-1) -> 0.70769231 | Y29: =IF(OR(Y14="",Y13=""),"",Y14-Y13) -> 3960.1424 | Z29: =IF(OR(Y14="",Y13="",Y13=0),"",Y14/Y13-1) -> 0.70769231 | AA29: =IF(OR(AA14="",AA13=""),"",AA14-AA13) -> 4808.7443 | AB29: =IF(OR(AA14="",AA13="",AA13=0),"",AA14/AA13-1) -> 0.70769231 | AC29: =IF(OR(AC14="",AC13=""),"",AC14-AC13) -> 4242.8965 | AD29: =IF(OR(AC14="",AC13="",AC13=0),"",AC14/AC13-1) -> 0.70769231 | AE29: =IF(OR(AE14="",AE13=""),"",AE14-AE13) -> 5152.0886 | AF29: =IF(OR(AE14="",AE13="",AE13=0),"",AE14/AE13-1) -> 0.70769231 | AG29: =IF(OR(AG14="",AG13=""),"",AG14-AG13) | AH29: =IF(OR(AG14="",AG13="",AG13=0),"",AG14/AG13-1) | AI29: =IF(OR(AI14="",AI13=""),"",AI14-AI13) | AJ29: =IF(OR(AI14="",AI13="",AI13=0),"",AI14/AI13-1) | AK29: =IF(OR(AK14="",AK13=""),"",AK14-AK13) | AL29: =IF(OR(AK14="",AK13="",AK13=0),"",AK14/AK13-1) | AM29: =IF(OR(AM14="",AM13=""),"",AM14-AM13) | AN29: =IF(OR(AM14="",AM13="",AM13=0),"",AM14/AM13-1) | AO29: =IF(OR(AO14="",AO13=""),"",AO14-AO13) | AP29: =IF(OR(AO14="",AO13="",AO13=0),"",AO14/AO13-1) | AQ29: =IF(OR(AQ14="",AQ13=""),"",AQ14-AQ13) | AR29: =IF(OR(AQ14="",AQ13="",AQ13=0),"",AQ14/AQ13-1) | AS29: =IF(OR(AS14="",AS13=""),"",AS14-AS13) | AT29: =IF(OR(AS14="",AS13="",AS13=0),"",AS14/AS13-1) | AU29: =IF(OR(AU14="",AU13=""),"",AU14-AU13) | AV29: =IF(OR(AU14="",AU13="",AU13=0),"",AU14/AU13-1) | AW29: =IF(OR(AW14="",AW13=""),"",AW14-AW13) | AX29: =IF(OR(AW14="",AW13="",AW13=0),"",AW14/AW13-1) | AY29: =IF(OR(AY14="",AY13=""),"",AY14-AY13) | AZ29: =IF(OR(AY14="",AY13="",AY13=0),"",AY14/AY13-1) | BA29: =IF(OR(BA14="",BA13=""),"",BA14-BA13) | BB29: =IF(OR(BA14="",BA13="",BA13=0),"",BA14/BA13-1) | BC29: =IF(OR(BC14="",BC13=""),"",BC14-BC13) | BD29: =IF(OR(BC14="",BC13="",BC13=0),"",BC14/BC13-1) | BE29: =IF(OR(BE14="",BE13=""),"",BE14-BE13) | BF29: =IF(OR(BE14="",BE13="",BE13=0),"",BE14/BE13-1) | BG29: =IF(OR(BG14="",BG13=""),"",BG14-BG13) | BH29: =IF(OR(BG14="",BG13="",BG13=0),"",BG14/BG13-1) | BI29: =IF(OR(BI14="",BI13=""),"",BI14-BI13) | BJ29: =IF(OR(BI14="",BI13="",BI13=0),"",BI14/BI13-1) | BK29: =IF(OR(BK14="",BK13=""),"",BK14-BK13) | BL29: =IF(OR(BK14="",BK13="",BK13=0),"",BK14/BK13-1) | BM29: =IF(OR(BM14="",BM13=""),"",BM14-BM13) | BN29: =IF(OR(BM14="",BM13="",BM13=0),"",BM14/BM13-1) | BO29: =IF(OR(BO14="",BO13=""),"",BO14-BO13) | BP29: =IF(OR(BO14="",BO13="",BO13=0),"",BO14/BO13-1) | BQ29: =IF(OR(BQ14="",BQ13=""),"",BQ14-BQ13) | BR29: =IF(OR(BQ14="",BQ13="",BQ13=0),"",BQ14/BQ13-1) | BS29: =IF(OR(BS14="",BS13=""),"",BS14-BS13) | BT29: =IF(OR(BS14="",BS13="",BS13=0),"",BS14/BS13-1) | BU29: =IF(OR(BU14="",BU13=""),"",BU14-BU13) | BV29: =IF(OR(BU14="",BU13="",BU13=0),"",BU14/BU13-1) | BW29: =IF(OR(BW14="",BW13=""),"",BW14-BW13) | BX29: =IF(OR(BW14="",BW13="",BW13=0),"",BW14/BW13-1) | BY29: =IF(OR(BY14="",BY13=""),"",BY14-BY13) | BZ29: =IF(OR(BY14="",BY13="",BY13=0),"",BY14/BY13-1) | CA29: =IF(OR(CA14="",CA13=""),"",CA14-CA13) | CB29: =IF(OR(CA14="",CA13="",CA13=0),"",CA14/CA13-1) | CC29: =IF(OR(CC14="",CC13=""),"",CC14-CC13) | CD29: =IF(OR(CC14="",CC13="",CC13=0),"",CC14/CC13-1) | CE29: =IF(OR(CE14="",CE13=""),"",CE14-CE13) | CF29: =IF(OR(CE14="",CE13="",CE13=0),"",CE14/CE13-1) | CG29: =IF(OR(CG14="",CG13=""),"",CG14-CG13) | CH29: =IF(OR(CG14="",CG13="",CG13=0),"",CG14/CG13-1) | CI29: =IF(OR(CI14="",CI13=""),"",CI14-CI13) | CJ29: =IF(OR(CI14="",CI13="",CI13=0),"",CI14/CI13-1) | CK29: =IF(OR(CK14="",CK13=""),"",CK14-CK13) | CL29: =IF(OR(CK14="",CK13="",CK13=0),"",CK14/CK13-1) | CM29: =IF(OR(CM14="",CM13=""),"",CM14-CM13) | CN29: =IF(OR(CM14="",CM13="",CM13=0),"",CM14/CM13-1) | CO29: =IF(OR(CO14="",CO13=""),"",CO14-CO13) | CP29: =IF(OR(CO14="",CO13="",CO13=0),"",CO14/CO13-1) | CQ29: =IF(OR(CQ14="",CQ13=""),"",CQ14-CQ13) | CR29: =IF(OR(CQ14="",CQ13="",CQ13=0),"",CQ14/CQ13-1) | CS29: =IF(OR(CS14="",CS13=""),"",CS14-CS13) | CT29: =IF(OR(CS14="",CS13="",CS13=0),"",CS14/CS13-1) | CU29: =IF(OR(CU14="",CU13=""),"",CU14-CU13) | CV29: =IF(OR(CU14="",CU13="",CU13=0),"",CU14/CU13-1) | CW29: =IF(OR(CW14="",CW13=""),"",CW14-CW13) | CX29: =IF(OR(CW14="",CW13="",CW13=0),"",CW14/CW13-1) | CY29: =IF(OR(CY14="",CY13=""),"",CY14-CY13) | CZ29: =IF(OR(CY14="",CY13="",CY13=0),"",CY14/CY13-1) | DA29: =IF(OR(DA14="",DA13=""),"",DA14-DA13) | DB29: =IF(OR(DA14="",DA13="",DA13=0),"",DA14/DA13-1) | DC29: =IF(OR(DC14="",DC13=""),"",DC14-DC13) | DD29: =IF(OR(DC14="",DC13="",DC13=0),"",DC14/DC13-1) | DE29: =IF(OR(DE14="",DE13=""),"",DE14-DE13) | DF29: =IF(OR(DE14="",DE13="",DE13=0),"",DE14/DE13-1) | DG29: =IF(OR(DG14="",DG13=""),"",DG14-DG13) | DH29: =IF(OR(DG14="",DG13="",DG13=0),"",DG14/DG13-1) | DI29: =IF(OR(DI14="",DI13=""),"",DI14-DI13) | DJ29: =IF(OR(DI14="",DI13="",DI13=0),"",DI14/DI13-1) | DK29: =IF(OR(DK14="",DK13=""),"",DK14-DK13) | DL29: =IF(OR(DK14="",DK13="",DK13=0),"",DK14/DK13-1) | DM29: =IF(OR(DM14="",DM13=""),"",DM14-DM13) | DN29: =IF(OR(DM14="",DM13="",DM13=0),"",DM14/DM13-1) | DO29: =IF(OR(DO14="",DO13=""),"",DO14-DO13) | DP29: =IF(OR(DO14="",DO13="",DO13=0),"",DO14/DO13-1) | DQ29: =IF(OR(DQ14="",DQ13=""),"",DQ14-DQ13) | DR29: =IF(OR(DQ14="",DQ13="",DQ13=0),"",DQ14/DQ13-1) | DS29: =IF(OR(DS14="",DS13=""),"",DS14-DS13) | DT29: =IF(OR(DS14="",DS13="",DS13=0),"",DS14/DS13-1) | DU29: =IF(OR(DU14="",DU13=""),"",DU14-DU13) | DV29: =IF(OR(DU14="",DU13="",DU13=0),"",DU14/DU13-1) | DW29: =IF(OR(DW14="",DW13=""),"",DW14-DW13) | DX29: =IF(OR(DW14="",DW13="",DW13=0),"",DW14/DW13-1) | DY29: =IF(OR(DY14="",DY13=""),"",DY14-DY13) | DZ29: =IF(OR(DY14="",DY13="",DY13=0),"",DY14/DY13-1) | EA29: =IF(OR(EA14="",EA13=""),"",EA14-EA13) | EB29: =IF(OR(EA14="",EA13="",EA13=0),"",EA14/EA13-1) | EC29: =IF(OR(EC14="",EC13=""),"",EC14-EC13) | ED29: =IF(OR(EC14="",EC13="",EC13=0),"",EC14/EC13-1) | EE29: =IF(OR(EE14="",EE13=""),"",EE14-EE13) | EF29: =IF(OR(EE14="",EE13="",EE13=0),"",EE14/EE13-1) | EG29: =IF(OR(EG14="",EG13=""),"",EG14-EG13) | EH29: =IF(OR(EG14="",EG13="",EG13=0),"",EG14/EG13-1) | EI29: =IF(OR(EI14="",EI13=""),"",EI14-EI13) | EJ29: =IF(OR(EI14="",EI13="",EI13=0),"",EI14/EI13-1) | EK29: =IF(OR(EK14="",EK13=""),"",EK14-EK13) | EL29: =IF(OR(EK14="",EK13="",EK13=0),"",EK14/EK13-1) | EM29: =IF(OR(EM14="",EM13=""),"",EM14-EM13) | EN29: =IF(OR(EM14="",EM13="",EM13=0),"",EM14/EM13-1) | EO29: =IF(OR(EO14="",EO13=""),"",EO14-EO13) | EP29: =IF(OR(EO14="",EO13="",EO13=0),"",EO14/EO13-1) | EQ29: =IF(OR(EQ14="",EQ13=""),"",EQ14-EQ13) | ER29: =IF(OR(EQ14="",EQ13="",EQ13=0),"",EQ14/EQ13-1) | ES29: =IF(OR(ES14="",ES13=""),"",ES14-ES13) | ET29: =IF(OR(ES14="",ES13="",ES13=0),"",ES14/ES13-1) | EU29: =IF(OR(EU14="",EU13=""),"",EU14-EU13) | EV29: =IF(OR(EU14="",EU13="",EU13=0),"",EU14/EU13-1) | EW29: =IF(OR(EW14="",EW13=""),"",EW14-EW13) | EX29: =IF(OR(EW14="",EW13="",EW13=0),"",EW14/EW13-1) | EY29: =IF(OR(EY14="",EY13=""),"",EY14-EY13) | EZ29: =IF(OR(EY14="",EY13="",EY13=0),"",EY14/EY13-1) | FA29: =IF(OR(FA14="",FA13=""),"",FA14-FA13) | FB29: =IF(OR(FA14="",FA13="",FA13=0),"",FA14/FA13-1) | FC29: =IF(OR(FC14="",FC13=""),"",FC14-FC13) | FD29: =IF(OR(FC14="",FC13="",FC13=0),"",FC14/FC13-1) | FE29: =IF(OR(FE14="",FE13=""),"",FE14-FE13) | FF29: =IF(OR(FE14="",FE13="",FE13=0),"",FE14/FE13-1) | FG29: =IF(OR(FG14="",FG13=""),"",FG14-FG13) | FH29: =IF(OR(FG14="",FG13="",FG13=0),"",FG14/FG13-1) | FI29: =IF(OR(FI14="",FI13=""),"",FI14-FI13) | FJ29: =IF(OR(FI14="",FI13="",FI13=0),"",FI14/FI13-1) | FK29: =IF(OR(FK14="",FK13=""),"",FK14-FK13) | FL29: =IF(OR(FK14="",FK13="",FK13=0),"",FK14/FK13-1) | FM29: =IF(OR(FM14="",FM13=""),"",FM14-FM13) | FN29: =IF(OR(FM14="",FM13="",FM13=0),"",FM14/FM13-1) | FO29: =IF(OR(FO14="",FO13=""),"",FO14-FO13) | FP29: =IF(OR(FO14="",FO13="",FO13=0),"",FO14/FO13-1) | FQ29: =IF(OR(FQ14="",FQ13=""),"",FQ14-FQ13) | FR29: =IF(OR(FQ14="",FQ13="",FQ13=0),"",FQ14/FQ13-1) | FS29: =IF(OR(FS14="",FS13=""),"",FS14-FS13) | FT29: =IF(OR(FS14="",FS13="",FS13=0),"",FS14/FS13-1) | FU29: =IF(OR(FU14="",FU13=""),"",FU14-FU13) | FV29: =IF(OR(FU14="",FU13="",FU13=0),"",FU14/FU13-1) | FW29: =IF(OR(FW14="",FW13=""),"",FW14-FW13) | FX29: =IF(OR(FW14="",FW13="",FW13=0),"",FW14/FW13-1) | FY29: =IF(OR(FY14="",FY13=""),"",FY14-FY13) | FZ29: =IF(OR(FY14="",FY13="",FY13=0),"",FY14/FY13-1) | GA29: =IF(OR(GA14="",GA13=""),"",GA14-GA13) | GB29: =IF(OR(GA14="",GA13="",GA13=0),"",GA14/GA13-1) | GC29: =IF(OR(GC14="",GC13=""),"",GC14-GC13) | GD29: =IF(OR(GC14="",GC13="",GC13=0),"",GC14/GC13-1) | GE29: =IF(OR(GE14="",GE13=""),"",GE14-GE13) | GF29: =IF(OR(GE14="",GE13="",GE13=0),"",GE14/GE13-1) | GG29: =IF(OR(GG14="",GG13=""),"",GG14-GG13) | GH29: =IF(OR(GG14="",GG13="",GG13=0),"",GG14/GG13-1) | GI29: =IF(OR(GI14="",GI13=""),"",GI14-GI13) | GJ29: =IF(OR(GI14="",GI13="",GI13=0),"",GI14/GI13-1) | GK29: =IF(OR(GK14="",GK13=""),"",GK14-GK13) | GL29: =IF(OR(GK14="",GK13="",GK13=0),"",GK14/GK13-1) | GM29: =IF(OR(GM14="",GM13=""),"",GM14-GM13) | GN29: =IF(OR(GM14="",GM13="",GM13=0),"",GM14/GM13-1) | GO29: =IF(OR(GO14="",GO13=""),"",GO14-GO13) | GP29: =IF(OR(GO14="",GO13="",GO13=0),"",GO14/GO13-1) | GQ29: =IF(OR(GQ14="",GQ13=""),"",GQ14-GQ13) | GR29: =IF(OR(GQ14="",GQ13="",GQ13=0),"",GQ14/GQ13-1) | GS29: =IF(OR(GS14="",GS13=""),"",GS14-GS13) | GT29: =IF(OR(GS14="",GS13="",GS13=0),"",GS14/GS13-1) | GU29: =IF(OR(GU14="",GU13=""),"",GU14-GU13) | GV29: =IF(OR(GU14="",GU13="",GU13=0),"",GU14/GU13-1) | GW29: =IF(OR(GW14="",GW13=""),"",GW14-GW13) | GX29: =IF(OR(GW14="",GW13="",GW13=0),"",GW14/GW13-1) | GY29: =IF(OR(GY14="",GY13=""),"",GY14-GY13) | GZ29: =IF(OR(GY14="",GY13="",GY13=0),"",GY14/GY13-1)
H30: =IF(OR('Довідник категорій'!B8="",'Довідник категорій'!B7=""),"",'Довідник категорій'!B8&" ↔ "&'Довідник категорій'!B7) | I30: =IF(OR(I15="",I14=""),"",I15-I14) | J30: =IF(OR(I15="",I14="",I14=0),"",I15/I14-1) | K30: =IF(OR(K15="",K14=""),"",K15-K14) | L30: =IF(OR(K15="",K14="",K14=0),"",K15/K14-1) | M30: =IF(OR(M15="",M14=""),"",M15-M14) | N30: =IF(OR(M15="",M14="",M14=0),"",M15/M14-1) | O30: =IF(OR(O15="",O14=""),"",O15-O14) | P30: =IF(OR(O15="",O14="",O14=0),"",O15/O14-1) | Q30: =IF(OR(Q15="",Q14=""),"",Q15-Q14) | R30: =IF(OR(Q15="",Q14="",Q14=0),"",Q15/Q14-1) | S30: =IF(OR(S15="",S14=""),"",S15-S14) | T30: =IF(OR(S15="",S14="",S14=0),"",S15/S14-1) | U30: =IF(OR(U15="",U14=""),"",U15-U14) | V30: =IF(OR(U15="",U14="",U14=0),"",U15/U14-1) | W30: =IF(OR(W15="",W14=""),"",W15-W14) | X30: =IF(OR(W15="",W14="",W14=0),"",W15/W14-1) | Y30: =IF(OR(Y15="",Y14=""),"",Y15-Y14) | Z30: =IF(OR(Y15="",Y14="",Y14=0),"",Y15/Y14-1) | AA30: =IF(OR(AA15="",AA14=""),"",AA15-AA14) | AB30: =IF(OR(AA15="",AA14="",AA14=0),"",AA15/AA14-1) | AC30: =IF(OR(AC15="",AC14=""),"",AC15-AC14) | AD30: =IF(OR(AC15="",AC14="",AC14=0),"",AC15/AC14-1) | AE30: =IF(OR(AE15="",AE14=""),"",AE15-AE14) | AF30: =IF(OR(AE15="",AE14="",AE14=0),"",AE15/AE14-1) | AG30: =IF(OR(AG15="",AG14=""),"",AG15-AG14) | AH30: =IF(OR(AG15="",AG14="",AG14=0),"",AG15/AG14-1) | AI30: =IF(OR(AI15="",AI14=""),"",AI15-AI14) | AJ30: =IF(OR(AI15="",AI14="",AI14=0),"",AI15/AI14-1) | AK30: =IF(OR(AK15="",AK14=""),"",AK15-AK14) | AL30: =IF(OR(AK15="",AK14="",AK14=0),"",AK15/AK14-1) | AM30: =IF(OR(AM15="",AM14=""),"",AM15-AM14) | AN30: =IF(OR(AM15="",AM14="",AM14=0),"",AM15/AM14-1) | AO30: =IF(OR(AO15="",AO14=""),"",AO15-AO14) | AP30: =IF(OR(AO15="",AO14="",AO14=0),"",AO15/AO14-1) | AQ30: =IF(OR(AQ15="",AQ14=""),"",AQ15-AQ14) | AR30: =IF(OR(AQ15="",AQ14="",AQ14=0),"",AQ15/AQ14-1) | AS30: =IF(OR(AS15="",AS14=""),"",AS15-AS14) | AT30: =IF(OR(AS15="",AS14="",AS14=0),"",AS15/AS14-1) | AU30: =IF(OR(AU15="",AU14=""),"",AU15-AU14) | AV30: =IF(OR(AU15="",AU14="",AU14=0),"",AU15/AU14-1) | AW30: =IF(OR(AW15="",AW14=""),"",AW15-AW14) | AX30: =IF(OR(AW15="",AW14="",AW14=0),"",AW15/AW14-1) | AY30: =IF(OR(AY15="",AY14=""),"",AY15-AY14) | AZ30: =IF(OR(AY15="",AY14="",AY14=0),"",AY15/AY14-1) | BA30: =IF(OR(BA15="",BA14=""),"",BA15-BA14) | BB30: =IF(OR(BA15="",BA14="",BA14=0),"",BA15/BA14-1) | BC30: =IF(OR(BC15="",BC14=""),"",BC15-BC14) | BD30: =IF(OR(BC15="",BC14="",BC14=0),"",BC15/BC14-1) | BE30: =IF(OR(BE15="",BE14=""),"",BE15-BE14) | BF30: =IF(OR(BE15="",BE14="",BE14=0),"",BE15/BE14-1) | BG30: =IF(OR(BG15="",BG14=""),"",BG15-BG14) | BH30: =IF(OR(BG15="",BG14="",BG14=0),"",BG15/BG14-1) | BI30: =IF(OR(BI15="",BI14=""),"",BI15-BI14) | BJ30: =IF(OR(BI15="",BI14="",BI14=0),"",BI15/BI14-1) | BK30: =IF(OR(BK15="",BK14=""),"",BK15-BK14) | BL30: =IF(OR(BK15="",BK14="",BK14=0),"",BK15/BK14-1) | BM30: =IF(OR(BM15="",BM14=""),"",BM15-BM14) | BN30: =IF(OR(BM15="",BM14="",BM14=0),"",BM15/BM14-1) | BO30: =IF(OR(BO15="",BO14=""),"",BO15-BO14) | BP30: =IF(OR(BO15="",BO14="",BO14=0),"",BO15/BO14-1) | BQ30: =IF(OR(BQ15="",BQ14=""),"",BQ15-BQ14) | BR30: =IF(OR(BQ15="",BQ14="",BQ14=0),"",BQ15/BQ14-1) | BS30: =IF(OR(BS15="",BS14=""),"",BS15-BS14) | BT30: =IF(OR(BS15="",BS14="",BS14=0),"",BS15/BS14-1) | BU30: =IF(OR(BU15="",BU14=""),"",BU15-BU14) | BV30: =IF(OR(BU15="",BU14="",BU14=0),"",BU15/BU14-1) | BW30: =IF(OR(BW15="",BW14=""),"",BW15-BW14) | BX30: =IF(OR(BW15="",BW14="",BW14=0),"",BW15/BW14-1) | BY30: =IF(OR(BY15="",BY14=""),"",BY15-BY14) | BZ30: =IF(OR(BY15="",BY14="",BY14=0),"",BY15/BY14-1) | CA30: =IF(OR(CA15="",CA14=""),"",CA15-CA14) | CB30: =IF(OR(CA15="",CA14="",CA14=0),"",CA15/CA14-1) | CC30: =IF(OR(CC15="",CC14=""),"",CC15-CC14) | CD30: =IF(OR(CC15="",CC14="",CC14=0),"",CC15/CC14-1) | CE30: =IF(OR(CE15="",CE14=""),"",CE15-CE14) | CF30: =IF(OR(CE15="",CE14="",CE14=0),"",CE15/CE14-1) | CG30: =IF(OR(CG15="",CG14=""),"",CG15-CG14) | CH30: =IF(OR(CG15="",CG14="",CG14=0),"",CG15/CG14-1) | CI30: =IF(OR(CI15="",CI14=""),"",CI15-CI14) | CJ30: =IF(OR(CI15="",CI14="",CI14=0),"",CI15/CI14-1) | CK30: =IF(OR(CK15="",CK14=""),"",CK15-CK14) | CL30: =IF(OR(CK15="",CK14="",CK14=0),"",CK15/CK14-1) | CM30: =IF(OR(CM15="",CM14=""),"",CM15-CM14) | CN30: =IF(OR(CM15="",CM14="",CM14=0),"",CM15/CM14-1) | CO30: =IF(OR(CO15="",CO14=""),"",CO15-CO14) | CP30: =IF(OR(CO15="",CO14="",CO14=0),"",CO15/CO14-1) | CQ30: =IF(OR(CQ15="",CQ14=""),"",CQ15-CQ14) | CR30: =IF(OR(CQ15="",CQ14="",CQ14=0),"",CQ15/CQ14-1) | CS30: =IF(OR(CS15="",CS14=""),"",CS15-CS14) | CT30: =IF(OR(CS15="",CS14="",CS14=0),"",CS15/CS14-1) | CU30: =IF(OR(CU15="",CU14=""),"",CU15-CU14) | CV30: =IF(OR(CU15="",CU14="",CU14=0),"",CU15/CU14-1) | CW30: =IF(OR(CW15="",CW14=""),"",CW15-CW14) | CX30: =IF(OR(CW15="",CW14="",CW14=0),"",CW15/CW14-1) | CY30: =IF(OR(CY15="",CY14=""),"",CY15-CY14) | CZ30: =IF(OR(CY15="",CY14="",CY14=0),"",CY15/CY14-1) | DA30: =IF(OR(DA15="",DA14=""),"",DA15-DA14) | DB30: =IF(OR(DA15="",DA14="",DA14=0),"",DA15/DA14-1) | DC30: =IF(OR(DC15="",DC14=""),"",DC15-DC14) | DD30: =IF(OR(DC15="",DC14="",DC14=0),"",DC15/DC14-1) | DE30: =IF(OR(DE15="",DE14=""),"",DE15-DE14) | DF30: =IF(OR(DE15="",DE14="",DE14=0),"",DE15/DE14-1) | DG30: =IF(OR(DG15="",DG14=""),"",DG15-DG14) | DH30: =IF(OR(DG15="",DG14="",DG14=0),"",DG15/DG14-1) | DI30: =IF(OR(DI15="",DI14=""),"",DI15-DI14) | DJ30: =IF(OR(DI15="",DI14="",DI14=0),"",DI15/DI14-1) | DK30: =IF(OR(DK15="",DK14=""),"",DK15-DK14) | DL30: =IF(OR(DK15="",DK14="",DK14=0),"",DK15/DK14-1) | DM30: =IF(OR(DM15="",DM14=""),"",DM15-DM14) | DN30: =IF(OR(DM15="",DM14="",DM14=0),"",DM15/DM14-1) | DO30: =IF(OR(DO15="",DO14=""),"",DO15-DO14) | DP30: =IF(OR(DO15="",DO14="",DO14=0),"",DO15/DO14-1) | DQ30: =IF(OR(DQ15="",DQ14=""),"",DQ15-DQ14) | DR30: =IF(OR(DQ15="",DQ14="",DQ14=0),"",DQ15/DQ14-1) | DS30: =IF(OR(DS15="",DS14=""),"",DS15-DS14) | DT30: =IF(OR(DS15="",DS14="",DS14=0),"",DS15/DS14-1) | DU30: =IF(OR(DU15="",DU14=""),"",DU15-DU14) | DV30: =IF(OR(DU15="",DU14="",DU14=0),"",DU15/DU14-1) | DW30: =IF(OR(DW15="",DW14=""),"",DW15-DW14) | DX30: =IF(OR(DW15="",DW14="",DW14=0),"",DW15/DW14-1) | DY30: =IF(OR(DY15="",DY14=""),"",DY15-DY14) | DZ30: =IF(OR(DY15="",DY14="",DY14=0),"",DY15/DY14-1) | EA30: =IF(OR(EA15="",EA14=""),"",EA15-EA14) | EB30: =IF(OR(EA15="",EA14="",EA14=0),"",EA15/EA14-1) | EC30: =IF(OR(EC15="",EC14=""),"",EC15-EC14) | ED30: =IF(OR(EC15="",EC14="",EC14=0),"",EC15/EC14-1) | EE30: =IF(OR(EE15="",EE14=""),"",EE15-EE14) | EF30: =IF(OR(EE15="",EE14="",EE14=0),"",EE15/EE14-1) | EG30: =IF(OR(EG15="",EG14=""),"",EG15-EG14) | EH30: =IF(OR(EG15="",EG14="",EG14=0),"",EG15/EG14-1) | EI30: =IF(OR(EI15="",EI14=""),"",EI15-EI14) | EJ30: =IF(OR(EI15="",EI14="",EI14=0),"",EI15/EI14-1) | EK30: =IF(OR(EK15="",EK14=""),"",EK15-EK14) | EL30: =IF(OR(EK15="",EK14="",EK14=0),"",EK15/EK14-1) | EM30: =IF(OR(EM15="",EM14=""),"",EM15-EM14) | EN30: =IF(OR(EM15="",EM14="",EM14=0),"",EM15/EM14-1) | EO30: =IF(OR(EO15="",EO14=""),"",EO15-EO14) | EP30: =IF(OR(EO15="",EO14="",EO14=0),"",EO15/EO14-1) | EQ30: =IF(OR(EQ15="",EQ14=""),"",EQ15-EQ14) | ER30: =IF(OR(EQ15="",EQ14="",EQ14=0),"",EQ15/EQ14-1) | ES30: =IF(OR(ES15="",ES14=""),"",ES15-ES14) | ET30: =IF(OR(ES15="",ES14="",ES14=0),"",ES15/ES14-1) | EU30: =IF(OR(EU15="",EU14=""),"",EU15-EU14) | EV30: =IF(OR(EU15="",EU14="",EU14=0),"",EU15/EU14-1) | EW30: =IF(OR(EW15="",EW14=""),"",EW15-EW14) | EX30: =IF(OR(EW15="",EW14="",EW14=0),"",EW15/EW14-1) | EY30: =IF(OR(EY15="",EY14=""),"",EY15-EY14) | EZ30: =IF(OR(EY15="",EY14="",EY14=0),"",EY15/EY14-1) | FA30: =IF(OR(FA15="",FA14=""),"",FA15-FA14) | FB30: =IF(OR(FA15="",FA14="",FA14=0),"",FA15/FA14-1) | FC30: =IF(OR(FC15="",FC14=""),"",FC15-FC14) | FD30: =IF(OR(FC15="",FC14="",FC14=0),"",FC15/FC14-1) | FE30: =IF(OR(FE15="",FE14=""),"",FE15-FE14) | FF30: =IF(OR(FE15="",FE14="",FE14=0),"",FE15/FE14-1) | FG30: =IF(OR(FG15="",FG14=""),"",FG15-FG14) | FH30: =IF(OR(FG15="",FG14="",FG14=0),"",FG15/FG14-1) | FI30: =IF(OR(FI15="",FI14=""),"",FI15-FI14) | FJ30: =IF(OR(FI15="",FI14="",FI14=0),"",FI15/FI14-1) | FK30: =IF(OR(FK15="",FK14=""),"",FK15-FK14) | FL30: =IF(OR(FK15="",FK14="",FK14=0),"",FK15/FK14-1) | FM30: =IF(OR(FM15="",FM14=""),"",FM15-FM14) | FN30: =IF(OR(FM15="",FM14="",FM14=0),"",FM15/FM14-1) | FO30: =IF(OR(FO15="",FO14=""),"",FO15-FO14) | FP30: =IF(OR(FO15="",FO14="",FO14=0),"",FO15/FO14-1) | FQ30: =IF(OR(FQ15="",FQ14=""),"",FQ15-FQ14) | FR30: =IF(OR(FQ15="",FQ14="",FQ14=0),"",FQ15/FQ14-1) | FS30: =IF(OR(FS15="",FS14=""),"",FS15-FS14) | FT30: =IF(OR(FS15="",FS14="",FS14=0),"",FS15/FS14-1) | FU30: =IF(OR(FU15="",FU14=""),"",FU15-FU14) | FV30: =IF(OR(FU15="",FU14="",FU14=0),"",FU15/FU14-1) | FW30: =IF(OR(FW15="",FW14=""),"",FW15-FW14) | FX30: =IF(OR(FW15="",FW14="",FW14=0),"",FW15/FW14-1) | FY30: =IF(OR(FY15="",FY14=""),"",FY15-FY14) | FZ30: =IF(OR(FY15="",FY14="",FY14=0),"",FY15/FY14-1) | GA30: =IF(OR(GA15="",GA14=""),"",GA15-GA14) | GB30: =IF(OR(GA15="",GA14="",GA14=0),"",GA15/GA14-1) | GC30: =IF(OR(GC15="",GC14=""),"",GC15-GC14) | GD30: =IF(OR(GC15="",GC14="",GC14=0),"",GC15/GC14-1) | GE30: =IF(OR(GE15="",GE14=""),"",GE15-GE14) | GF30: =IF(OR(GE15="",GE14="",GE14=0),"",GE15/GE14-1) | GG30: =IF(OR(GG15="",GG14=""),"",GG15-GG14) | GH30: =IF(OR(GG15="",GG14="",GG14=0),"",GG15/GG14-1) | GI30: =IF(OR(GI15="",GI14=""),"",GI15-GI14) | GJ30: =IF(OR(GI15="",GI14="",GI14=0),"",GI15/GI14-1) | GK30: =IF(OR(GK15="",GK14=""),"",GK15-GK14) | GL30: =IF(OR(GK15="",GK14="",GK14=0),"",GK15/GK14-1) | GM30: =IF(OR(GM15="",GM14=""),"",GM15-GM14) | GN30: =IF(OR(GM15="",GM14="",GM14=0),"",GM15/GM14-1) | GO30: =IF(OR(GO15="",GO14=""),"",GO15-GO14) | GP30: =IF(OR(GO15="",GO14="",GO14=0),"",GO15/GO14-1) | GQ30: =IF(OR(GQ15="",GQ14=""),"",GQ15-GQ14) | GR30: =IF(OR(GQ15="",GQ14="",GQ14=0),"",GQ15/GQ14-1) | GS30: =IF(OR(GS15="",GS14=""),"",GS15-GS14) | GT30: =IF(OR(GS15="",GS14="",GS14=0),"",GS15/GS14-1) | GU30: =IF(OR(GU15="",GU14=""),"",GU15-GU14) | GV30: =IF(OR(GU15="",GU14="",GU14=0),"",GU15/GU14-1) | GW30: =IF(OR(GW15="",GW14=""),"",GW15-GW14) | GX30: =IF(OR(GW15="",GW14="",GW14=0),"",GW15/GW14-1) | GY30: =IF(OR(GY15="",GY14=""),"",GY15-GY14) | GZ30: =IF(OR(GY15="",GY14="",GY14=0),"",GY15/GY14-1)
F31: Типи дня | H31: =IF(OR('Довідник категорій'!B9="",'Довідник категорій'!B8=""),"",'Довідник категорій'!B9&" ↔ "&'Довідник категорій'!B8) | I31: =IF(OR(I16="",I15=""),"",I16-I15) | J31: =IF(OR(I16="",I15="",I15=0),"",I16/I15-1) | K31: =IF(OR(K16="",K15=""),"",K16-K15) | L31: =IF(OR(K16="",K15="",K15=0),"",K16/K15-1) | M31: =IF(OR(M16="",M15=""),"",M16-M15) | N31: =IF(OR(M16="",M15="",M15=0),"",M16/M15-1) | O31: =IF(OR(O16="",O15=""),"",O16-O15) | P31: =IF(OR(O16="",O15="",O15=0),"",O16/O15-1) | Q31: =IF(OR(Q16="",Q15=""),"",Q16-Q15) | R31: =IF(OR(Q16="",Q15="",Q15=0),"",Q16/Q15-1) | S31: =IF(OR(S16="",S15=""),"",S16-S15) | T31: =IF(OR(S16="",S15="",S15=0),"",S16/S15-1) | U31: =IF(OR(U16="",U15=""),"",U16-U15) | V31: =IF(OR(U16="",U15="",U15=0),"",U16/U15-1) | W31: =IF(OR(W16="",W15=""),"",W16-W15) | X31: =IF(OR(W16="",W15="",W15=0),"",W16/W15-1) | Y31: =IF(OR(Y16="",Y15=""),"",Y16-Y15) | Z31: =IF(OR(Y16="",Y15="",Y15=0),"",Y16/Y15-1) | AA31: =IF(OR(AA16="",AA15=""),"",AA16-AA15) | AB31: =IF(OR(AA16="",AA15="",AA15=0),"",AA16/AA15-1) | AC31: =IF(OR(AC16="",AC15=""),"",AC16-AC15) | AD31: =IF(OR(AC16="",AC15="",AC15=0),"",AC16/AC15-1) | AE31: =IF(OR(AE16="",AE15=""),"",AE16-AE15) | AF31: =IF(OR(AE16="",AE15="",AE15=0),"",AE16/AE15-1) | AG31: =IF(OR(AG16="",AG15=""),"",AG16-AG15) | AH31: =IF(OR(AG16="",AG15="",AG15=0),"",AG16/AG15-1) | AI31: =IF(OR(AI16="",AI15=""),"",AI16-AI15) | AJ31: =IF(OR(AI16="",AI15="",AI15=0),"",AI16/AI15-1) | AK31: =IF(OR(AK16="",AK15=""),"",AK16-AK15) | AL31: =IF(OR(AK16="",AK15="",AK15=0),"",AK16/AK15-1) | AM31: =IF(OR(AM16="",AM15=""),"",AM16-AM15) | AN31: =IF(OR(AM16="",AM15="",AM15=0),"",AM16/AM15-1) | AO31: =IF(OR(AO16="",AO15=""),"",AO16-AO15) | AP31: =IF(OR(AO16="",AO15="",AO15=0),"",AO16/AO15-1) | AQ31: =IF(OR(AQ16="",AQ15=""),"",AQ16-AQ15) | AR31: =IF(OR(AQ16="",AQ15="",AQ15=0),"",AQ16/AQ15-1) | AS31: =IF(OR(AS16="",AS15=""),"",AS16-AS15) | AT31: =IF(OR(AS16="",AS15="",AS15=0),"",AS16/AS15-1) | AU31: =IF(OR(AU16="",AU15=""),"",AU16-AU15) | AV31: =IF(OR(AU16="",AU15="",AU15=0),"",AU16/AU15-1) | AW31: =IF(OR(AW16="",AW15=""),"",AW16-AW15) | AX31: =IF(OR(AW16="",AW15="",AW15=0),"",AW16/AW15-1) | AY31: =IF(OR(AY16="",AY15=""),"",AY16-AY15) | AZ31: =IF(OR(AY16="",AY15="",AY15=0),"",AY16/AY15-1) | BA31: =IF(OR(BA16="",BA15=""),"",BA16-BA15) | BB31: =IF(OR(BA16="",BA15="",BA15=0),"",BA16/BA15-1) | BC31: =IF(OR(BC16="",BC15=""),"",BC16-BC15) | BD31: =IF(OR(BC16="",BC15="",BC15=0),"",BC16/BC15-1) | BE31: =IF(OR(BE16="",BE15=""),"",BE16-BE15) | BF31: =IF(OR(BE16="",BE15="",BE15=0),"",BE16/BE15-1) | BG31: =IF(OR(BG16="",BG15=""),"",BG16-BG15) | BH31: =IF(OR(BG16="",BG15="",BG15=0),"",BG16/BG15-1) | BI31: =IF(OR(BI16="",BI15=""),"",BI16-BI15) | BJ31: =IF(OR(BI16="",BI15="",BI15=0),"",BI16/BI15-1) | BK31: =IF(OR(BK16="",BK15=""),"",BK16-BK15) | BL31: =IF(OR(BK16="",BK15="",BK15=0),"",BK16/BK15-1) | BM31: =IF(OR(BM16="",BM15=""),"",BM16-BM15) | BN31: =IF(OR(BM16="",BM15="",BM15=0),"",BM16/BM15-1) | BO31: =IF(OR(BO16="",BO15=""),"",BO16-BO15) | BP31: =IF(OR(BO16="",BO15="",BO15=0),"",BO16/BO15-1) | BQ31: =IF(OR(BQ16="",BQ15=""),"",BQ16-BQ15) | BR31: =IF(OR(BQ16="",BQ15="",BQ15=0),"",BQ16/BQ15-1) | BS31: =IF(OR(BS16="",BS15=""),"",BS16-BS15) | BT31: =IF(OR(BS16="",BS15="",BS15=0),"",BS16/BS15-1) | BU31: =IF(OR(BU16="",BU15=""),"",BU16-BU15) | BV31: =IF(OR(BU16="",BU15="",BU15=0),"",BU16/BU15-1) | BW31: =IF(OR(BW16="",BW15=""),"",BW16-BW15) | BX31: =IF(OR(BW16="",BW15="",BW15=0),"",BW16/BW15-1) | BY31: =IF(OR(BY16="",BY15=""),"",BY16-BY15) | BZ31: =IF(OR(BY16="",BY15="",BY15=0),"",BY16/BY15-1) | CA31: =IF(OR(CA16="",CA15=""),"",CA16-CA15) | CB31: =IF(OR(CA16="",CA15="",CA15=0),"",CA16/CA15-1) | CC31: =IF(OR(CC16="",CC15=""),"",CC16-CC15) | CD31: =IF(OR(CC16="",CC15="",CC15=0),"",CC16/CC15-1) | CE31: =IF(OR(CE16="",CE15=""),"",CE16-CE15) | CF31: =IF(OR(CE16="",CE15="",CE15=0),"",CE16/CE15-1) | CG31: =IF(OR(CG16="",CG15=""),"",CG16-CG15) | CH31: =IF(OR(CG16="",CG15="",CG15=0),"",CG16/CG15-1) | CI31: =IF(OR(CI16="",CI15=""),"",CI16-CI15) | CJ31: =IF(OR(CI16="",CI15="",CI15=0),"",CI16/CI15-1) | CK31: =IF(OR(CK16="",CK15=""),"",CK16-CK15) | CL31: =IF(OR(CK16="",CK15="",CK15=0),"",CK16/CK15-1) | CM31: =IF(OR(CM16="",CM15=""),"",CM16-CM15) | CN31: =IF(OR(CM16="",CM15="",CM15=0),"",CM16/CM15-1) | CO31: =IF(OR(CO16="",CO15=""),"",CO16-CO15) | CP31: =IF(OR(CO16="",CO15="",CO15=0),"",CO16/CO15-1) | CQ31: =IF(OR(CQ16="",CQ15=""),"",CQ16-CQ15) | CR31: =IF(OR(CQ16="",CQ15="",CQ15=0),"",CQ16/CQ15-1) | CS31: =IF(OR(CS16="",CS15=""),"",CS16-CS15) | CT31: =IF(OR(CS16="",CS15="",CS15=0),"",CS16/CS15-1) | CU31: =IF(OR(CU16="",CU15=""),"",CU16-CU15) | CV31: =IF(OR(CU16="",CU15="",CU15=0),"",CU16/CU15-1) | CW31: =IF(OR(CW16="",CW15=""),"",CW16-CW15) | CX31: =IF(OR(CW16="",CW15="",CW15=0),"",CW16/CW15-1) | CY31: =IF(OR(CY16="",CY15=""),"",CY16-CY15) | CZ31: =IF(OR(CY16="",CY15="",CY15=0),"",CY16/CY15-1) | DA31: =IF(OR(DA16="",DA15=""),"",DA16-DA15) | DB31: =IF(OR(DA16="",DA15="",DA15=0),"",DA16/DA15-1) | DC31: =IF(OR(DC16="",DC15=""),"",DC16-DC15) | DD31: =IF(OR(DC16="",DC15="",DC15=0),"",DC16/DC15-1) | DE31: =IF(OR(DE16="",DE15=""),"",DE16-DE15) | DF31: =IF(OR(DE16="",DE15="",DE15=0),"",DE16/DE15-1) | DG31: =IF(OR(DG16="",DG15=""),"",DG16-DG15) | DH31: =IF(OR(DG16="",DG15="",DG15=0),"",DG16/DG15-1) | DI31: =IF(OR(DI16="",DI15=""),"",DI16-DI15) | DJ31: =IF(OR(DI16="",DI15="",DI15=0),"",DI16/DI15-1) | DK31: =IF(OR(DK16="",DK15=""),"",DK16-DK15) | DL31: =IF(OR(DK16="",DK15="",DK15=0),"",DK16/DK15-1) | DM31: =IF(OR(DM16="",DM15=""),"",DM16-DM15) | DN31: =IF(OR(DM16="",DM15="",DM15=0),"",DM16/DM15-1) | DO31: =IF(OR(DO16="",DO15=""),"",DO16-DO15) | DP31: =IF(OR(DO16="",DO15="",DO15=0),"",DO16/DO15-1) | DQ31: =IF(OR(DQ16="",DQ15=""),"",DQ16-DQ15) | DR31: =IF(OR(DQ16="",DQ15="",DQ15=0),"",DQ16/DQ15-1) | DS31: =IF(OR(DS16="",DS15=""),"",DS16-DS15) | DT31: =IF(OR(DS16="",DS15="",DS15=0),"",DS16/DS15-1) | DU31: =IF(OR(DU16="",DU15=""),"",DU16-DU15) | DV31: =IF(OR(DU16="",DU15="",DU15=0),"",DU16/DU15-1) | DW31: =IF(OR(DW16="",DW15=""),"",DW16-DW15) | DX31: =IF(OR(DW16="",DW15="",DW15=0),"",DW16/DW15-1) | DY31: =IF(OR(DY16="",DY15=""),"",DY16-DY15) | DZ31: =IF(OR(DY16="",DY15="",DY15=0),"",DY16/DY15-1) | EA31: =IF(OR(EA16="",EA15=""),"",EA16-EA15) | EB31: =IF(OR(EA16="",EA15="",EA15=0),"",EA16/EA15-1) | EC31: =IF(OR(EC16="",EC15=""),"",EC16-EC15) | ED31: =IF(OR(EC16="",EC15="",EC15=0),"",EC16/EC15-1) | EE31: =IF(OR(EE16="",EE15=""),"",EE16-EE15) | EF31: =IF(OR(EE16="",EE15="",EE15=0),"",EE16/EE15-1) | EG31: =IF(OR(EG16="",EG15=""),"",EG16-EG15) | EH31: =IF(OR(EG16="",EG15="",EG15=0),"",EG16/EG15-1) | EI31: =IF(OR(EI16="",EI15=""),"",EI16-EI15) | EJ31: =IF(OR(EI16="",EI15="",EI15=0),"",EI16/EI15-1) | EK31: =IF(OR(EK16="",EK15=""),"",EK16-EK15) | EL31: =IF(OR(EK16="",EK15="",EK15=0),"",EK16/EK15-1) | EM31: =IF(OR(EM16="",EM15=""),"",EM16-EM15) | EN31: =IF(OR(EM16="",EM15="",EM15=0),"",EM16/EM15-1) | EO31: =IF(OR(EO16="",EO15=""),"",EO16-EO15) | EP31: =IF(OR(EO16="",EO15="",EO15=0),"",EO16/EO15-1) | EQ31: =IF(OR(EQ16="",EQ15=""),"",EQ16-EQ15) | ER31: =IF(OR(EQ16="",EQ15="",EQ15=0),"",EQ16/EQ15-1) | ES31: =IF(OR(ES16="",ES15=""),"",ES16-ES15) | ET31: =IF(OR(ES16="",ES15="",ES15=0),"",ES16/ES15-1) | EU31: =IF(OR(EU16="",EU15=""),"",EU16-EU15) | EV31: =IF(OR(EU16="",EU15="",EU15=0),"",EU16/EU15-1) | EW31: =IF(OR(EW16="",EW15=""),"",EW16-EW15) | EX31: =IF(OR(EW16="",EW15="",EW15=0),"",EW16/EW15-1) | EY31: =IF(OR(EY16="",EY15=""),"",EY16-EY15) | EZ31: =IF(OR(EY16="",EY15="",EY15=0),"",EY16/EY15-1) | FA31: =IF(OR(FA16="",FA15=""),"",FA16-FA15) | FB31: =IF(OR(FA16="",FA15="",FA15=0),"",FA16/FA15-1) | FC31: =IF(OR(FC16="",FC15=""),"",FC16-FC15) | FD31: =IF(OR(FC16="",FC15="",FC15=0),"",FC16/FC15-1) | FE31: =IF(OR(FE16="",FE15=""),"",FE16-FE15) | FF31: =IF(OR(FE16="",FE15="",FE15=0),"",FE16/FE15-1) | FG31: =IF(OR(FG16="",FG15=""),"",FG16-FG15) | FH31: =IF(OR(FG16="",FG15="",FG15=0),"",FG16/FG15-1) | FI31: =IF(OR(FI16="",FI15=""),"",FI16-FI15) | FJ31: =IF(OR(FI16="",FI15="",FI15=0),"",FI16/FI15-1) | FK31: =IF(OR(FK16="",FK15=""),"",FK16-FK15) | FL31: =IF(OR(FK16="",FK15="",FK15=0),"",FK16/FK15-1) | FM31: =IF(OR(FM16="",FM15=""),"",FM16-FM15) | FN31: =IF(OR(FM16="",FM15="",FM15=0),"",FM16/FM15-1) | FO31: =IF(OR(FO16="",FO15=""),"",FO16-FO15) | FP31: =IF(OR(FO16="",FO15="",FO15=0),"",FO16/FO15-1) | FQ31: =IF(OR(FQ16="",FQ15=""),"",FQ16-FQ15) | FR31: =IF(OR(FQ16="",FQ15="",FQ15=0),"",FQ16/FQ15-1) | FS31: =IF(OR(FS16="",FS15=""),"",FS16-FS15) | FT31: =IF(OR(FS16="",FS15="",FS15=0),"",FS16/FS15-1) | FU31: =IF(OR(FU16="",FU15=""),"",FU16-FU15) | FV31: =IF(OR(FU16="",FU15="",FU15=0),"",FU16/FU15-1) | FW31: =IF(OR(FW16="",FW15=""),"",FW16-FW15) | FX31: =IF(OR(FW16="",FW15="",FW15=0),"",FW16/FW15-1) | FY31: =IF(OR(FY16="",FY15=""),"",FY16-FY15) | FZ31: =IF(OR(FY16="",FY15="",FY15=0),"",FY16/FY15-1) | GA31: =IF(OR(GA16="",GA15=""),"",GA16-GA15) | GB31: =IF(OR(GA16="",GA15="",GA15=0),"",GA16/GA15-1) | GC31: =IF(OR(GC16="",GC15=""),"",GC16-GC15) | GD31: =IF(OR(GC16="",GC15="",GC15=0),"",GC16/GC15-1) | GE31: =IF(OR(GE16="",GE15=""),"",GE16-GE15) | GF31: =IF(OR(GE16="",GE15="",GE15=0),"",GE16/GE15-1) | GG31: =IF(OR(GG16="",GG15=""),"",GG16-GG15) | GH31: =IF(OR(GG16="",GG15="",GG15=0),"",GG16/GG15-1) | GI31: =IF(OR(GI16="",GI15=""),"",GI16-GI15) | GJ31: =IF(OR(GI16="",GI15="",GI15=0),"",GI16/GI15-1) | GK31: =IF(OR(GK16="",GK15=""),"",GK16-GK15) | GL31: =IF(OR(GK16="",GK15="",GK15=0),"",GK16/GK15-1) | GM31: =IF(OR(GM16="",GM15=""),"",GM16-GM15) | GN31: =IF(OR(GM16="",GM15="",GM15=0),"",GM16/GM15-1) | GO31: =IF(OR(GO16="",GO15=""),"",GO16-GO15) | GP31: =IF(OR(GO16="",GO15="",GO15=0),"",GO16/GO15-1) | GQ31: =IF(OR(GQ16="",GQ15=""),"",GQ16-GQ15) | GR31: =IF(OR(GQ16="",GQ15="",GQ15=0),"",GQ16/GQ15-1) | GS31: =IF(OR(GS16="",GS15=""),"",GS16-GS15) | GT31: =IF(OR(GS16="",GS15="",GS15=0),"",GS16/GS15-1) | GU31: =IF(OR(GU16="",GU15=""),"",GU16-GU15) | GV31: =IF(OR(GU16="",GU15="",GU15=0),"",GU16/GU15-1) | GW31: =IF(OR(GW16="",GW15=""),"",GW16-GW15) | GX31: =IF(OR(GW16="",GW15="",GW15=0),"",GW16/GW15-1) | GY31: =IF(OR(GY16="",GY15=""),"",GY16-GY15) | GZ31: =IF(OR(GY16="",GY15="",GY15=0),"",GY16/GY15-1)
F32: Будні | H32: =IF(OR('Довідник категорій'!B10="",'Довідник категорій'!B9=""),"",'Довідник категорій'!B10&" ↔ "&'Довідник категорій'!B9) | I32: =IF(OR(I17="",I16=""),"",I17-I16) | J32: =IF(OR(I17="",I16="",I16=0),"",I17/I16-1) | K32: =IF(OR(K17="",K16=""),"",K17-K16) | L32: =IF(OR(K17="",K16="",K16=0),"",K17/K16-1) | M32: =IF(OR(M17="",M16=""),"",M17-M16) | N32: =IF(OR(M17="",M16="",M16=0),"",M17/M16-1) | O32: =IF(OR(O17="",O16=""),"",O17-O16) | P32: =IF(OR(O17="",O16="",O16=0),"",O17/O16-1) | Q32: =IF(OR(Q17="",Q16=""),"",Q17-Q16) | R32: =IF(OR(Q17="",Q16="",Q16=0),"",Q17/Q16-1) | S32: =IF(OR(S17="",S16=""),"",S17-S16) | T32: =IF(OR(S17="",S16="",S16=0),"",S17/S16-1) | U32: =IF(OR(U17="",U16=""),"",U17-U16) | V32: =IF(OR(U17="",U16="",U16=0),"",U17/U16-1) | W32: =IF(OR(W17="",W16=""),"",W17-W16) | X32: =IF(OR(W17="",W16="",W16=0),"",W17/W16-1) | Y32: =IF(OR(Y17="",Y16=""),"",Y17-Y16) | Z32: =IF(OR(Y17="",Y16="",Y16=0),"",Y17/Y16-1) | AA32: =IF(OR(AA17="",AA16=""),"",AA17-AA16) | AB32: =IF(OR(AA17="",AA16="",AA16=0),"",AA17/AA16-1) | AC32: =IF(OR(AC17="",AC16=""),"",AC17-AC16) | AD32: =IF(OR(AC17="",AC16="",AC16=0),"",AC17/AC16-1) | AE32: =IF(OR(AE17="",AE16=""),"",AE17-AE16) | AF32: =IF(OR(AE17="",AE16="",AE16=0),"",AE17/AE16-1) | AG32: =IF(OR(AG17="",AG16=""),"",AG17-AG16) | AH32: =IF(OR(AG17="",AG16="",AG16=0),"",AG17/AG16-1) | AI32: =IF(OR(AI17="",AI16=""),"",AI17-AI16) | AJ32: =IF(OR(AI17="",AI16="",AI16=0),"",AI17/AI16-1) | AK32: =IF(OR(AK17="",AK16=""),"",AK17-AK16) | AL32: =IF(OR(AK17="",AK16="",AK16=0),"",AK17/AK16-1) | AM32: =IF(OR(AM17="",AM16=""),"",AM17-AM16) | AN32: =IF(OR(AM17="",AM16="",AM16=0),"",AM17/AM16-1) | AO32: =IF(OR(AO17="",AO16=""),"",AO17-AO16) | AP32: =IF(OR(AO17="",AO16="",AO16=0),"",AO17/AO16-1) | AQ32: =IF(OR(AQ17="",AQ16=""),"",AQ17-AQ16) | AR32: =IF(OR(AQ17="",AQ16="",AQ16=0),"",AQ17/AQ16-1) | AS32: =IF(OR(AS17="",AS16=""),"",AS17-AS16) | AT32: =IF(OR(AS17="",AS16="",AS16=0),"",AS17/AS16-1) | AU32: =IF(OR(AU17="",AU16=""),"",AU17-AU16) | AV32: =IF(OR(AU17="",AU16="",AU16=0),"",AU17/AU16-1) | AW32: =IF(OR(AW17="",AW16=""),"",AW17-AW16) | AX32: =IF(OR(AW17="",AW16="",AW16=0),"",AW17/AW16-1) | AY32: =IF(OR(AY17="",AY16=""),"",AY17-AY16) | AZ32: =IF(OR(AY17="",AY16="",AY16=0),"",AY17/AY16-1) | BA32: =IF(OR(BA17="",BA16=""),"",BA17-BA16) | BB32: =IF(OR(BA17="",BA16="",BA16=0),"",BA17/BA16-1) | BC32: =IF(OR(BC17="",BC16=""),"",BC17-BC16) | BD32: =IF(OR(BC17="",BC16="",BC16=0),"",BC17/BC16-1) | BE32: =IF(OR(BE17="",BE16=""),"",BE17-BE16) | BF32: =IF(OR(BE17="",BE16="",BE16=0),"",BE17/BE16-1) | BG32: =IF(OR(BG17="",BG16=""),"",BG17-BG16) | BH32: =IF(OR(BG17="",BG16="",BG16=0),"",BG17/BG16-1) | BI32: =IF(OR(BI17="",BI16=""),"",BI17-BI16) | BJ32: =IF(OR(BI17="",BI16="",BI16=0),"",BI17/BI16-1) | BK32: =IF(OR(BK17="",BK16=""),"",BK17-BK16) | BL32: =IF(OR(BK17="",BK16="",BK16=0),"",BK17/BK16-1) | BM32: =IF(OR(BM17="",BM16=""),"",BM17-BM16) | BN32: =IF(OR(BM17="",BM16="",BM16=0),"",BM17/BM16-1) | BO32: =IF(OR(BO17="",BO16=""),"",BO17-BO16) | BP32: =IF(OR(BO17="",BO16="",BO16=0),"",BO17/BO16-1) | BQ32: =IF(OR(BQ17="",BQ16=""),"",BQ17-BQ16) | BR32: =IF(OR(BQ17="",BQ16="",BQ16=0),"",BQ17/BQ16-1) | BS32: =IF(OR(BS17="",BS16=""),"",BS17-BS16) | BT32: =IF(OR(BS17="",BS16="",BS16=0),"",BS17/BS16-1) | BU32: =IF(OR(BU17="",BU16=""),"",BU17-BU16) | BV32: =IF(OR(BU17="",BU16="",BU16=0),"",BU17/BU16-1) | BW32: =IF(OR(BW17="",BW16=""),"",BW17-BW16) | BX32: =IF(OR(BW17="",BW16="",BW16=0),"",BW17/BW16-1) | BY32: =IF(OR(BY17="",BY16=""),"",BY17-BY16) | BZ32: =IF(OR(BY17="",BY16="",BY16=0),"",BY17/BY16-1) | CA32: =IF(OR(CA17="",CA16=""),"",CA17-CA16) | CB32: =IF(OR(CA17="",CA16="",CA16=0),"",CA17/CA16-1) | CC32: =IF(OR(CC17="",CC16=""),"",CC17-CC16) | CD32: =IF(OR(CC17="",CC16="",CC16=0),"",CC17/CC16-1) | CE32: =IF(OR(CE17="",CE16=""),"",CE17-CE16) | CF32: =IF(OR(CE17="",CE16="",CE16=0),"",CE17/CE16-1) | CG32: =IF(OR(CG17="",CG16=""),"",CG17-CG16) | CH32: =IF(OR(CG17="",CG16="",CG16=0),"",CG17/CG16-1) | CI32: =IF(OR(CI17="",CI16=""),"",CI17-CI16) | CJ32: =IF(OR(CI17="",CI16="",CI16=0),"",CI17/CI16-1) | CK32: =IF(OR(CK17="",CK16=""),"",CK17-CK16) | CL32: =IF(OR(CK17="",CK16="",CK16=0),"",CK17/CK16-1) | CM32: =IF(OR(CM17="",CM16=""),"",CM17-CM16) | CN32: =IF(OR(CM17="",CM16="",CM16=0),"",CM17/CM16-1) | CO32: =IF(OR(CO17="",CO16=""),"",CO17-CO16) | CP32: =IF(OR(CO17="",CO16="",CO16=0),"",CO17/CO16-1) | CQ32: =IF(OR(CQ17="",CQ16=""),"",CQ17-CQ16) | CR32: =IF(OR(CQ17="",CQ16="",CQ16=0),"",CQ17/CQ16-1) | CS32: =IF(OR(CS17="",CS16=""),"",CS17-CS16) | CT32: =IF(OR(CS17="",CS16="",CS16=0),"",CS17/CS16-1) | CU32: =IF(OR(CU17="",CU16=""),"",CU17-CU16) | CV32: =IF(OR(CU17="",CU16="",CU16=0),"",CU17/CU16-1) | CW32: =IF(OR(CW17="",CW16=""),"",CW17-CW16) | CX32: =IF(OR(CW17="",CW16="",CW16=0),"",CW17/CW16-1) | CY32: =IF(OR(CY17="",CY16=""),"",CY17-CY16) | CZ32: =IF(OR(CY17="",CY16="",CY16=0),"",CY17/CY16-1) | DA32: =IF(OR(DA17="",DA16=""),"",DA17-DA16) | DB32: =IF(OR(DA17="",DA16="",DA16=0),"",DA17/DA16-1) | DC32: =IF(OR(DC17="",DC16=""),"",DC17-DC16) | DD32: =IF(OR(DC17="",DC16="",DC16=0),"",DC17/DC16-1) | DE32: =IF(OR(DE17="",DE16=""),"",DE17-DE16) | DF32: =IF(OR(DE17="",DE16="",DE16=0),"",DE17/DE16-1) | DG32: =IF(OR(DG17="",DG16=""),"",DG17-DG16) | DH32: =IF(OR(DG17="",DG16="",DG16=0),"",DG17/DG16-1) | DI32: =IF(OR(DI17="",DI16=""),"",DI17-DI16) | DJ32: =IF(OR(DI17="",DI16="",DI16=0),"",DI17/DI16-1) | DK32: =IF(OR(DK17="",DK16=""),"",DK17-DK16) | DL32: =IF(OR(DK17="",DK16="",DK16=0),"",DK17/DK16-1) | DM32: =IF(OR(DM17="",DM16=""),"",DM17-DM16) | DN32: =IF(OR(DM17="",DM16="",DM16=0),"",DM17/DM16-1) | DO32: =IF(OR(DO17="",DO16=""),"",DO17-DO16) | DP32: =IF(OR(DO17="",DO16="",DO16=0),"",DO17/DO16-1) | DQ32: =IF(OR(DQ17="",DQ16=""),"",DQ17-DQ16) | DR32: =IF(OR(DQ17="",DQ16="",DQ16=0),"",DQ17/DQ16-1) | DS32: =IF(OR(DS17="",DS16=""),"",DS17-DS16) | DT32: =IF(OR(DS17="",DS16="",DS16=0),"",DS17/DS16-1) | DU32: =IF(OR(DU17="",DU16=""),"",DU17-DU16) | DV32: =IF(OR(DU17="",DU16="",DU16=0),"",DU17/DU16-1) | DW32: =IF(OR(DW17="",DW16=""),"",DW17-DW16) | DX32: =IF(OR(DW17="",DW16="",DW16=0),"",DW17/DW16-1) | DY32: =IF(OR(DY17="",DY16=""),"",DY17-DY16) | DZ32: =IF(OR(DY17="",DY16="",DY16=0),"",DY17/DY16-1) | EA32: =IF(OR(EA17="",EA16=""),"",EA17-EA16) | EB32: =IF(OR(EA17="",EA16="",EA16=0),"",EA17/EA16-1) | EC32: =IF(OR(EC17="",EC16=""),"",EC17-EC16) | ED32: =IF(OR(EC17="",EC16="",EC16=0),"",EC17/EC16-1) | EE32: =IF(OR(EE17="",EE16=""),"",EE17-EE16) | EF32: =IF(OR(EE17="",EE16="",EE16=0),"",EE17/EE16-1) | EG32: =IF(OR(EG17="",EG16=""),"",EG17-EG16) | EH32: =IF(OR(EG17="",EG16="",EG16=0),"",EG17/EG16-1) | EI32: =IF(OR(EI17="",EI16=""),"",EI17-EI16) | EJ32: =IF(OR(EI17="",EI16="",EI16=0),"",EI17/EI16-1) | EK32: =IF(OR(EK17="",EK16=""),"",EK17-EK16) | EL32: =IF(OR(EK17="",EK16="",EK16=0),"",EK17/EK16-1) | EM32: =IF(OR(EM17="",EM16=""),"",EM17-EM16) | EN32: =IF(OR(EM17="",EM16="",EM16=0),"",EM17/EM16-1) | EO32: =IF(OR(EO17="",EO16=""),"",EO17-EO16) | EP32: =IF(OR(EO17="",EO16="",EO16=0),"",EO17/EO16-1) | EQ32: =IF(OR(EQ17="",EQ16=""),"",EQ17-EQ16) | ER32: =IF(OR(EQ17="",EQ16="",EQ16=0),"",EQ17/EQ16-1) | ES32: =IF(OR(ES17="",ES16=""),"",ES17-ES16) | ET32: =IF(OR(ES17="",ES16="",ES16=0),"",ES17/ES16-1) | EU32: =IF(OR(EU17="",EU16=""),"",EU17-EU16) | EV32: =IF(OR(EU17="",EU16="",EU16=0),"",EU17/EU16-1) | EW32: =IF(OR(EW17="",EW16=""),"",EW17-EW16) | EX32: =IF(OR(EW17="",EW16="",EW16=0),"",EW17/EW16-1) | EY32: =IF(OR(EY17="",EY16=""),"",EY17-EY16) | EZ32: =IF(OR(EY17="",EY16="",EY16=0),"",EY17/EY16-1) | FA32: =IF(OR(FA17="",FA16=""),"",FA17-FA16) | FB32: =IF(OR(FA17="",FA16="",FA16=0),"",FA17/FA16-1) | FC32: =IF(OR(FC17="",FC16=""),"",FC17-FC16) | FD32: =IF(OR(FC17="",FC16="",FC16=0),"",FC17/FC16-1) | FE32: =IF(OR(FE17="",FE16=""),"",FE17-FE16) | FF32: =IF(OR(FE17="",FE16="",FE16=0),"",FE17/FE16-1) | FG32: =IF(OR(FG17="",FG16=""),"",FG17-FG16) | FH32: =IF(OR(FG17="",FG16="",FG16=0),"",FG17/FG16-1) | FI32: =IF(OR(FI17="",FI16=""),"",FI17-FI16) | FJ32: =IF(OR(FI17="",FI16="",FI16=0),"",FI17/FI16-1) | FK32: =IF(OR(FK17="",FK16=""),"",FK17-FK16) | FL32: =IF(OR(FK17="",FK16="",FK16=0),"",FK17/FK16-1) | FM32: =IF(OR(FM17="",FM16=""),"",FM17-FM16) | FN32: =IF(OR(FM17="",FM16="",FM16=0),"",FM17/FM16-1) | FO32: =IF(OR(FO17="",FO16=""),"",FO17-FO16) | FP32: =IF(OR(FO17="",FO16="",FO16=0),"",FO17/FO16-1) | FQ32: =IF(OR(FQ17="",FQ16=""),"",FQ17-FQ16) | FR32: =IF(OR(FQ17="",FQ16="",FQ16=0),"",FQ17/FQ16-1) | FS32: =IF(OR(FS17="",FS16=""),"",FS17-FS16) | FT32: =IF(OR(FS17="",FS16="",FS16=0),"",FS17/FS16-1) | FU32: =IF(OR(FU17="",FU16=""),"",FU17-FU16) | FV32: =IF(OR(FU17="",FU16="",FU16=0),"",FU17/FU16-1) | FW32: =IF(OR(FW17="",FW16=""),"",FW17-FW16) | FX32: =IF(OR(FW17="",FW16="",FW16=0),"",FW17/FW16-1) | FY32: =IF(OR(FY17="",FY16=""),"",FY17-FY16) | FZ32: =IF(OR(FY17="",FY16="",FY16=0),"",FY17/FY16-1) | GA32: =IF(OR(GA17="",GA16=""),"",GA17-GA16) | GB32: =IF(OR(GA17="",GA16="",GA16=0),"",GA17/GA16-1) | GC32: =IF(OR(GC17="",GC16=""),"",GC17-GC16) | GD32: =IF(OR(GC17="",GC16="",GC16=0),"",GC17/GC16-1) | GE32: =IF(OR(GE17="",GE16=""),"",GE17-GE16) | GF32: =IF(OR(GE17="",GE16="",GE16=0),"",GE17/GE16-1) | GG32: =IF(OR(GG17="",GG16=""),"",GG17-GG16) | GH32: =IF(OR(GG17="",GG16="",GG16=0),"",GG17/GG16-1) | GI32: =IF(OR(GI17="",GI16=""),"",GI17-GI16) | GJ32: =IF(OR(GI17="",GI16="",GI16=0),"",GI17/GI16-1) | GK32: =IF(OR(GK17="",GK16=""),"",GK17-GK16) | GL32: =IF(OR(GK17="",GK16="",GK16=0),"",GK17/GK16-1) | GM32: =IF(OR(GM17="",GM16=""),"",GM17-GM16) | GN32: =IF(OR(GM17="",GM16="",GM16=0),"",GM17/GM16-1) | GO32: =IF(OR(GO17="",GO16=""),"",GO17-GO16) | GP32: =IF(OR(GO17="",GO16="",GO16=0),"",GO17/GO16-1) | GQ32: =IF(OR(GQ17="",GQ16=""),"",GQ17-GQ16) | GR32: =IF(OR(GQ17="",GQ16="",GQ16=0),"",GQ17/GQ16-1) | GS32: =IF(OR(GS17="",GS16=""),"",GS17-GS16) | GT32: =IF(OR(GS17="",GS16="",GS16=0),"",GS17/GS16-1) | GU32: =IF(OR(GU17="",GU16=""),"",GU17-GU16) | GV32: =IF(OR(GU17="",GU16="",GU16=0),"",GU17/GU16-1) | GW32: =IF(OR(GW17="",GW16=""),"",GW17-GW16) | GX32: =IF(OR(GW17="",GW16="",GW16=0),"",GW17/GW16-1) | GY32: =IF(OR(GY17="",GY16=""),"",GY17-GY16) | GZ32: =IF(OR(GY17="",GY16="",GY16=0),"",GY17/GY16-1)
F33: Вихідні | H33: =IF(OR('Довідник категорій'!B11="",'Довідник категорій'!B10=""),"",'Довідник категорій'!B11&" ↔ "&'Довідник категорій'!B10) | I33: =IF(OR(I18="",I17=""),"",I18-I17) | J33: =IF(OR(I18="",I17="",I17=0),"",I18/I17-1) | K33: =IF(OR(K18="",K17=""),"",K18-K17) | L33: =IF(OR(K18="",K17="",K17=0),"",K18/K17-1) | M33: =IF(OR(M18="",M17=""),"",M18-M17) | N33: =IF(OR(M18="",M17="",M17=0),"",M18/M17-1) | O33: =IF(OR(O18="",O17=""),"",O18-O17) | P33: =IF(OR(O18="",O17="",O17=0),"",O18/O17-1) | Q33: =IF(OR(Q18="",Q17=""),"",Q18-Q17) | R33: =IF(OR(Q18="",Q17="",Q17=0),"",Q18/Q17-1) | S33: =IF(OR(S18="",S17=""),"",S18-S17) | T33: =IF(OR(S18="",S17="",S17=0),"",S18/S17-1) | U33: =IF(OR(U18="",U17=""),"",U18-U17) | V33: =IF(OR(U18="",U17="",U17=0),"",U18/U17-1) | W33: =IF(OR(W18="",W17=""),"",W18-W17) | X33: =IF(OR(W18="",W17="",W17=0),"",W18/W17-1) | Y33: =IF(OR(Y18="",Y17=""),"",Y18-Y17) | Z33: =IF(OR(Y18="",Y17="",Y17=0),"",Y18/Y17-1) | AA33: =IF(OR(AA18="",AA17=""),"",AA18-AA17) | AB33: =IF(OR(AA18="",AA17="",AA17=0),"",AA18/AA17-1) | AC33: =IF(OR(AC18="",AC17=""),"",AC18-AC17) | AD33: =IF(OR(AC18="",AC17="",AC17=0),"",AC18/AC17-1) | AE33: =IF(OR(AE18="",AE17=""),"",AE18-AE17) | AF33: =IF(OR(AE18="",AE17="",AE17=0),"",AE18/AE17-1) | AG33: =IF(OR(AG18="",AG17=""),"",AG18-AG17) | AH33: =IF(OR(AG18="",AG17="",AG17=0),"",AG18/AG17-1) | AI33: =IF(OR(AI18="",AI17=""),"",AI18-AI17) | AJ33: =IF(OR(AI18="",AI17="",AI17=0),"",AI18/AI17-1) | AK33: =IF(OR(AK18="",AK17=""),"",AK18-AK17) | AL33: =IF(OR(AK18="",AK17="",AK17=0),"",AK18/AK17-1) | AM33: =IF(OR(AM18="",AM17=""),"",AM18-AM17) | AN33: =IF(OR(AM18="",AM17="",AM17=0),"",AM18/AM17-1) | AO33: =IF(OR(AO18="",AO17=""),"",AO18-AO17) | AP33: =IF(OR(AO18="",AO17="",AO17=0),"",AO18/AO17-1) | AQ33: =IF(OR(AQ18="",AQ17=""),"",AQ18-AQ17) | AR33: =IF(OR(AQ18="",AQ17="",AQ17=0),"",AQ18/AQ17-1) | AS33: =IF(OR(AS18="",AS17=""),"",AS18-AS17) | AT33: =IF(OR(AS18="",AS17="",AS17=0),"",AS18/AS17-1) | AU33: =IF(OR(AU18="",AU17=""),"",AU18-AU17) | AV33: =IF(OR(AU18="",AU17="",AU17=0),"",AU18/AU17-1) | AW33: =IF(OR(AW18="",AW17=""),"",AW18-AW17) | AX33: =IF(OR(AW18="",AW17="",AW17=0),"",AW18/AW17-1) | AY33: =IF(OR(AY18="",AY17=""),"",AY18-AY17) | AZ33: =IF(OR(AY18="",AY17="",AY17=0),"",AY18/AY17-1) | BA33: =IF(OR(BA18="",BA17=""),"",BA18-BA17) | BB33: =IF(OR(BA18="",BA17="",BA17=0),"",BA18/BA17-1) | BC33: =IF(OR(BC18="",BC17=""),"",BC18-BC17) | BD33: =IF(OR(BC18="",BC17="",BC17=0),"",BC18/BC17-1) | BE33: =IF(OR(BE18="",BE17=""),"",BE18-BE17) | BF33: =IF(OR(BE18="",BE17="",BE17=0),"",BE18/BE17-1) | BG33: =IF(OR(BG18="",BG17=""),"",BG18-BG17) | BH33: =IF(OR(BG18="",BG17="",BG17=0),"",BG18/BG17-1) | BI33: =IF(OR(BI18="",BI17=""),"",BI18-BI17) | BJ33: =IF(OR(BI18="",BI17="",BI17=0),"",BI18/BI17-1) | BK33: =IF(OR(BK18="",BK17=""),"",BK18-BK17) | BL33: =IF(OR(BK18="",BK17="",BK17=0),"",BK18/BK17-1) | BM33: =IF(OR(BM18="",BM17=""),"",BM18-BM17) | BN33: =IF(OR(BM18="",BM17="",BM17=0),"",BM18/BM17-1) | BO33: =IF(OR(BO18="",BO17=""),"",BO18-BO17) | BP33: =IF(OR(BO18="",BO17="",BO17=0),"",BO18/BO17-1) | BQ33: =IF(OR(BQ18="",BQ17=""),"",BQ18-BQ17) | BR33: =IF(OR(BQ18="",BQ17="",BQ17=0),"",BQ18/BQ17-1) | BS33: =IF(OR(BS18="",BS17=""),"",BS18-BS17) | BT33: =IF(OR(BS18="",BS17="",BS17=0),"",BS18/BS17-1) | BU33: =IF(OR(BU18="",BU17=""),"",BU18-BU17) | BV33: =IF(OR(BU18="",BU17="",BU17=0),"",BU18/BU17-1) | BW33: =IF(OR(BW18="",BW17=""),"",BW18-BW17) | BX33: =IF(OR(BW18="",BW17="",BW17=0),"",BW18/BW17-1) | BY33: =IF(OR(BY18="",BY17=""),"",BY18-BY17) | BZ33: =IF(OR(BY18="",BY17="",BY17=0),"",BY18/BY17-1) | CA33: =IF(OR(CA18="",CA17=""),"",CA18-CA17) | CB33: =IF(OR(CA18="",CA17="",CA17=0),"",CA18/CA17-1) | CC33: =IF(OR(CC18="",CC17=""),"",CC18-CC17) | CD33: =IF(OR(CC18="",CC17="",CC17=0),"",CC18/CC17-1) | CE33: =IF(OR(CE18="",CE17=""),"",CE18-CE17) | CF33: =IF(OR(CE18="",CE17="",CE17=0),"",CE18/CE17-1) | CG33: =IF(OR(CG18="",CG17=""),"",CG18-CG17) | CH33: =IF(OR(CG18="",CG17="",CG17=0),"",CG18/CG17-1) | CI33: =IF(OR(CI18="",CI17=""),"",CI18-CI17) | CJ33: =IF(OR(CI18="",CI17="",CI17=0),"",CI18/CI17-1) | CK33: =IF(OR(CK18="",CK17=""),"",CK18-CK17) | CL33: =IF(OR(CK18="",CK17="",CK17=0),"",CK18/CK17-1) | CM33: =IF(OR(CM18="",CM17=""),"",CM18-CM17) | CN33: =IF(OR(CM18="",CM17="",CM17=0),"",CM18/CM17-1) | CO33: =IF(OR(CO18="",CO17=""),"",CO18-CO17) | CP33: =IF(OR(CO18="",CO17="",CO17=0),"",CO18/CO17-1) | CQ33: =IF(OR(CQ18="",CQ17=""),"",CQ18-CQ17) | CR33: =IF(OR(CQ18="",CQ17="",CQ17=0),"",CQ18/CQ17-1) | CS33: =IF(OR(CS18="",CS17=""),"",CS18-CS17) | CT33: =IF(OR(CS18="",CS17="",CS17=0),"",CS18/CS17-1) | CU33: =IF(OR(CU18="",CU17=""),"",CU18-CU17) | CV33: =IF(OR(CU18="",CU17="",CU17=0),"",CU18/CU17-1) | CW33: =IF(OR(CW18="",CW17=""),"",CW18-CW17) | CX33: =IF(OR(CW18="",CW17="",CW17=0),"",CW18/CW17-1) | CY33: =IF(OR(CY18="",CY17=""),"",CY18-CY17) | CZ33: =IF(OR(CY18="",CY17="",CY17=0),"",CY18/CY17-1) | DA33: =IF(OR(DA18="",DA17=""),"",DA18-DA17) | DB33: =IF(OR(DA18="",DA17="",DA17=0),"",DA18/DA17-1) | DC33: =IF(OR(DC18="",DC17=""),"",DC18-DC17) | DD33: =IF(OR(DC18="",DC17="",DC17=0),"",DC18/DC17-1) | DE33: =IF(OR(DE18="",DE17=""),"",DE18-DE17) | DF33: =IF(OR(DE18="",DE17="",DE17=0),"",DE18/DE17-1) | DG33: =IF(OR(DG18="",DG17=""),"",DG18-DG17) | DH33: =IF(OR(DG18="",DG17="",DG17=0),"",DG18/DG17-1) | DI33: =IF(OR(DI18="",DI17=""),"",DI18-DI17) | DJ33: =IF(OR(DI18="",DI17="",DI17=0),"",DI18/DI17-1) | DK33: =IF(OR(DK18="",DK17=""),"",DK18-DK17) | DL33: =IF(OR(DK18="",DK17="",DK17=0),"",DK18/DK17-1) | DM33: =IF(OR(DM18="",DM17=""),"",DM18-DM17) | DN33: =IF(OR(DM18="",DM17="",DM17=0),"",DM18/DM17-1) | DO33: =IF(OR(DO18="",DO17=""),"",DO18-DO17) | DP33: =IF(OR(DO18="",DO17="",DO17=0),"",DO18/DO17-1) | DQ33: =IF(OR(DQ18="",DQ17=""),"",DQ18-DQ17) | DR33: =IF(OR(DQ18="",DQ17="",DQ17=0),"",DQ18/DQ17-1) | DS33: =IF(OR(DS18="",DS17=""),"",DS18-DS17) | DT33: =IF(OR(DS18="",DS17="",DS17=0),"",DS18/DS17-1) | DU33: =IF(OR(DU18="",DU17=""),"",DU18-DU17) | DV33: =IF(OR(DU18="",DU17="",DU17=0),"",DU18/DU17-1) | DW33: =IF(OR(DW18="",DW17=""),"",DW18-DW17) | DX33: =IF(OR(DW18="",DW17="",DW17=0),"",DW18/DW17-1) | DY33: =IF(OR(DY18="",DY17=""),"",DY18-DY17) | DZ33: =IF(OR(DY18="",DY17="",DY17=0),"",DY18/DY17-1) | EA33: =IF(OR(EA18="",EA17=""),"",EA18-EA17) | EB33: =IF(OR(EA18="",EA17="",EA17=0),"",EA18/EA17-1) | EC33: =IF(OR(EC18="",EC17=""),"",EC18-EC17) | ED33: =IF(OR(EC18="",EC17="",EC17=0),"",EC18/EC17-1) | EE33: =IF(OR(EE18="",EE17=""),"",EE18-EE17) | EF33: =IF(OR(EE18="",EE17="",EE17=0),"",EE18/EE17-1) | EG33: =IF(OR(EG18="",EG17=""),"",EG18-EG17) | EH33: =IF(OR(EG18="",EG17="",EG17=0),"",EG18/EG17-1) | EI33: =IF(OR(EI18="",EI17=""),"",EI18-EI17) | EJ33: =IF(OR(EI18="",EI17="",EI17=0),"",EI18/EI17-1) | EK33: =IF(OR(EK18="",EK17=""),"",EK18-EK17) | EL33: =IF(OR(EK18="",EK17="",EK17=0),"",EK18/EK17-1) | EM33: =IF(OR(EM18="",EM17=""),"",EM18-EM17) | EN33: =IF(OR(EM18="",EM17="",EM17=0),"",EM18/EM17-1) | EO33: =IF(OR(EO18="",EO17=""),"",EO18-EO17) | EP33: =IF(OR(EO18="",EO17="",EO17=0),"",EO18/EO17-1) | EQ33: =IF(OR(EQ18="",EQ17=""),"",EQ18-EQ17) | ER33: =IF(OR(EQ18="",EQ17="",EQ17=0),"",EQ18/EQ17-1) | ES33: =IF(OR(ES18="",ES17=""),"",ES18-ES17) | ET33: =IF(OR(ES18="",ES17="",ES17=0),"",ES18/ES17-1) | EU33: =IF(OR(EU18="",EU17=""),"",EU18-EU17) | EV33: =IF(OR(EU18="",EU17="",EU17=0),"",EU18/EU17-1) | EW33: =IF(OR(EW18="",EW17=""),"",EW18-EW17) | EX33: =IF(OR(EW18="",EW17="",EW17=0),"",EW18/EW17-1) | EY33: =IF(OR(EY18="",EY17=""),"",EY18-EY17) | EZ33: =IF(OR(EY18="",EY17="",EY17=0),"",EY18/EY17-1) | FA33: =IF(OR(FA18="",FA17=""),"",FA18-FA17) | FB33: =IF(OR(FA18="",FA17="",FA17=0),"",FA18/FA17-1) | FC33: =IF(OR(FC18="",FC17=""),"",FC18-FC17) | FD33: =IF(OR(FC18="",FC17="",FC17=0),"",FC18/FC17-1) | FE33: =IF(OR(FE18="",FE17=""),"",FE18-FE17) | FF33: =IF(OR(FE18="",FE17="",FE17=0),"",FE18/FE17-1) | FG33: =IF(OR(FG18="",FG17=""),"",FG18-FG17) | FH33: =IF(OR(FG18="",FG17="",FG17=0),"",FG18/FG17-1) | FI33: =IF(OR(FI18="",FI17=""),"",FI18-FI17) | FJ33: =IF(OR(FI18="",FI17="",FI17=0),"",FI18/FI17-1) | FK33: =IF(OR(FK18="",FK17=""),"",FK18-FK17) | FL33: =IF(OR(FK18="",FK17="",FK17=0),"",FK18/FK17-1) | FM33: =IF(OR(FM18="",FM17=""),"",FM18-FM17) | FN33: =IF(OR(FM18="",FM17="",FM17=0),"",FM18/FM17-1) | FO33: =IF(OR(FO18="",FO17=""),"",FO18-FO17) | FP33: =IF(OR(FO18="",FO17="",FO17=0),"",FO18/FO17-1) | FQ33: =IF(OR(FQ18="",FQ17=""),"",FQ18-FQ17) | FR33: =IF(OR(FQ18="",FQ17="",FQ17=0),"",FQ18/FQ17-1) | FS33: =IF(OR(FS18="",FS17=""),"",FS18-FS17) | FT33: =IF(OR(FS18="",FS17="",FS17=0),"",FS18/FS17-1) | FU33: =IF(OR(FU18="",FU17=""),"",FU18-FU17) | FV33: =IF(OR(FU18="",FU17="",FU17=0),"",FU18/FU17-1) | FW33: =IF(OR(FW18="",FW17=""),"",FW18-FW17) | FX33: =IF(OR(FW18="",FW17="",FW17=0),"",FW18/FW17-1) | FY33: =IF(OR(FY18="",FY17=""),"",FY18-FY17) | FZ33: =IF(OR(FY18="",FY17="",FY17=0),"",FY18/FY17-1) | GA33: =IF(OR(GA18="",GA17=""),"",GA18-GA17) | GB33: =IF(OR(GA18="",GA17="",GA17=0),"",GA18/GA17-1) | GC33: =IF(OR(GC18="",GC17=""),"",GC18-GC17) | GD33: =IF(OR(GC18="",GC17="",GC17=0),"",GC18/GC17-1) | GE33: =IF(OR(GE18="",GE17=""),"",GE18-GE17) | GF33: =IF(OR(GE18="",GE17="",GE17=0),"",GE18/GE17-1) | GG33: =IF(OR(GG18="",GG17=""),"",GG18-GG17) | GH33: =IF(OR(GG18="",GG17="",GG17=0),"",GG18/GG17-1) | GI33: =IF(OR(GI18="",GI17=""),"",GI18-GI17) | GJ33: =IF(OR(GI18="",GI17="",GI17=0),"",GI18/GI17-1) | GK33: =IF(OR(GK18="",GK17=""),"",GK18-GK17) | GL33: =IF(OR(GK18="",GK17="",GK17=0),"",GK18/GK17-1) | GM33: =IF(OR(GM18="",GM17=""),"",GM18-GM17) | GN33: =IF(OR(GM18="",GM17="",GM17=0),"",GM18/GM17-1) | GO33: =IF(OR(GO18="",GO17=""),"",GO18-GO17) | GP33: =IF(OR(GO18="",GO17="",GO17=0),"",GO18/GO17-1) | GQ33: =IF(OR(GQ18="",GQ17=""),"",GQ18-GQ17) | GR33: =IF(OR(GQ18="",GQ17="",GQ17=0),"",GQ18/GQ17-1) | GS33: =IF(OR(GS18="",GS17=""),"",GS18-GS17) | GT33: =IF(OR(GS18="",GS17="",GS17=0),"",GS18/GS17-1) | GU33: =IF(OR(GU18="",GU17=""),"",GU18-GU17) | GV33: =IF(OR(GU18="",GU17="",GU17=0),"",GU18/GU17-1) | GW33: =IF(OR(GW18="",GW17=""),"",GW18-GW17) | GX33: =IF(OR(GW18="",GW17="",GW17=0),"",GW18/GW17-1) | GY33: =IF(OR(GY18="",GY17=""),"",GY18-GY17) | GZ33: =IF(OR(GY18="",GY17="",GY17=0),"",GY18/GY17-1)
H34: =IF(OR('Довідник категорій'!B12="",'Довідник категорій'!B11=""),"",'Довідник категорій'!B12&" ↔ "&'Довідник категорій'!B11) | I34: =IF(OR(I19="",I18=""),"",I19-I18) | J34: =IF(OR(I19="",I18="",I18=0),"",I19/I18-1) | K34: =IF(OR(K19="",K18=""),"",K19-K18) | L34: =IF(OR(K19="",K18="",K18=0),"",K19/K18-1) | M34: =IF(OR(M19="",M18=""),"",M19-M18) | N34: =IF(OR(M19="",M18="",M18=0),"",M19/M18-1) | O34: =IF(OR(O19="",O18=""),"",O19-O18) | P34: =IF(OR(O19="",O18="",O18=0),"",O19/O18-1) | Q34: =IF(OR(Q19="",Q18=""),"",Q19-Q18) | R34: =IF(OR(Q19="",Q18="",Q18=0),"",Q19/Q18-1) | S34: =IF(OR(S19="",S18=""),"",S19-S18) | T34: =IF(OR(S19="",S18="",S18=0),"",S19/S18-1) | U34: =IF(OR(U19="",U18=""),"",U19-U18) | V34: =IF(OR(U19="",U18="",U18=0),"",U19/U18-1) | W34: =IF(OR(W19="",W18=""),"",W19-W18) | X34: =IF(OR(W19="",W18="",W18=0),"",W19/W18-1) | Y34: =IF(OR(Y19="",Y18=""),"",Y19-Y18) | Z34: =IF(OR(Y19="",Y18="",Y18=0),"",Y19/Y18-1) | AA34: =IF(OR(AA19="",AA18=""),"",AA19-AA18) | AB34: =IF(OR(AA19="",AA18="",AA18=0),"",AA19/AA18-1) | AC34: =IF(OR(AC19="",AC18=""),"",AC19-AC18) | AD34: =IF(OR(AC19="",AC18="",AC18=0),"",AC19/AC18-1) | AE34: =IF(OR(AE19="",AE18=""),"",AE19-AE18) | AF34: =IF(OR(AE19="",AE18="",AE18=0),"",AE19/AE18-1) | AG34: =IF(OR(AG19="",AG18=""),"",AG19-AG18) | AH34: =IF(OR(AG19="",AG18="",AG18=0),"",AG19/AG18-1) | AI34: =IF(OR(AI19="",AI18=""),"",AI19-AI18) | AJ34: =IF(OR(AI19="",AI18="",AI18=0),"",AI19/AI18-1) | AK34: =IF(OR(AK19="",AK18=""),"",AK19-AK18) | AL34: =IF(OR(AK19="",AK18="",AK18=0),"",AK19/AK18-1) | AM34: =IF(OR(AM19="",AM18=""),"",AM19-AM18) | AN34: =IF(OR(AM19="",AM18="",AM18=0),"",AM19/AM18-1) | AO34: =IF(OR(AO19="",AO18=""),"",AO19-AO18) | AP34: =IF(OR(AO19="",AO18="",AO18=0),"",AO19/AO18-1) | AQ34: =IF(OR(AQ19="",AQ18=""),"",AQ19-AQ18) | AR34: =IF(OR(AQ19="",AQ18="",AQ18=0),"",AQ19/AQ18-1) | AS34: =IF(OR(AS19="",AS18=""),"",AS19-AS18) | AT34: =IF(OR(AS19="",AS18="",AS18=0),"",AS19/AS18-1) | AU34: =IF(OR(AU19="",AU18=""),"",AU19-AU18) | AV34: =IF(OR(AU19="",AU18="",AU18=0),"",AU19/AU18-1) | AW34: =IF(OR(AW19="",AW18=""),"",AW19-AW18) | AX34: =IF(OR(AW19="",AW18="",AW18=0),"",AW19/AW18-1) | AY34: =IF(OR(AY19="",AY18=""),"",AY19-AY18) | AZ34: =IF(OR(AY19="",AY18="",AY18=0),"",AY19/AY18-1) | BA34: =IF(OR(BA19="",BA18=""),"",BA19-BA18) | BB34: =IF(OR(BA19="",BA18="",BA18=0),"",BA19/BA18-1) | BC34: =IF(OR(BC19="",BC18=""),"",BC19-BC18) | BD34: =IF(OR(BC19="",BC18="",BC18=0),"",BC19/BC18-1) | BE34: =IF(OR(BE19="",BE18=""),"",BE19-BE18) | BF34: =IF(OR(BE19="",BE18="",BE18=0),"",BE19/BE18-1) | BG34: =IF(OR(BG19="",BG18=""),"",BG19-BG18) | BH34: =IF(OR(BG19="",BG18="",BG18=0),"",BG19/BG18-1) | BI34: =IF(OR(BI19="",BI18=""),"",BI19-BI18) | BJ34: =IF(OR(BI19="",BI18="",BI18=0),"",BI19/BI18-1) | BK34: =IF(OR(BK19="",BK18=""),"",BK19-BK18) | BL34: =IF(OR(BK19="",BK18="",BK18=0),"",BK19/BK18-1) | BM34: =IF(OR(BM19="",BM18=""),"",BM19-BM18) | BN34: =IF(OR(BM19="",BM18="",BM18=0),"",BM19/BM18-1) | BO34: =IF(OR(BO19="",BO18=""),"",BO19-BO18) | BP34: =IF(OR(BO19="",BO18="",BO18=0),"",BO19/BO18-1) | BQ34: =IF(OR(BQ19="",BQ18=""),"",BQ19-BQ18) | BR34: =IF(OR(BQ19="",BQ18="",BQ18=0),"",BQ19/BQ18-1) | BS34: =IF(OR(BS19="",BS18=""),"",BS19-BS18) | BT34: =IF(OR(BS19="",BS18="",BS18=0),"",BS19/BS18-1) | BU34: =IF(OR(BU19="",BU18=""),"",BU19-BU18) | BV34: =IF(OR(BU19="",BU18="",BU18=0),"",BU19/BU18-1) | BW34: =IF(OR(BW19="",BW18=""),"",BW19-BW18) | BX34: =IF(OR(BW19="",BW18="",BW18=0),"",BW19/BW18-1) | BY34: =IF(OR(BY19="",BY18=""),"",BY19-BY18) | BZ34: =IF(OR(BY19="",BY18="",BY18=0),"",BY19/BY18-1) | CA34: =IF(OR(CA19="",CA18=""),"",CA19-CA18) | CB34: =IF(OR(CA19="",CA18="",CA18=0),"",CA19/CA18-1) | CC34: =IF(OR(CC19="",CC18=""),"",CC19-CC18) | CD34: =IF(OR(CC19="",CC18="",CC18=0),"",CC19/CC18-1) | CE34: =IF(OR(CE19="",CE18=""),"",CE19-CE18) | CF34: =IF(OR(CE19="",CE18="",CE18=0),"",CE19/CE18-1) | CG34: =IF(OR(CG19="",CG18=""),"",CG19-CG18) | CH34: =IF(OR(CG19="",CG18="",CG18=0),"",CG19/CG18-1) | CI34: =IF(OR(CI19="",CI18=""),"",CI19-CI18) | CJ34: =IF(OR(CI19="",CI18="",CI18=0),"",CI19/CI18-1) | CK34: =IF(OR(CK19="",CK18=""),"",CK19-CK18) | CL34: =IF(OR(CK19="",CK18="",CK18=0),"",CK19/CK18-1) | CM34: =IF(OR(CM19="",CM18=""),"",CM19-CM18) | CN34: =IF(OR(CM19="",CM18="",CM18=0),"",CM19/CM18-1) | CO34: =IF(OR(CO19="",CO18=""),"",CO19-CO18) | CP34: =IF(OR(CO19="",CO18="",CO18=0),"",CO19/CO18-1) | CQ34: =IF(OR(CQ19="",CQ18=""),"",CQ19-CQ18) | CR34: =IF(OR(CQ19="",CQ18="",CQ18=0),"",CQ19/CQ18-1) | CS34: =IF(OR(CS19="",CS18=""),"",CS19-CS18) | CT34: =IF(OR(CS19="",CS18="",CS18=0),"",CS19/CS18-1) | CU34: =IF(OR(CU19="",CU18=""),"",CU19-CU18) | CV34: =IF(OR(CU19="",CU18="",CU18=0),"",CU19/CU18-1) | CW34: =IF(OR(CW19="",CW18=""),"",CW19-CW18) | CX34: =IF(OR(CW19="",CW18="",CW18=0),"",CW19/CW18-1) | CY34: =IF(OR(CY19="",CY18=""),"",CY19-CY18) | CZ34: =IF(OR(CY19="",CY18="",CY18=0),"",CY19/CY18-1) | DA34: =IF(OR(DA19="",DA18=""),"",DA19-DA18) | DB34: =IF(OR(DA19="",DA18="",DA18=0),"",DA19/DA18-1) | DC34: =IF(OR(DC19="",DC18=""),"",DC19-DC18) | DD34: =IF(OR(DC19="",DC18="",DC18=0),"",DC19/DC18-1) | DE34: =IF(OR(DE19="",DE18=""),"",DE19-DE18) | DF34: =IF(OR(DE19="",DE18="",DE18=0),"",DE19/DE18-1) | DG34: =IF(OR(DG19="",DG18=""),"",DG19-DG18) | DH34: =IF(OR(DG19="",DG18="",DG18=0),"",DG19/DG18-1) | DI34: =IF(OR(DI19="",DI18=""),"",DI19-DI18) | DJ34: =IF(OR(DI19="",DI18="",DI18=0),"",DI19/DI18-1) | DK34: =IF(OR(DK19="",DK18=""),"",DK19-DK18) | DL34: =IF(OR(DK19="",DK18="",DK18=0),"",DK19/DK18-1) | DM34: =IF(OR(DM19="",DM18=""),"",DM19-DM18) | DN34: =IF(OR(DM19="",DM18="",DM18=0),"",DM19/DM18-1) | DO34: =IF(OR(DO19="",DO18=""),"",DO19-DO18) | DP34: =IF(OR(DO19="",DO18="",DO18=0),"",DO19/DO18-1) | DQ34: =IF(OR(DQ19="",DQ18=""),"",DQ19-DQ18) | DR34: =IF(OR(DQ19="",DQ18="",DQ18=0),"",DQ19/DQ18-1) | DS34: =IF(OR(DS19="",DS18=""),"",DS19-DS18) | DT34: =IF(OR(DS19="",DS18="",DS18=0),"",DS19/DS18-1) | DU34: =IF(OR(DU19="",DU18=""),"",DU19-DU18) | DV34: =IF(OR(DU19="",DU18="",DU18=0),"",DU19/DU18-1) | DW34: =IF(OR(DW19="",DW18=""),"",DW19-DW18) | DX34: =IF(OR(DW19="",DW18="",DW18=0),"",DW19/DW18-1) | DY34: =IF(OR(DY19="",DY18=""),"",DY19-DY18) | DZ34: =IF(OR(DY19="",DY18="",DY18=0),"",DY19/DY18-1) | EA34: =IF(OR(EA19="",EA18=""),"",EA19-EA18) | EB34: =IF(OR(EA19="",EA18="",EA18=0),"",EA19/EA18-1) | EC34: =IF(OR(EC19="",EC18=""),"",EC19-EC18) | ED34: =IF(OR(EC19="",EC18="",EC18=0),"",EC19/EC18-1) | EE34: =IF(OR(EE19="",EE18=""),"",EE19-EE18) | EF34: =IF(OR(EE19="",EE18="",EE18=0),"",EE19/EE18-1) | EG34: =IF(OR(EG19="",EG18=""),"",EG19-EG18) | EH34: =IF(OR(EG19="",EG18="",EG18=0),"",EG19/EG18-1) | EI34: =IF(OR(EI19="",EI18=""),"",EI19-EI18) | EJ34: =IF(OR(EI19="",EI18="",EI18=0),"",EI19/EI18-1) | EK34: =IF(OR(EK19="",EK18=""),"",EK19-EK18) | EL34: =IF(OR(EK19="",EK18="",EK18=0),"",EK19/EK18-1) | EM34: =IF(OR(EM19="",EM18=""),"",EM19-EM18) | EN34: =IF(OR(EM19="",EM18="",EM18=0),"",EM19/EM18-1) | EO34: =IF(OR(EO19="",EO18=""),"",EO19-EO18) | EP34: =IF(OR(EO19="",EO18="",EO18=0),"",EO19/EO18-1) | EQ34: =IF(OR(EQ19="",EQ18=""),"",EQ19-EQ18) | ER34: =IF(OR(EQ19="",EQ18="",EQ18=0),"",EQ19/EQ18-1) | ES34: =IF(OR(ES19="",ES18=""),"",ES19-ES18) | ET34: =IF(OR(ES19="",ES18="",ES18=0),"",ES19/ES18-1) | EU34: =IF(OR(EU19="",EU18=""),"",EU19-EU18) | EV34: =IF(OR(EU19="",EU18="",EU18=0),"",EU19/EU18-1) | EW34: =IF(OR(EW19="",EW18=""),"",EW19-EW18) | EX34: =IF(OR(EW19="",EW18="",EW18=0),"",EW19/EW18-1) | EY34: =IF(OR(EY19="",EY18=""),"",EY19-EY18) | EZ34: =IF(OR(EY19="",EY18="",EY18=0),"",EY19/EY18-1) | FA34: =IF(OR(FA19="",FA18=""),"",FA19-FA18) | FB34: =IF(OR(FA19="",FA18="",FA18=0),"",FA19/FA18-1) | FC34: =IF(OR(FC19="",FC18=""),"",FC19-FC18) | FD34: =IF(OR(FC19="",FC18="",FC18=0),"",FC19/FC18-1) | FE34: =IF(OR(FE19="",FE18=""),"",FE19-FE18) | FF34: =IF(OR(FE19="",FE18="",FE18=0),"",FE19/FE18-1) | FG34: =IF(OR(FG19="",FG18=""),"",FG19-FG18) | FH34: =IF(OR(FG19="",FG18="",FG18=0),"",FG19/FG18-1) | FI34: =IF(OR(FI19="",FI18=""),"",FI19-FI18) | FJ34: =IF(OR(FI19="",FI18="",FI18=0),"",FI19/FI18-1) | FK34: =IF(OR(FK19="",FK18=""),"",FK19-FK18) | FL34: =IF(OR(FK19="",FK18="",FK18=0),"",FK19/FK18-1) | FM34: =IF(OR(FM19="",FM18=""),"",FM19-FM18) | FN34: =IF(OR(FM19="",FM18="",FM18=0),"",FM19/FM18-1) | FO34: =IF(OR(FO19="",FO18=""),"",FO19-FO18) | FP34: =IF(OR(FO19="",FO18="",FO18=0),"",FO19/FO18-1) | FQ34: =IF(OR(FQ19="",FQ18=""),"",FQ19-FQ18) | FR34: =IF(OR(FQ19="",FQ18="",FQ18=0),"",FQ19/FQ18-1) | FS34: =IF(OR(FS19="",FS18=""),"",FS19-FS18) | FT34: =IF(OR(FS19="",FS18="",FS18=0),"",FS19/FS18-1) | FU34: =IF(OR(FU19="",FU18=""),"",FU19-FU18) | FV34: =IF(OR(FU19="",FU18="",FU18=0),"",FU19/FU18-1) | FW34: =IF(OR(FW19="",FW18=""),"",FW19-FW18) | FX34: =IF(OR(FW19="",FW18="",FW18=0),"",FW19/FW18-1) | FY34: =IF(OR(FY19="",FY18=""),"",FY19-FY18) | FZ34: =IF(OR(FY19="",FY18="",FY18=0),"",FY19/FY18-1) | GA34: =IF(OR(GA19="",GA18=""),"",GA19-GA18) | GB34: =IF(OR(GA19="",GA18="",GA18=0),"",GA19/GA18-1) | GC34: =IF(OR(GC19="",GC18=""),"",GC19-GC18) | GD34: =IF(OR(GC19="",GC18="",GC18=0),"",GC19/GC18-1) | GE34: =IF(OR(GE19="",GE18=""),"",GE19-GE18) | GF34: =IF(OR(GE19="",GE18="",GE18=0),"",GE19/GE18-1) | GG34: =IF(OR(GG19="",GG18=""),"",GG19-GG18) | GH34: =IF(OR(GG19="",GG18="",GG18=0),"",GG19/GG18-1) | GI34: =IF(OR(GI19="",GI18=""),"",GI19-GI18) | GJ34: =IF(OR(GI19="",GI18="",GI18=0),"",GI19/GI18-1) | GK34: =IF(OR(GK19="",GK18=""),"",GK19-GK18) | GL34: =IF(OR(GK19="",GK18="",GK18=0),"",GK19/GK18-1) | GM34: =IF(OR(GM19="",GM18=""),"",GM19-GM18) | GN34: =IF(OR(GM19="",GM18="",GM18=0),"",GM19/GM18-1) | GO34: =IF(OR(GO19="",GO18=""),"",GO19-GO18) | GP34: =IF(OR(GO19="",GO18="",GO18=0),"",GO19/GO18-1) | GQ34: =IF(OR(GQ19="",GQ18=""),"",GQ19-GQ18) | GR34: =IF(OR(GQ19="",GQ18="",GQ18=0),"",GQ19/GQ18-1) | GS34: =IF(OR(GS19="",GS18=""),"",GS19-GS18) | GT34: =IF(OR(GS19="",GS18="",GS18=0),"",GS19/GS18-1) | GU34: =IF(OR(GU19="",GU18=""),"",GU19-GU18) | GV34: =IF(OR(GU19="",GU18="",GU18=0),"",GU19/GU18-1) | GW34: =IF(OR(GW19="",GW18=""),"",GW19-GW18) | GX34: =IF(OR(GW19="",GW18="",GW18=0),"",GW19/GW18-1) | GY34: =IF(OR(GY19="",GY18=""),"",GY19-GY18) | GZ34: =IF(OR(GY19="",GY18="",GY18=0),"",GY19/GY18-1)
F35: Статуси | H35: =IF(OR('Довідник категорій'!B13="",'Довідник категорій'!B12=""),"",'Довідник категорій'!B13&" ↔ "&'Довідник категорій'!B12) | I35: =IF(OR(I20="",I19=""),"",I20-I19) | J35: =IF(OR(I20="",I19="",I19=0),"",I20/I19-1) | K35: =IF(OR(K20="",K19=""),"",K20-K19) | L35: =IF(OR(K20="",K19="",K19=0),"",K20/K19-1) | M35: =IF(OR(M20="",M19=""),"",M20-M19) | N35: =IF(OR(M20="",M19="",M19=0),"",M20/M19-1) | O35: =IF(OR(O20="",O19=""),"",O20-O19) | P35: =IF(OR(O20="",O19="",O19=0),"",O20/O19-1) | Q35: =IF(OR(Q20="",Q19=""),"",Q20-Q19) | R35: =IF(OR(Q20="",Q19="",Q19=0),"",Q20/Q19-1) | S35: =IF(OR(S20="",S19=""),"",S20-S19) | T35: =IF(OR(S20="",S19="",S19=0),"",S20/S19-1) | U35: =IF(OR(U20="",U19=""),"",U20-U19) | V35: =IF(OR(U20="",U19="",U19=0),"",U20/U19-1) | W35: =IF(OR(W20="",W19=""),"",W20-W19) | X35: =IF(OR(W20="",W19="",W19=0),"",W20/W19-1) | Y35: =IF(OR(Y20="",Y19=""),"",Y20-Y19) | Z35: =IF(OR(Y20="",Y19="",Y19=0),"",Y20/Y19-1) | AA35: =IF(OR(AA20="",AA19=""),"",AA20-AA19) | AB35: =IF(OR(AA20="",AA19="",AA19=0),"",AA20/AA19-1) | AC35: =IF(OR(AC20="",AC19=""),"",AC20-AC19) | AD35: =IF(OR(AC20="",AC19="",AC19=0),"",AC20/AC19-1) | AE35: =IF(OR(AE20="",AE19=""),"",AE20-AE19) | AF35: =IF(OR(AE20="",AE19="",AE19=0),"",AE20/AE19-1) | AG35: =IF(OR(AG20="",AG19=""),"",AG20-AG19) | AH35: =IF(OR(AG20="",AG19="",AG19=0),"",AG20/AG19-1) | AI35: =IF(OR(AI20="",AI19=""),"",AI20-AI19) | AJ35: =IF(OR(AI20="",AI19="",AI19=0),"",AI20/AI19-1) | AK35: =IF(OR(AK20="",AK19=""),"",AK20-AK19) | AL35: =IF(OR(AK20="",AK19="",AK19=0),"",AK20/AK19-1) | AM35: =IF(OR(AM20="",AM19=""),"",AM20-AM19) | AN35: =IF(OR(AM20="",AM19="",AM19=0),"",AM20/AM19-1) | AO35: =IF(OR(AO20="",AO19=""),"",AO20-AO19) | AP35: =IF(OR(AO20="",AO19="",AO19=0),"",AO20/AO19-1) | AQ35: =IF(OR(AQ20="",AQ19=""),"",AQ20-AQ19) | AR35: =IF(OR(AQ20="",AQ19="",AQ19=0),"",AQ20/AQ19-1) | AS35: =IF(OR(AS20="",AS19=""),"",AS20-AS19) | AT35: =IF(OR(AS20="",AS19="",AS19=0),"",AS20/AS19-1) | AU35: =IF(OR(AU20="",AU19=""),"",AU20-AU19) | AV35: =IF(OR(AU20="",AU19="",AU19=0),"",AU20/AU19-1) | AW35: =IF(OR(AW20="",AW19=""),"",AW20-AW19) | AX35: =IF(OR(AW20="",AW19="",AW19=0),"",AW20/AW19-1) | AY35: =IF(OR(AY20="",AY19=""),"",AY20-AY19) | AZ35: =IF(OR(AY20="",AY19="",AY19=0),"",AY20/AY19-1) | BA35: =IF(OR(BA20="",BA19=""),"",BA20-BA19) | BB35: =IF(OR(BA20="",BA19="",BA19=0),"",BA20/BA19-1) | BC35: =IF(OR(BC20="",BC19=""),"",BC20-BC19) | BD35: =IF(OR(BC20="",BC19="",BC19=0),"",BC20/BC19-1) | BE35: =IF(OR(BE20="",BE19=""),"",BE20-BE19) | BF35: =IF(OR(BE20="",BE19="",BE19=0),"",BE20/BE19-1) | BG35: =IF(OR(BG20="",BG19=""),"",BG20-BG19) | BH35: =IF(OR(BG20="",BG19="",BG19=0),"",BG20/BG19-1) | BI35: =IF(OR(BI20="",BI19=""),"",BI20-BI19) | BJ35: =IF(OR(BI20="",BI19="",BI19=0),"",BI20/BI19-1) | BK35: =IF(OR(BK20="",BK19=""),"",BK20-BK19) | BL35: =IF(OR(BK20="",BK19="",BK19=0),"",BK20/BK19-1) | BM35: =IF(OR(BM20="",BM19=""),"",BM20-BM19) | BN35: =IF(OR(BM20="",BM19="",BM19=0),"",BM20/BM19-1) | BO35: =IF(OR(BO20="",BO19=""),"",BO20-BO19) | BP35: =IF(OR(BO20="",BO19="",BO19=0),"",BO20/BO19-1) | BQ35: =IF(OR(BQ20="",BQ19=""),"",BQ20-BQ19) | BR35: =IF(OR(BQ20="",BQ19="",BQ19=0),"",BQ20/BQ19-1) | BS35: =IF(OR(BS20="",BS19=""),"",BS20-BS19) | BT35: =IF(OR(BS20="",BS19="",BS19=0),"",BS20/BS19-1) | BU35: =IF(OR(BU20="",BU19=""),"",BU20-BU19) | BV35: =IF(OR(BU20="",BU19="",BU19=0),"",BU20/BU19-1) | BW35: =IF(OR(BW20="",BW19=""),"",BW20-BW19) | BX35: =IF(OR(BW20="",BW19="",BW19=0),"",BW20/BW19-1) | BY35: =IF(OR(BY20="",BY19=""),"",BY20-BY19) | BZ35: =IF(OR(BY20="",BY19="",BY19=0),"",BY20/BY19-1) | CA35: =IF(OR(CA20="",CA19=""),"",CA20-CA19) | CB35: =IF(OR(CA20="",CA19="",CA19=0),"",CA20/CA19-1) | CC35: =IF(OR(CC20="",CC19=""),"",CC20-CC19) | CD35: =IF(OR(CC20="",CC19="",CC19=0),"",CC20/CC19-1) | CE35: =IF(OR(CE20="",CE19=""),"",CE20-CE19) | CF35: =IF(OR(CE20="",CE19="",CE19=0),"",CE20/CE19-1) | CG35: =IF(OR(CG20="",CG19=""),"",CG20-CG19) | CH35: =IF(OR(CG20="",CG19="",CG19=0),"",CG20/CG19-1) | CI35: =IF(OR(CI20="",CI19=""),"",CI20-CI19) | CJ35: =IF(OR(CI20="",CI19="",CI19=0),"",CI20/CI19-1) | CK35: =IF(OR(CK20="",CK19=""),"",CK20-CK19) | CL35: =IF(OR(CK20="",CK19="",CK19=0),"",CK20/CK19-1) | CM35: =IF(OR(CM20="",CM19=""),"",CM20-CM19) | CN35: =IF(OR(CM20="",CM19="",CM19=0),"",CM20/CM19-1) | CO35: =IF(OR(CO20="",CO19=""),"",CO20-CO19) | CP35: =IF(OR(CO20="",CO19="",CO19=0),"",CO20/CO19-1) | CQ35: =IF(OR(CQ20="",CQ19=""),"",CQ20-CQ19) | CR35: =IF(OR(CQ20="",CQ19="",CQ19=0),"",CQ20/CQ19-1) | CS35: =IF(OR(CS20="",CS19=""),"",CS20-CS19) | CT35: =IF(OR(CS20="",CS19="",CS19=0),"",CS20/CS19-1) | CU35: =IF(OR(CU20="",CU19=""),"",CU20-CU19) | CV35: =IF(OR(CU20="",CU19="",CU19=0),"",CU20/CU19-1) | CW35: =IF(OR(CW20="",CW19=""),"",CW20-CW19) | CX35: =IF(OR(CW20="",CW19="",CW19=0),"",CW20/CW19-1) | CY35: =IF(OR(CY20="",CY19=""),"",CY20-CY19) | CZ35: =IF(OR(CY20="",CY19="",CY19=0),"",CY20/CY19-1) | DA35: =IF(OR(DA20="",DA19=""),"",DA20-DA19) | DB35: =IF(OR(DA20="",DA19="",DA19=0),"",DA20/DA19-1) | DC35: =IF(OR(DC20="",DC19=""),"",DC20-DC19) | DD35: =IF(OR(DC20="",DC19="",DC19=0),"",DC20/DC19-1) | DE35: =IF(OR(DE20="",DE19=""),"",DE20-DE19) | DF35: =IF(OR(DE20="",DE19="",DE19=0),"",DE20/DE19-1) | DG35: =IF(OR(DG20="",DG19=""),"",DG20-DG19) | DH35: =IF(OR(DG20="",DG19="",DG19=0),"",DG20/DG19-1) | DI35: =IF(OR(DI20="",DI19=""),"",DI20-DI19) | DJ35: =IF(OR(DI20="",DI19="",DI19=0),"",DI20/DI19-1) | DK35: =IF(OR(DK20="",DK19=""),"",DK20-DK19) | DL35: =IF(OR(DK20="",DK19="",DK19=0),"",DK20/DK19-1) | DM35: =IF(OR(DM20="",DM19=""),"",DM20-DM19) | DN35: =IF(OR(DM20="",DM19="",DM19=0),"",DM20/DM19-1) | DO35: =IF(OR(DO20="",DO19=""),"",DO20-DO19) | DP35: =IF(OR(DO20="",DO19="",DO19=0),"",DO20/DO19-1) | DQ35: =IF(OR(DQ20="",DQ19=""),"",DQ20-DQ19) | DR35: =IF(OR(DQ20="",DQ19="",DQ19=0),"",DQ20/DQ19-1) | DS35: =IF(OR(DS20="",DS19=""),"",DS20-DS19) | DT35: =IF(OR(DS20="",DS19="",DS19=0),"",DS20/DS19-1) | DU35: =IF(OR(DU20="",DU19=""),"",DU20-DU19) | DV35: =IF(OR(DU20="",DU19="",DU19=0),"",DU20/DU19-1) | DW35: =IF(OR(DW20="",DW19=""),"",DW20-DW19) | DX35: =IF(OR(DW20="",DW19="",DW19=0),"",DW20/DW19-1) | DY35: =IF(OR(DY20="",DY19=""),"",DY20-DY19) | DZ35: =IF(OR(DY20="",DY19="",DY19=0),"",DY20/DY19-1) | EA35: =IF(OR(EA20="",EA19=""),"",EA20-EA19) | EB35: =IF(OR(EA20="",EA19="",EA19=0),"",EA20/EA19-1) | EC35: =IF(OR(EC20="",EC19=""),"",EC20-EC19) | ED35: =IF(OR(EC20="",EC19="",EC19=0),"",EC20/EC19-1) | EE35: =IF(OR(EE20="",EE19=""),"",EE20-EE19) | EF35: =IF(OR(EE20="",EE19="",EE19=0),"",EE20/EE19-1) | EG35: =IF(OR(EG20="",EG19=""),"",EG20-EG19) | EH35: =IF(OR(EG20="",EG19="",EG19=0),"",EG20/EG19-1) | EI35: =IF(OR(EI20="",EI19=""),"",EI20-EI19) | EJ35: =IF(OR(EI20="",EI19="",EI19=0),"",EI20/EI19-1) | EK35: =IF(OR(EK20="",EK19=""),"",EK20-EK19) | EL35: =IF(OR(EK20="",EK19="",EK19=0),"",EK20/EK19-1) | EM35: =IF(OR(EM20="",EM19=""),"",EM20-EM19) | EN35: =IF(OR(EM20="",EM19="",EM19=0),"",EM20/EM19-1) | EO35: =IF(OR(EO20="",EO19=""),"",EO20-EO19) | EP35: =IF(OR(EO20="",EO19="",EO19=0),"",EO20/EO19-1) | EQ35: =IF(OR(EQ20="",EQ19=""),"",EQ20-EQ19) | ER35: =IF(OR(EQ20="",EQ19="",EQ19=0),"",EQ20/EQ19-1) | ES35: =IF(OR(ES20="",ES19=""),"",ES20-ES19) | ET35: =IF(OR(ES20="",ES19="",ES19=0),"",ES20/ES19-1) | EU35: =IF(OR(EU20="",EU19=""),"",EU20-EU19) | EV35: =IF(OR(EU20="",EU19="",EU19=0),"",EU20/EU19-1) | EW35: =IF(OR(EW20="",EW19=""),"",EW20-EW19) | EX35: =IF(OR(EW20="",EW19="",EW19=0),"",EW20/EW19-1) | EY35: =IF(OR(EY20="",EY19=""),"",EY20-EY19) | EZ35: =IF(OR(EY20="",EY19="",EY19=0),"",EY20/EY19-1) | FA35: =IF(OR(FA20="",FA19=""),"",FA20-FA19) | FB35: =IF(OR(FA20="",FA19="",FA19=0),"",FA20/FA19-1) | FC35: =IF(OR(FC20="",FC19=""),"",FC20-FC19) | FD35: =IF(OR(FC20="",FC19="",FC19=0),"",FC20/FC19-1) | FE35: =IF(OR(FE20="",FE19=""),"",FE20-FE19) | FF35: =IF(OR(FE20="",FE19="",FE19=0),"",FE20/FE19-1) | FG35: =IF(OR(FG20="",FG19=""),"",FG20-FG19) | FH35: =IF(OR(FG20="",FG19="",FG19=0),"",FG20/FG19-1) | FI35: =IF(OR(FI20="",FI19=""),"",FI20-FI19) | FJ35: =IF(OR(FI20="",FI19="",FI19=0),"",FI20/FI19-1) | FK35: =IF(OR(FK20="",FK19=""),"",FK20-FK19) | FL35: =IF(OR(FK20="",FK19="",FK19=0),"",FK20/FK19-1) | FM35: =IF(OR(FM20="",FM19=""),"",FM20-FM19) | FN35: =IF(OR(FM20="",FM19="",FM19=0),"",FM20/FM19-1) | FO35: =IF(OR(FO20="",FO19=""),"",FO20-FO19) | FP35: =IF(OR(FO20="",FO19="",FO19=0),"",FO20/FO19-1) | FQ35: =IF(OR(FQ20="",FQ19=""),"",FQ20-FQ19) | FR35: =IF(OR(FQ20="",FQ19="",FQ19=0),"",FQ20/FQ19-1) | FS35: =IF(OR(FS20="",FS19=""),"",FS20-FS19) | FT35: =IF(OR(FS20="",FS19="",FS19=0),"",FS20/FS19-1) | FU35: =IF(OR(FU20="",FU19=""),"",FU20-FU19) | FV35: =IF(OR(FU20="",FU19="",FU19=0),"",FU20/FU19-1) | FW35: =IF(OR(FW20="",FW19=""),"",FW20-FW19) | FX35: =IF(OR(FW20="",FW19="",FW19=0),"",FW20/FW19-1) | FY35: =IF(OR(FY20="",FY19=""),"",FY20-FY19) | FZ35: =IF(OR(FY20="",FY19="",FY19=0),"",FY20/FY19-1) | GA35: =IF(OR(GA20="",GA19=""),"",GA20-GA19) | GB35: =IF(OR(GA20="",GA19="",GA19=0),"",GA20/GA19-1) | GC35: =IF(OR(GC20="",GC19=""),"",GC20-GC19) | GD35: =IF(OR(GC20="",GC19="",GC19=0),"",GC20/GC19-1) | GE35: =IF(OR(GE20="",GE19=""),"",GE20-GE19) | GF35: =IF(OR(GE20="",GE19="",GE19=0),"",GE20/GE19-1) | GG35: =IF(OR(GG20="",GG19=""),"",GG20-GG19) | GH35: =IF(OR(GG20="",GG19="",GG19=0),"",GG20/GG19-1) | GI35: =IF(OR(GI20="",GI19=""),"",GI20-GI19) | GJ35: =IF(OR(GI20="",GI19="",GI19=0),"",GI20/GI19-1) | GK35: =IF(OR(GK20="",GK19=""),"",GK20-GK19) | GL35: =IF(OR(GK20="",GK19="",GK19=0),"",GK20/GK19-1) | GM35: =IF(OR(GM20="",GM19=""),"",GM20-GM19) | GN35: =IF(OR(GM20="",GM19="",GM19=0),"",GM20/GM19-1) | GO35: =IF(OR(GO20="",GO19=""),"",GO20-GO19) | GP35: =IF(OR(GO20="",GO19="",GO19=0),"",GO20/GO19-1) | GQ35: =IF(OR(GQ20="",GQ19=""),"",GQ20-GQ19) | GR35: =IF(OR(GQ20="",GQ19="",GQ19=0),"",GQ20/GQ19-1) | GS35: =IF(OR(GS20="",GS19=""),"",GS20-GS19) | GT35: =IF(OR(GS20="",GS19="",GS19=0),"",GS20/GS19-1) | GU35: =IF(OR(GU20="",GU19=""),"",GU20-GU19) | GV35: =IF(OR(GU20="",GU19="",GU19=0),"",GU20/GU19-1) | GW35: =IF(OR(GW20="",GW19=""),"",GW20-GW19) | GX35: =IF(OR(GW20="",GW19="",GW19=0),"",GW20/GW19-1) | GY35: =IF(OR(GY20="",GY19=""),"",GY20-GY19) | GZ35: =IF(OR(GY20="",GY19="",GY19=0),"",GY20/GY19-1)
F36: Активний | H36: =IF(OR('Довідник категорій'!B14="",'Довідник категорій'!B13=""),"",'Довідник категорій'!B14&" ↔ "&'Довідник категорій'!B13) | I36: =IF(OR(I21="",I20=""),"",I21-I20) | J36: =IF(OR(I21="",I20="",I20=0),"",I21/I20-1) | K36: =IF(OR(K21="",K20=""),"",K21-K20) | L36: =IF(OR(K21="",K20="",K20=0),"",K21/K20-1) | M36: =IF(OR(M21="",M20=""),"",M21-M20) | N36: =IF(OR(M21="",M20="",M20=0),"",M21/M20-1) | O36: =IF(OR(O21="",O20=""),"",O21-O20) | P36: =IF(OR(O21="",O20="",O20=0),"",O21/O20-1) | Q36: =IF(OR(Q21="",Q20=""),"",Q21-Q20) | R36: =IF(OR(Q21="",Q20="",Q20=0),"",Q21/Q20-1) | S36: =IF(OR(S21="",S20=""),"",S21-S20) | T36: =IF(OR(S21="",S20="",S20=0),"",S21/S20-1) | U36: =IF(OR(U21="",U20=""),"",U21-U20) | V36: =IF(OR(U21="",U20="",U20=0),"",U21/U20-1) | W36: =IF(OR(W21="",W20=""),"",W21-W20) | X36: =IF(OR(W21="",W20="",W20=0),"",W21/W20-1) | Y36: =IF(OR(Y21="",Y20=""),"",Y21-Y20) | Z36: =IF(OR(Y21="",Y20="",Y20=0),"",Y21/Y20-1) | AA36: =IF(OR(AA21="",AA20=""),"",AA21-AA20) | AB36: =IF(OR(AA21="",AA20="",AA20=0),"",AA21/AA20-1) | AC36: =IF(OR(AC21="",AC20=""),"",AC21-AC20) | AD36: =IF(OR(AC21="",AC20="",AC20=0),"",AC21/AC20-1) | AE36: =IF(OR(AE21="",AE20=""),"",AE21-AE20) | AF36: =IF(OR(AE21="",AE20="",AE20=0),"",AE21/AE20-1) | AG36: =IF(OR(AG21="",AG20=""),"",AG21-AG20) | AH36: =IF(OR(AG21="",AG20="",AG20=0),"",AG21/AG20-1) | AI36: =IF(OR(AI21="",AI20=""),"",AI21-AI20) | AJ36: =IF(OR(AI21="",AI20="",AI20=0),"",AI21/AI20-1) | AK36: =IF(OR(AK21="",AK20=""),"",AK21-AK20) | AL36: =IF(OR(AK21="",AK20="",AK20=0),"",AK21/AK20-1) | AM36: =IF(OR(AM21="",AM20=""),"",AM21-AM20) | AN36: =IF(OR(AM21="",AM20="",AM20=0),"",AM21/AM20-1) | AO36: =IF(OR(AO21="",AO20=""),"",AO21-AO20) | AP36: =IF(OR(AO21="",AO20="",AO20=0),"",AO21/AO20-1) | AQ36: =IF(OR(AQ21="",AQ20=""),"",AQ21-AQ20) | AR36: =IF(OR(AQ21="",AQ20="",AQ20=0),"",AQ21/AQ20-1) | AS36: =IF(OR(AS21="",AS20=""),"",AS21-AS20) | AT36: =IF(OR(AS21="",AS20="",AS20=0),"",AS21/AS20-1) | AU36: =IF(OR(AU21="",AU20=""),"",AU21-AU20) | AV36: =IF(OR(AU21="",AU20="",AU20=0),"",AU21/AU20-1) | AW36: =IF(OR(AW21="",AW20=""),"",AW21-AW20) | AX36: =IF(OR(AW21="",AW20="",AW20=0),"",AW21/AW20-1) | AY36: =IF(OR(AY21="",AY20=""),"",AY21-AY20) | AZ36: =IF(OR(AY21="",AY20="",AY20=0),"",AY21/AY20-1) | BA36: =IF(OR(BA21="",BA20=""),"",BA21-BA20) | BB36: =IF(OR(BA21="",BA20="",BA20=0),"",BA21/BA20-1) | BC36: =IF(OR(BC21="",BC20=""),"",BC21-BC20) | BD36: =IF(OR(BC21="",BC20="",BC20=0),"",BC21/BC20-1) | BE36: =IF(OR(BE21="",BE20=""),"",BE21-BE20) | BF36: =IF(OR(BE21="",BE20="",BE20=0),"",BE21/BE20-1) | BG36: =IF(OR(BG21="",BG20=""),"",BG21-BG20) | BH36: =IF(OR(BG21="",BG20="",BG20=0),"",BG21/BG20-1) | BI36: =IF(OR(BI21="",BI20=""),"",BI21-BI20) | BJ36: =IF(OR(BI21="",BI20="",BI20=0),"",BI21/BI20-1) | BK36: =IF(OR(BK21="",BK20=""),"",BK21-BK20) | BL36: =IF(OR(BK21="",BK20="",BK20=0),"",BK21/BK20-1) | BM36: =IF(OR(BM21="",BM20=""),"",BM21-BM20) | BN36: =IF(OR(BM21="",BM20="",BM20=0),"",BM21/BM20-1) | BO36: =IF(OR(BO21="",BO20=""),"",BO21-BO20) | BP36: =IF(OR(BO21="",BO20="",BO20=0),"",BO21/BO20-1) | BQ36: =IF(OR(BQ21="",BQ20=""),"",BQ21-BQ20) | BR36: =IF(OR(BQ21="",BQ20="",BQ20=0),"",BQ21/BQ20-1) | BS36: =IF(OR(BS21="",BS20=""),"",BS21-BS20) | BT36: =IF(OR(BS21="",BS20="",BS20=0),"",BS21/BS20-1) | BU36: =IF(OR(BU21="",BU20=""),"",BU21-BU20) | BV36: =IF(OR(BU21="",BU20="",BU20=0),"",BU21/BU20-1) | BW36: =IF(OR(BW21="",BW20=""),"",BW21-BW20) | BX36: =IF(OR(BW21="",BW20="",BW20=0),"",BW21/BW20-1) | BY36: =IF(OR(BY21="",BY20=""),"",BY21-BY20) | BZ36: =IF(OR(BY21="",BY20="",BY20=0),"",BY21/BY20-1) | CA36: =IF(OR(CA21="",CA20=""),"",CA21-CA20) | CB36: =IF(OR(CA21="",CA20="",CA20=0),"",CA21/CA20-1) | CC36: =IF(OR(CC21="",CC20=""),"",CC21-CC20) | CD36: =IF(OR(CC21="",CC20="",CC20=0),"",CC21/CC20-1) | CE36: =IF(OR(CE21="",CE20=""),"",CE21-CE20) | CF36: =IF(OR(CE21="",CE20="",CE20=0),"",CE21/CE20-1) | CG36: =IF(OR(CG21="",CG20=""),"",CG21-CG20) | CH36: =IF(OR(CG21="",CG20="",CG20=0),"",CG21/CG20-1) | CI36: =IF(OR(CI21="",CI20=""),"",CI21-CI20) | CJ36: =IF(OR(CI21="",CI20="",CI20=0),"",CI21/CI20-1) | CK36: =IF(OR(CK21="",CK20=""),"",CK21-CK20) | CL36: =IF(OR(CK21="",CK20="",CK20=0),"",CK21/CK20-1) | CM36: =IF(OR(CM21="",CM20=""),"",CM21-CM20) | CN36: =IF(OR(CM21="",CM20="",CM20=0),"",CM21/CM20-1) | CO36: =IF(OR(CO21="",CO20=""),"",CO21-CO20) | CP36: =IF(OR(CO21="",CO20="",CO20=0),"",CO21/CO20-1) | CQ36: =IF(OR(CQ21="",CQ20=""),"",CQ21-CQ20) | CR36: =IF(OR(CQ21="",CQ20="",CQ20=0),"",CQ21/CQ20-1) | CS36: =IF(OR(CS21="",CS20=""),"",CS21-CS20) | CT36: =IF(OR(CS21="",CS20="",CS20=0),"",CS21/CS20-1) | CU36: =IF(OR(CU21="",CU20=""),"",CU21-CU20) | CV36: =IF(OR(CU21="",CU20="",CU20=0),"",CU21/CU20-1) | CW36: =IF(OR(CW21="",CW20=""),"",CW21-CW20) | CX36: =IF(OR(CW21="",CW20="",CW20=0),"",CW21/CW20-1) | CY36: =IF(OR(CY21="",CY20=""),"",CY21-CY20) | CZ36: =IF(OR(CY21="",CY20="",CY20=0),"",CY21/CY20-1) | DA36: =IF(OR(DA21="",DA20=""),"",DA21-DA20) | DB36: =IF(OR(DA21="",DA20="",DA20=0),"",DA21/DA20-1) | DC36: =IF(OR(DC21="",DC20=""),"",DC21-DC20) | DD36: =IF(OR(DC21="",DC20="",DC20=0),"",DC21/DC20-1) | DE36: =IF(OR(DE21="",DE20=""),"",DE21-DE20) | DF36: =IF(OR(DE21="",DE20="",DE20=0),"",DE21/DE20-1) | DG36: =IF(OR(DG21="",DG20=""),"",DG21-DG20) | DH36: =IF(OR(DG21="",DG20="",DG20=0),"",DG21/DG20-1) | DI36: =IF(OR(DI21="",DI20=""),"",DI21-DI20) | DJ36: =IF(OR(DI21="",DI20="",DI20=0),"",DI21/DI20-1) | DK36: =IF(OR(DK21="",DK20=""),"",DK21-DK20) | DL36: =IF(OR(DK21="",DK20="",DK20=0),"",DK21/DK20-1) | DM36: =IF(OR(DM21="",DM20=""),"",DM21-DM20) | DN36: =IF(OR(DM21="",DM20="",DM20=0),"",DM21/DM20-1) | DO36: =IF(OR(DO21="",DO20=""),"",DO21-DO20) | DP36: =IF(OR(DO21="",DO20="",DO20=0),"",DO21/DO20-1) | DQ36: =IF(OR(DQ21="",DQ20=""),"",DQ21-DQ20) | DR36: =IF(OR(DQ21="",DQ20="",DQ20=0),"",DQ21/DQ20-1) | DS36: =IF(OR(DS21="",DS20=""),"",DS21-DS20) | DT36: =IF(OR(DS21="",DS20="",DS20=0),"",DS21/DS20-1) | DU36: =IF(OR(DU21="",DU20=""),"",DU21-DU20) | DV36: =IF(OR(DU21="",DU20="",DU20=0),"",DU21/DU20-1) | DW36: =IF(OR(DW21="",DW20=""),"",DW21-DW20) | DX36: =IF(OR(DW21="",DW20="",DW20=0),"",DW21/DW20-1) | DY36: =IF(OR(DY21="",DY20=""),"",DY21-DY20) | DZ36: =IF(OR(DY21="",DY20="",DY20=0),"",DY21/DY20-1) | EA36: =IF(OR(EA21="",EA20=""),"",EA21-EA20) | EB36: =IF(OR(EA21="",EA20="",EA20=0),"",EA21/EA20-1) | EC36: =IF(OR(EC21="",EC20=""),"",EC21-EC20) | ED36: =IF(OR(EC21="",EC20="",EC20=0),"",EC21/EC20-1) | EE36: =IF(OR(EE21="",EE20=""),"",EE21-EE20) | EF36: =IF(OR(EE21="",EE20="",EE20=0),"",EE21/EE20-1) | EG36: =IF(OR(EG21="",EG20=""),"",EG21-EG20) | EH36: =IF(OR(EG21="",EG20="",EG20=0),"",EG21/EG20-1) | EI36: =IF(OR(EI21="",EI20=""),"",EI21-EI20) | EJ36: =IF(OR(EI21="",EI20="",EI20=0),"",EI21/EI20-1) | EK36: =IF(OR(EK21="",EK20=""),"",EK21-EK20) | EL36: =IF(OR(EK21="",EK20="",EK20=0),"",EK21/EK20-1) | EM36: =IF(OR(EM21="",EM20=""),"",EM21-EM20) | EN36: =IF(OR(EM21="",EM20="",EM20=0),"",EM21/EM20-1) | EO36: =IF(OR(EO21="",EO20=""),"",EO21-EO20) | EP36: =IF(OR(EO21="",EO20="",EO20=0),"",EO21/EO20-1) | EQ36: =IF(OR(EQ21="",EQ20=""),"",EQ21-EQ20) | ER36: =IF(OR(EQ21="",EQ20="",EQ20=0),"",EQ21/EQ20-1) | ES36: =IF(OR(ES21="",ES20=""),"",ES21-ES20) | ET36: =IF(OR(ES21="",ES20="",ES20=0),"",ES21/ES20-1) | EU36: =IF(OR(EU21="",EU20=""),"",EU21-EU20) | EV36: =IF(OR(EU21="",EU20="",EU20=0),"",EU21/EU20-1) | EW36: =IF(OR(EW21="",EW20=""),"",EW21-EW20) | EX36: =IF(OR(EW21="",EW20="",EW20=0),"",EW21/EW20-1) | EY36: =IF(OR(EY21="",EY20=""),"",EY21-EY20) | EZ36: =IF(OR(EY21="",EY20="",EY20=0),"",EY21/EY20-1) | FA36: =IF(OR(FA21="",FA20=""),"",FA21-FA20) | FB36: =IF(OR(FA21="",FA20="",FA20=0),"",FA21/FA20-1) | FC36: =IF(OR(FC21="",FC20=""),"",FC21-FC20) | FD36: =IF(OR(FC21="",FC20="",FC20=0),"",FC21/FC20-1) | FE36: =IF(OR(FE21="",FE20=""),"",FE21-FE20) | FF36: =IF(OR(FE21="",FE20="",FE20=0),"",FE21/FE20-1) | FG36: =IF(OR(FG21="",FG20=""),"",FG21-FG20) | FH36: =IF(OR(FG21="",FG20="",FG20=0),"",FG21/FG20-1) | FI36: =IF(OR(FI21="",FI20=""),"",FI21-FI20) | FJ36: =IF(OR(FI21="",FI20="",FI20=0),"",FI21/FI20-1) | FK36: =IF(OR(FK21="",FK20=""),"",FK21-FK20) | FL36: =IF(OR(FK21="",FK20="",FK20=0),"",FK21/FK20-1) | FM36: =IF(OR(FM21="",FM20=""),"",FM21-FM20) | FN36: =IF(OR(FM21="",FM20="",FM20=0),"",FM21/FM20-1) | FO36: =IF(OR(FO21="",FO20=""),"",FO21-FO20) | FP36: =IF(OR(FO21="",FO20="",FO20=0),"",FO21/FO20-1) | FQ36: =IF(OR(FQ21="",FQ20=""),"",FQ21-FQ20) | FR36: =IF(OR(FQ21="",FQ20="",FQ20=0),"",FQ21/FQ20-1) | FS36: =IF(OR(FS21="",FS20=""),"",FS21-FS20) | FT36: =IF(OR(FS21="",FS20="",FS20=0),"",FS21/FS20-1) | FU36: =IF(OR(FU21="",FU20=""),"",FU21-FU20) | FV36: =IF(OR(FU21="",FU20="",FU20=0),"",FU21/FU20-1) | FW36: =IF(OR(FW21="",FW20=""),"",FW21-FW20) | FX36: =IF(OR(FW21="",FW20="",FW20=0),"",FW21/FW20-1) | FY36: =IF(OR(FY21="",FY20=""),"",FY21-FY20) | FZ36: =IF(OR(FY21="",FY20="",FY20=0),"",FY21/FY20-1) | GA36: =IF(OR(GA21="",GA20=""),"",GA21-GA20) | GB36: =IF(OR(GA21="",GA20="",GA20=0),"",GA21/GA20-1) | GC36: =IF(OR(GC21="",GC20=""),"",GC21-GC20) | GD36: =IF(OR(GC21="",GC20="",GC20=0),"",GC21/GC20-1) | GE36: =IF(OR(GE21="",GE20=""),"",GE21-GE20) | GF36: =IF(OR(GE21="",GE20="",GE20=0),"",GE21/GE20-1) | GG36: =IF(OR(GG21="",GG20=""),"",GG21-GG20) | GH36: =IF(OR(GG21="",GG20="",GG20=0),"",GG21/GG20-1) | GI36: =IF(OR(GI21="",GI20=""),"",GI21-GI20) | GJ36: =IF(OR(GI21="",GI20="",GI20=0),"",GI21/GI20-1) | GK36: =IF(OR(GK21="",GK20=""),"",GK21-GK20) | GL36: =IF(OR(GK21="",GK20="",GK20=0),"",GK21/GK20-1) | GM36: =IF(OR(GM21="",GM20=""),"",GM21-GM20) | GN36: =IF(OR(GM21="",GM20="",GM20=0),"",GM21/GM20-1) | GO36: =IF(OR(GO21="",GO20=""),"",GO21-GO20) | GP36: =IF(OR(GO21="",GO20="",GO20=0),"",GO21/GO20-1) | GQ36: =IF(OR(GQ21="",GQ20=""),"",GQ21-GQ20) | GR36: =IF(OR(GQ21="",GQ20="",GQ20=0),"",GQ21/GQ20-1) | GS36: =IF(OR(GS21="",GS20=""),"",GS21-GS20) | GT36: =IF(OR(GS21="",GS20="",GS20=0),"",GS21/GS20-1) | GU36: =IF(OR(GU21="",GU20=""),"",GU21-GU20) | GV36: =IF(OR(GU21="",GU20="",GU20=0),"",GU21/GU20-1) | GW36: =IF(OR(GW21="",GW20=""),"",GW21-GW20) | GX36: =IF(OR(GW21="",GW20="",GW20=0),"",GW21/GW20-1) | GY36: =IF(OR(GY21="",GY20=""),"",GY21-GY20) | GZ36: =IF(OR(GY21="",GY20="",GY20=0),"",GY21/GY20-1)
